Workbook
Name Slicer_Country: #N/A
Name Slicer_Country1: #N/A
Name Slicer_Country11: #N/A
Name Slicer_Country2: #N/A
Name Slicer_Country3: #N/A
Name Slicer_Distributor_Name: #N/A
Name Slicer_Distributor_Name1: #N/A
Name Slicer_Group: #N/A
Name Slicer_Group1: #N/A
Name Slicer_Manager: #N/A
Name Slicer_Manager1: #N/A
Name Slicer_Manager2: #N/A
Name Slicer_Manager3: #N/A
Name Slicer_Manager4: #N/A
Name Slicer_Product_Name: #N/A
Name Slicer_Product_Name1: #N/A
Name Slicer_Region: #N/A
Name Slicer_Region1: #N/A
Name Slicer_Region2: #N/A
Name Slicer_Region3: #N/A
Name Slicer_Region31: #N/A

Sheet Wholeseller(Direct Party)
A2: Party Name | B2: Product | C2: Quatity | D2: S.P | E2: Value
A3: Shani Distributor , Khanewal | B3: GTN Cream | C3: 100 | D3: =(8026+9180)/C3 -> 172.06 | E3: =C3*D3 -> 17206
A4: Shani Distributor , Khanewal | B4: Mediscon Syp | C4: 200 | D4: =20020/C4 -> 100.1 | E4: =C4*D4 -> 20020
A5: Naveed Pharma, Haripur | B5: Novagen 1g | C5: 1040 | D5: =98280/1040 -> 94.5 | E5: =C5*D5 -> 98280
A6: Mother Care, Lahore | B6: G-sef 250mg | C6: 28 | D6: 240 | E6: =C6*D6 -> 6720
A7: Blue Ocean, Lahore | B7: GTN Cream | C7: 200 | D7: =32760/C7 -> 163.8 | E7: =C7*D7 -> 32760
A8: Blue Ocean, Lahore | B8: Mediscon Syp | C8: 50 | D8: =5005/C8 -> 100.1 | E8: =C8*D8 -> 5005
A9: ZA Traders, Gujranwala | B9: Mediscon Syp | C9: 300 | D9: 100.1 | E9: =C9*D9 -> 30030
A10: ZA Traders, Gujranwala | B10: Novagen 500mg | C10: 60 | D10: =4800/C10 -> 80 | E10: =C10*D10 -> 4800
A11: ZA Traders, Gujranwala | B11: Medizek Injection 40mg | C11: 50 | D11: =6000/C11 -> 120 | E11: =C11*D11 -> 6000
A12: Total Direct Sale : | E12: =SUM(E3:E11) -> 220821
A13: Total National Sales : | E13: =GETPIVOTDATA("Sales Value",'Combine Sales Distributor Vise'!$A$3) -> 10666150
A14: Total Sales : | E14: =SUM(E12:E13) -> 10886972

Sheet Trade Group LMTD
A1: Group | B1: Medicronis
A2: Category | B2: (All)
A4: Distributor Name | B4: City | C4: 'Yesterday Sale Value | D4: Today Sales Value | E4: 'Difference | F4: 'Target Value | G4: 'Average Target Achv. % | H4: 'LMTD Sales Value | I4: Sum of LMTD Difference2 | J4: Average of LMTD %age
A5: AL-HARAM ENTERPRISES, Kohat | B5: Kohat | C5: 215077 | D5: 215077 | E5: 0 | F5: 657451.31 | G5: 0.41261785 | H5: 327300 | I5: -112223 | J5: -0.31704492
A6: MEHRAN TRADERS, Mardan | B6: Mardan | C6: 55195 | D6: 92799 | E6: 37604 | F6: 550588.18 | G6: 0.2186995 | H6: 63268 | I6: 29531 | J6: 1.3391629
A7: Noor Khan Corporation, Mingora | B7: Mingora | C7: 443672 | D7: 443672 | E7: 0 | F7: 1022820.3 | G7: 0.32422513 | H7: 592501 | I7: -148829 | J7: 0.12924969
A8: Umar Medicine Distribution, Swabi | B8: Swabi | C8: 49790 | D8: 49790 | E8: 0 | F8: 471286.46 | G8: 0.11001177 | H8: 91713 | I8: -41923 | J8: 0.19094896
A9: NEW TAWAKAL ENTERPRISES, ABBT | B9: Abbottabad | C9: 137679 | D9: 150629 | E9: 12950 | F9: 307314 | G9: 0.42147604 | H9: 227423 | I9: -76794 | J9: -0.17224164
A10: M&C Distributor, RWP | B10: Rwp | C10: 79420 | D10: 85890 | E10: 6470 | F10: 360810.68 | G10: 0.13216203 | H10: 77170 | I10: 8720 | J10: 15.521236
A11: MASHAL ENTERPRISES, Bajaur | B11: Bajaur | C11: 253240 | D11: 253240 | E11: 0 | F11: 607425.03 | G11: 0.24195437 | H11: 253005 | I11: 235 | J11: -0.17876801
A12: Wellness Traders, Bhatkela | B12: Bhatkela | C12: 0 | D12: 0 | E12: 0 | F12: 538778.64 | G12: 0 | H12: 7335 | I12: -7335 | J12: -1
A13: Al Makkah Trading Co, Buner | B13: Buner | C13: 295389 | D13: 295389 | E13: 0 | F13: 547999.2 | G13: 0.31384257 | H13: 210956 | I13: 84433 | J13: 0.29932397
A14: CHAUDHARY MEDICINE COMPANY, MWL | B14: Mianwali | C14: 232520 | D14: 277800 | E14: 45280 | F14: 648479.94 | G14: 0.37792619 | H14: 247176 | I14: 30624 | J14: 1.8562365
A15: Evergreen Enterprises, D.I.Khan | B15: D.I.Khan | C15: 450045 | D15: 450045 | E15: 0 | F15: 587264.6 | G15: 0.68721576 | H15: 308400 | I15: 141645 | J15: 1.6538016
A16: NEW SHAHZAIB PHARMACY, Okara | B16: Okara | C16: 268180 | D16: 268180 | E16: 0 | F16: 509925 | G16: 0.50262577 | H16: 298145 | I16: -29965 | J16: -0.092081544
... A30: AQ DISTRIBUTOR,Sargodha | B30: Sargodha | C30: 150784 | D30: 150784 | E30: 0 | F30: 549072.96 | G30: 0.2268459 | H30: 115770 | I30: 35014 | J30: 0.45525289
A31: REHMAN DRUG AGENCY, SKT | B31: Sialkot | C31: 0 | D31: 0 | E31: 0 | F31: 438568.44 | G31: 0 | H31: 0 | I31: 0 | J31: --
A32: Zavion Marketing, Jhang | B32: Jhang | C32: 85719 | D32: 85719 | E32: 0 | F32: 516143.63 | G32: 0.18709078 | H32: 83576 | I32: 2143 | J32: 0.18388287
A33: LIFE CARE, Gujrat | B33: Gujrat | C33: 268476 | D33: 268476 | E33: 0 | F33: 544975.76 | G33: 0.26488193 | H33: 273859 | I33: -5383 | J33: -0.008617079
A34: Pharmarite Distributor, Jehlum | B34: Jhelum | C34: 203040 | D34: 203040 | E34: 0 | F34: 495090.6 | G34: 0.37750204 | H34: 236215 | I34: -33175 | J34: -0.27984604
A35: RELIABLE MEDICOS MIRPURKHAS, MPK | B35: Mirpur Khas | C35: 75161 | D35: 75161 | E35: 0 | F35: 515964 | G35: 0.092540488 | H35: 86415 | I35: -11254 | J35: 0.12012307
A36: ZAFAR & SONS PHARMA, NWS | B36: Nawabshah | C36: 278716 | D36: 278716 | E36: 0 | F36: 484784.52 | G36: 0.61447969 | H36: 200412 | I36: 78304 | J36: 1.9245796
A37: Al Rehman Medical Sources, Lahore | B37: Lahore | C37: 221547 | D37: 221547 | E37: 0 | F37: 1120172.8 | G37: 0.21616425 | H37: 542503 | I37: -320956 | J37: -3.2569572
A38: THE HAMZA TRADERS, Kasur | B38: Kasur | C38: 212565 | D38: 212565 | E38: 0 | F38: 461513.18 | G38: 0.31992826 | H38: 148475 | I38: 64090 | J38: 0.80930266
A39: HAJI NIZAM UD DIN & SONS, Quetta | B39: Quetta | C39: 1736659 | D39: 1744669 | E39: 8010 | F39: 2546675.5 | G39: 0.47193596 | H39: 1635580 | I39: 109089 | J39: 0.45419966
A40: Ayyan Medicine Company, SKP | B40: SKP | C40: 15810 | D40: 15810 | E40: 0 | F40: 454753.17 | G40: 0.028398724 | H40: 147965 | I40: -132155 | J40: -0.151344
A41: Lal Drug Agency, Sibbi | B41: Sibbi | C41: 13760 | D41: 43386 | E41: 29626 | F41: 0 | G41: -- | H41: 44129 | I41: -743 | J41: -0.27429243
A42: SR Traders, Charsadda | B42: Charsadda | C42: 0 | D42: 0 | E42: 0 | F42: 460276.46 | G42: 0 | H42: 0 | I42: 0 | J42: --
A43: Medicamp Distributor, PSW | B43: Peshawar | C43: 9270 | D43: 9270 | E43: 0 | F43: 864245.14 | G43: 0.0060763767 | H43: 35528 | I43: -26258 | J43: -0.755959
A44: Naveed Pharma, Haripur | B44: Haripur | C44: 0 | D44: 0 | E44: 0 | F44: 0 | G44: -- | H44: 429240 | I44: -429240 | J44: -1
A45: AIM Pharma, HYD | B45: Hyderabad | C45: 207317 | D45: 241236 | E45: 33919 | F45: 0 | G45: -- | H45: 109991 | I45: 131245 | J45: 1.9008303
A46: Hamed Pharma, Bannu | B46: Bannu | C46: 209920 | D46: 271000 | E46: 61080 | F46: 421151.84 | G46: 0.26865706 | H46: 342383 | I46: -71383 | J46: 0.032243045
A47: Kamal Medicine Company, Timergara | B47: Timergara | C47: 141683 | D47: 178639 | E47: 36956 | F47: 824606.95 | G47: 0.22587474 | H47: 156395 | I47: 15809 | J47: 3.0827919
A48: Faiz Enterprises, Rajanpur | B48: Rajan pur | C48: 262896 | D48: 272806 | E48: 9910 | F48: 553868.01 | G48: 0.7019154 | H48: 94208 | I48: 178598 | J48: 1.7665012
A49: Hashmani Health Care | B49: Karachi | C49: 308722 | D49: 341592 | E49: 32870 | F49: 0 | G49: -- | H49: 100796 | I49: 240796 | J49: 2.0856487
A50: Bukhari Medicine Company, MBD | B50: MBD | C50: 79102 | D50: 91845 | E50: 12743 | F50: 501874.53 | G50: 0.17632605 | H50: 89472 | I50: 2373 | J50: 1.3605088
A51: Basher Pharma, Gujranwala | B51: Gujranwala | C51: 145567 | D51: 145567 | E51: 0 | F51: 452847.6 | G51: 0.32680102 | H51: 0 | I51: 145567 | J51: --
A52: Ruman Medicine, RYK | B52: R.Y.Khan | C52: 50615 | D52: 50615 | E52: 0 | F52: 230523 | G52: 0.19504024 | H52: 18763 | I52: 31852 | J52: 6.1550139
A53: Global Pharma, SKP | B53: SKP | C53: 10500 | D53: 13650 | E53: 0 | F53: 0 | G53: -- | H53: 0 | I53: 13650 | J53: --
A54: Grand Total | C54: 8912263 | D54: 9261745 | E54: 346332 | F54: 26200092 | G54: 0.26415309 | H54: 9319388 | I54: -64078 | J54: 0.56354665

Sheet Transformer Group LMTD
A1: Group | B1: Transformer
A3: Distributor Name | B3: City | C3: 'Yesterday Sale Value | D3: Today Sales Value | E3: 'Difference | F3: 'Target Value | G3: 'Average Target Achv. % | H3: 'LMTD Sales Value | I3: Sum of LMTD Difference2 | J3: Average of LMTD %age
A4: AL-HARAM ENTERPRISES, Kohat | B4: Kohat | C4: 77562.5 | D4: 77562.5 | E4: 0 | F4: 598302.2 | G4: 0.08061771 | H4: 154700 | I4: -77137.5 | J4: -0.49269603
A5: MEHRAN TRADERS, Mardan | B5: Mardan | C5: -1870 | D5: -1700 | E5: 170 | F5: 0 | G5: -- | H5: 0 | I5: -1700 | J5: --
A6: Noor Khan Corporation, Mingora | B6: Mingora | C6: 0 | D6: 99195 | E6: 99195 | F6: 268175 | G6: 0.44452381 | H6: 1317.5 | I6: 97877.5 | J6: 7.125
A7: Umar Medicine Distribution, Swabi | B7: Swabi | C7: 6120 | D7: 6120 | E7: 0 | F7: 0 | G7: -- | H7: 0 | I7: 6120 | J7: --
A8: NEW TAWAKAL ENTERPRISES, ABBT | B8: Abbottabad | C8: 0 | D8: 0 | E8: 0 | F8: 0 | G8: -- | H8: 0 | I8: 0 | J8: --
A9: M&C Distributor, RWP | B9: Rwp | C9: 0 | D9: 0 | E9: 0 | F9: 0 | G9: -- | H9: 0 | I9: 0 | J9: --
A10: MASHAL ENTERPRISES, Bajaur | B10: Bajaur | C10: 0 | D10: 0 | E10: 0 | F10: 0 | G10: -- | H10: 0 | I10: 0 | J10: --
A11: Wellness Traders, Bhatkela | B11: Bhatkela | C11: 0 | D11: 0 | E11: 0 | F11: 0 | G11: -- | H11: 374 | I11: -374 | J11: -1
A12: Al Makkah Trading Co, Buner | B12: Buner | C12: 0 | D12: 0 | E12: 0 | F12: 0 | G12: -- | H12: 0 | I12: 0 | J12: --
A13: CHAUDHARY MEDICINE COMPANY, MWL | B13: Mianwali | C13: 1016 | D13: 1016 | E13: 0 | F13: 0 | G13: -- | H13: 680 | I13: 336 | J13: 0
A14: Evergreen Enterprises, D.I.Khan | B14: D.I.Khan | C14: 250125.25 | D14: 250125.25 | E14: 0 | F14: 868227.27 | G14: 0.45909533 | H14: 292570 | I14: -42444.75 | J14: -0.22030276
A15: NEW SHAHZAIB PHARMACY, Okara | B15: Okara | C15: 5364 | D15: 5364 | E15: 0 | F15: 0 | G15: -- | H15: 3366 | I15: 1998 | J15: 0.22222222
A16: N&G Enterprises, SWL | B16: SWL | C16: 0 | D16: 0 | E16: 0 | F16: 0 | G16: -- | H16: 0 | I16: 0 | J16: --
A17: AL SHIFA DISTRIBUTOR, Jampur | B17: Jampur | C17: -37315 | D17: -37315 | E17: 0 | F17: 0 | G17: -- | H17: 52402.59 | I17: -89717.59 | J17: -1.4166667
A18: AL Harmain Distribution, D.G Khan | B18: D.G.Khan | C18: 58713.75 | D18: 58713.75 | E18: 0 | F18: 0 | G18: -- | H18: 92259 | I18: -33545.25 | J18: -0.33945869
A19: AYAN PHARMA, Taunsa | B19: Taunsa | C19: 109918 | D19: 109918 | E19: 0 | F19: 0 | G19: -- | H19: 49727.5 | I19: 60190.5 | J19: 1.080632
A20: PUNJAB MEDICINE COMPANY, Layyah | B20: Layyah | C20: 0 | D20: 0 | E20: 0 | F20: 0 | G20: -- | H20: -1360 | I20: 1360 | J20: -1
A21: Wellcome Pharma Distributor, Ali Pur | B21: Ali Pur | C21: 1870 | D21: 2618 | E21: 748 | F21: 0 | G21: -- | H21: 748 | I21: 1870 | J21: 2.5
A22: MRWA ENTERPRISES, BWP | B22: Bahawalpur | C22: 0 | D22: 0 | E22: 0 | F22: 0 | G22: -- | H22: 1700 | I22: -1700 | J22: -1
A23: ALI DISTRIBUTOR, RYK | B23: R.Y.Khan | C23: 35851 | D23: 35851 | E23: 0 | F23: 355765 | G23: 0.13714286 | H23: 175879.5 | I23: -140028.5 | J23: -0.67985657
A24: Royal Medicine Company, Sadiqabad | B24: Sadiq Abad | C24: 0 | D24: 0 | E24: 0 | F24: 0 | G24: -- | H24: 0 | I24: 0 | J24: --
A25: SHAFIQ ENTERPRISES, Khanpur | B25: Khanpur | C25: -7714 | D25: -7714 | E25: 0 | F25: 0 | G25: -- | H25: 12219.5 | I25: -19933.5 | J25: -1.4464286
A26: Hamza Medicine Company, TTS | B26: TTS | C26: 0 | D26: 0 | E26: 0 | F26: 0 | G26: -- | H26: 0 | I26: 0 | J26: --
A27: AMT International, FSD | B27: Faisalabad | C27: 340 | D27: 340 | E27: 0 | F27: 571775.5 | G27: 0.0022675737 | H27: 0 | I27: 340 | J27: --
A28: Chishti Pharma, Multan | B28: Multan | C28: 166680.75 | D28: 166680.75 | E28: 0 | F28: 615570 | G28: 0.4889881 | H28: 5372 | I28: 161308.75 | J28: 0.66666667
A29: AQ DISTRIBUTOR,Sargodha | B29: Sargodha | C29: 1309 | D29: 1309 | E29: 0 | F29: 0 | G29: -- | H29: 561 | I29: 748 | J29: 1.3333333
A30: REHMAN DRUG AGENCY, SKT | B30: Sialkot | C30: 0 | D30: 0 | E30: 0 | F30: 0 | G30: -- | H30: 0 | I30: 0 | J30: --
A31: Zavion Marketing, Jhang | B31: Jhang | C31: 0 | D31: 0 | E31: 0 | F31: 0 | G31: -- | H31: 0 | I31: 0 | J31: --
A32: LIFE CARE, Gujrat | B32: Gujrat | C32: 0 | D32: 0 | E32: 0 | F32: 0 | G32: -- | H32: 2040 | I32: -2040 | J32: -1
A33: Pharmarite Distributor, Jehlum | B33: Jhelum | C33: -178.5 | D33: -178.5 | E33: 0 | F33: 0 | G33: -- | H33: 1309 | I33: -1487.5 | J33: -0.71428571
A34: RELIABLE MEDICOS MIRPURKHAS, MPK | B34: Mirpur Khas | C34: 0 | D34: 0 | E34: 0 | F34: 0 | G34: -- | H34: 0 | I34: 0 | J34: --
A35: ZAFAR & SONS PHARMA, NWS | B35: Nawabshah | C35: 1870 | D35: 1870 | E35: 0 | F35: 0 | G35: -- | H35: 1870 | I35: 0 | J35: 0
A36: Al Rehman Medical Sources, Lahore | B36: Lahore | C36: 187 | D36: 187 | E36: 0 | F36: 0 | G36: -- | H36: 7106 | I36: -6919 | J36: -0.97368421
A37: THE HAMZA TRADERS, Kasur | B37: Kasur | C37: 0 | D37: 0 | E37: 0 | F37: 412058.75 | G37: 0 | H37: 0 | I37: 0 | J37: --
A38: HAJI NIZAM UD DIN & SONS, Quetta | B38: Quetta | C38: 216654 | D38: 216399 | E38: -255 | F38: 0 | G38: -- | H38: 160180 | I38: 56219 | J38: 0.34011905
A39: Ayyan Medicine Company, SKP | B39: SKP | C39: 0 | D39: 0 | E39: 0 | F39: 0 | G39: -- | H39: 4114 | I39: -4114 | J39: -1
A40: Lal Drug Agency, Sibbi | B40: Sibbi | C40: 0 | D40: 0 | E40: 0 | F40: 0 | G40: -- | H40: 0 | I40: 0 | J40: --
A41: SR Traders, Charsadda | B41: Charsadda | C41: 0 | D41: 0 | E41: 0 | F41: 0 | G41: -- | H41: 0 | I41: 0 | J41: --
A42: Medicamp Distributor, PSW | B42: Peshawar | C42: -10200 | D42: -10200 | E42: 0 | F42: 1560903.4 | G42: -0.0075 | H42: 10200 | I42: -20400 | J42: -2
A43: Naveed Pharma, Haripur | B43: Haripur | C43: 0 | D43: 0 | E43: 0 | F43: 0 | G43: -- | H43: 0 | I43: 0 | J43: --
A44: AIM Pharma, HYD | B44: Hyderabad | C44: 10244 | D44: 21634 | E44: 11390 | F44: 0 | G44: -- | H44: 15921 | I44: 5713 | J44: -0.95454545
A45: Hamed Pharma, Bannu | B45: Bannu | C45: 85310.25 | D45: 190072.75 | E45: 104762.5 | F45: 753000.45 | G45: 0.32486194 | H45: 305096.5 | I45: -115023.75 | J45: -0.80674008
A46: Kamal Medicine Company, Timergara | B46: Timergara | C46: 935 | D46: 1870 | E46: 935 | F46: 255010 | G46: 0.011904762 | H46: 0 | I46: 1870 | J46: --
A47: Faiz Enterprises, Rajanpur | B47: Rajan pur | C47: 0 | D47: 0 | E47: 0 | F47: 0 | G47: -- | H47: 5474 | I47: -5474 | J47: -1
A48: Hashmani Health Care | B48: Karachi | C48: 4301 | D48: 5423 | E48: 1122 | F48: 0 | G48: -- | H48: 1870 | I48: 3553 | J48: 1.9
A49: Bukhari Medicine Company, MBD | B49: MBD | C49: 0 | D49: 374 | E49: 374 | F49: 293847.5 | G49: 0.0035714286 | H49: 3740 | I49: -3366 | J49: -0.9
A50: Basher Pharma, Gujranwala | B50: Gujranwala | C50: 0 | D50: 0 | E50: 0 | F50: 0 | G50: -- | H50: 0 | I50: 0 | J50: --
A51: Ruman Medicine, RYK | B51: R.Y.Khan | C51: 208870 | D51: 208870 | E51: 0 | F51: 355765 | G51: 0.40285714 | H51: 0 | I51: 208870 | J51: --
A52: Global Pharma, SKP | B52: SKP | C52: 0 | D52: 0 | E52: 0 | F52: 0 | G52: -- | H52: 0 | I52: 0 | J52: --
A53: Grand Total | C53: 1185964 | D53: 1404405.5 | E53: 218441.5 | F53: 6908400 | G53: 0.20724961 | H53: 1361437.1 | I53: 42968.41 | J53: 0.050555099

Sheet Combine Sales Distributor Vise
A1: Category | B1: (All)
A3: Sum of Sales Value | C3: Group
A4: Distributor Name | B4: City | C4: Medicronis | D4: Transformer | E4: Grand Total
A5: AL-HARAM ENTERPRISES, Kohat | B5: Kohat | C5: 215077 | D5: 77562.5 | E5: 292639.5
A6: MEHRAN TRADERS, Mardan | B6: Mardan | C6: 92799 | D6: -1700 | E6: 91099
A7: Noor Khan Corporation, Mingora | B7: Mingora | C7: 443672 | D7: 99195 | E7: 542867
A8: Umar Medicine Distribution, Swabi | B8: Swabi | C8: 49790 | D8: 6120 | E8: 55910
A9: NEW TAWAKAL ENTERPRISES, ABBT | B9: Abbottabad | C9: 150629 | D9: 0 | E9: 150629
A10: M&C Distributor, RWP | B10: Rwp | C10: 85890 | D10: 0 | E10: 85890
A11: MASHAL ENTERPRISES, Bajaur | B11: Bajaur | C11: 253240 | D11: 0 | E11: 253240
A12: Wellness Traders, Bhatkela | B12: Bhatkela | C12: 0 | D12: 0 | E12: 0
A13: Al Makkah Trading Co, Buner | B13: Buner | C13: 295389 | D13: 0 | E13: 295389
A14: CHAUDHARY MEDICINE COMPANY, MWL | B14: Mianwali | C14: 277800 | D14: 1016 | E14: 278816
A15: Evergreen Enterprises, D.I.Khan | B15: D.I.Khan | C15: 450045 | D15: 250125.25 | E15: 700170.25
A16: NEW SHAHZAIB PHARMACY, Okara | B16: Okara | C16: 268180 | D16: 5364 | E16: 273544
... A53: Global Pharma, SKP | B53: SKP | C53: 13650 | D53: 0 | E53: 13650
A54: Grand Total | C54: 9261745 | D54: 1404405.5 | E54: 10666150

Sheet Distributor Wise
C3: Values
A4: Distributor Name | B4: City | C4: 'Target Units | D4: April Sales Units | E4: March LMTD Sales Unit | F4: 'Target Value | G4: April Sales Value | H4: 'Target Achv. % | I4: 'LMTD Sales Value | J4: 'LMTD %age | K4: 'Closing Stock Units | L4: 'Stock Value
A5: AL-HARAM ENTERPRISES, Kohat | B5: Kohat | C5: 6682.0475 | D5: 2086 | E5: 2740 | F5: 1255753.5 | G5: 292639.5 | H5: 0.37827301 | I5: 482000 | J5: -0.35757979 | K5: 5574 | L5: 998968.25
A6: MEHRAN TRADERS, Mardan | B6: Mardan | C6: 4998.6062 | D6: 818 | E6: 578 | F6: 550588.18 | G6: 91099 | H6: 0.2186995 | I6: 63268 | J6: 1.3391629 | K6: 3638 | L6: 509282
A7: Noor Khan Corporation, Mingora | B7: Mingora | C7: 8878.6457 | D7: 3997 | E7: 3780 | F7: 1290995.3 | G7: 542867 | H7: 0.34761654 | I7: 593818.5 | J7: 1.0941808 | K7: 6781 | L7: 1039062
A8: Umar Medicine Distribution, Swabi | B8: Swabi | C8: 3995.93 | D8: 508 | E8: 798 | F8: 471286.46 | G8: 55910 | H8: 0.11001177 | I8: 91713 | J8: 0.19094896 | K8: 3015 | L8: 418123
A9: NEW TAWAKAL ENTERPRISES, ABBT | B9: Abbottabad | C9: 2619 | D9: 1236 | E9: 2005 | F9: 307314 | G9: 150629 | H9: 0.42147604 | I9: 227423 | J9: -0.17224164 | K9: 1549 | L9: 165336
A10: M&C Distributor, RWP | B10: Rwp | C10: 3217.6065 | D10: 498 | E10: 516 | F10: 360810.68 | G10: 85890 | H10: 0.13216203 | I10: 77170 | J10: 15.521236 | K10: 709 | L10: 85970
A11: MASHAL ENTERPRISES, Bajaur | B11: Bajaur | C11: 5174.924 | D11: 1906 | E11: 2298 | F11: 607425.03 | G11: 253240 | H11: 0.24195437 | I11: 253005 | J11: -0.17876801 | K11: 3209 | L11: 348320
A12: Wellness Traders, Bhatkela | B12: Bhatkela | C12: 4810.68 | D12: 0 | E12: 101 | F12: 538778.64 | G12: 0 | H12: 0 | I12: 7709 | J12: -1 | K12: 0 | L12: 0
A13: Al Makkah Trading Co, Buner | B13: Buner | C13: 4810.68 | D13: 2752 | E13: 1957 | F13: 547999.2 | G13: 295389 | H13: 0.31384257 | I13: 210956 | J13: 0.29932397 | K13: 2029 | L13: 218341
A14: CHAUDHARY MEDICINE COMPANY, MWL | B14: Mianwali | C14: 5704.48 | D14: 1920 | E14: 1782 | F14: 648479.94 | G14: 278816 | H14: 0.37792619 | I14: 247856 | J14: 1.787487 | K14: 3690 | L14: 452505
A15: Evergreen Enterprises, D.I.Khan | B15: D.I.Khan | C15: 6626.465 | D15: 4591 | E15: 3118 | F15: 1455491.9 | G15: 700170.25 | H15: 0.62384897 | I15: 600970 | J15: 1.2014316 | K15: 4542 | L15: 1007118.2
A16: NEW SHAHZAIB PHARMACY, Okara | B16: Okara | C16: 4135.2 | D16: 2201 | E16: 2401 | F16: 509925 | G16: 273544 | H16: 0.50262577 | I16: 301511 | J16: -0.081942713 | K16: 3192 | L16: 397643
... A30: AQ DISTRIBUTOR,Sargodha | B30: Sargodha | C30: 4870.053 | D30: 1274 | E30: 995 | F30: 549072.96 | G30: 152093 | H30: 0.2268459 | I30: 116331 | J30: 0.48777439 | K30: 2442 | L30: 266275
A31: REHMAN DRUG AGENCY, SKT | B31: Sialkot | C31: 4009.8 | D31: 0 | E31: 0 | F31: 438568.44 | G31: 0 | H31: 0 | I31: 0 | J31: -- | K31: 2212 | L31: 286053
A32: Zavion Marketing, Jhang | B32: Jhang | C32: 4536.068 | D32: 769 | E32: 718 | F32: 516143.63 | G32: 85719 | H32: 0.18709078 | I32: 83576 | J32: 0.18388287 | K32: 1778 | L32: 214036
A33: LIFE CARE, Gujrat | B33: Gujrat | C33: 5038.272 | D33: 2477 | E33: 2535 | F33: 544975.76 | G33: 268476 | H33: 0.26488193 | I33: 275899 | J33: -0.051720684 | K33: 3338 | L33: 369797
A34: Pharmarite Distributor, Jehlum | B34: Jhelum | C34: 4334.52 | D34: 1782 | E34: 1908 | F34: 495090.6 | G34: 202861.5 | H34: 0.37750204 | I34: 237524 | J34: -0.29873472 | K34: 2318 | L34: 264220
A35: RELIABLE MEDICOS MIRPURKHAS, MPK | B35: Mirpur Khas | C35: 4737.72 | D35: 685 | E35: 778 | F35: 515964 | G35: 75161 | H35: 0.092540488 | I35: 86415 | J35: 0.12012307 | K35: 2334 | L35: 280974
A36: ZAFAR & SONS PHARMA, NWS | B36: Nawabshah | C36: 4324.92 | D36: 2572 | E36: 1865 | F36: 484784.52 | G36: 280586 | H36: 0.61447969 | I36: 202282 | J36: 1.8604269 | K36: 1692 | L36: 213325
A37: Al Rehman Medical Sources, Lahore | B37: Lahore | C37: 9621.09 | D37: 1796 | E37: 4636 | F37: 1120172.8 | G37: 221734 | H37: 0.21616425 | I37: 549609 | J37: -3.1656263 | K37: 4997 | L37: 589888
A38: THE HAMZA TRADERS, Kasur | B38: Kasur | C38: 4872.6825 | D38: 1612 | E38: 1039 | F38: 873571.93 | G38: 212565 | H38: 0.25771999 | I38: 148475 | J38: 0.80930266 | K38: 1536 | L38: 189395
A39: HAJI NIZAM UD DIN & SONS, Quetta | B39: Quetta | C39: 22437.45 | D39: 16204 | E39: 15292 | F39: 2546675.5 | G39: 1961068 | H39: 0.47193596 | I39: 1795760 | J39: 0.43835513 | K39: 13284 | L39: 1693345.5
A40: Ayyan Medicine Company, SKP | B40: SKP | C40: 3936.093 | D40: 148 | E40: 1511 | F40: 454753.17 | G40: 15810 | H40: 0.028398724 | I40: 152079 | J40: -0.20792106 | K40: 2854 | L40: 313406
A41: Lal Drug Agency, Sibbi | B41: Sibbi | C41: 0 | D41: 394 | E41: 427 | F41: 0 | G41: 43386 | H41: -- | I41: 44129 | J41: -0.27429243 | K41: 3102 | L41: 331014
A42: SR Traders, Charsadda | B42: Charsadda | C42: 3822.5687 | D42: 0 | E42: 0 | F42: 460276.46 | G42: 0 | H42: 0 | I42: 0 | J42: -- | K42: 1208 | L42: 142797
A43: Medicamp Distributor, PSW | B43: Peshawar | C43: 10515.064 | D43: 59 | E43: 339 | F43: 2425148.5 | G43: -930 | H43: 0.0023051609 | I43: 45728 | J43: -0.83371156 | K43: 3605 | L43: 678893
A44: Naveed Pharma, Haripur | B44: Haripur | C44: 0 | D44: 0 | E44: 4092 | F44: 0 | G44: 0 | H44: -- | I44: 429240 | J44: -1 | K44: 0 | L44: 0
A45: AIM Pharma, HYD | B45: Hyderabad | C45: 0 | D45: 2052 | E45: 1016 | F45: 0 | G45: 262870 | H45: -- | I45: 125912 | J45: 1.5201136 | K45: 3265 | L45: 499584.75
A46: Hamed Pharma, Bannu | B46: Bannu | C46: 5376.572 | D46: 2465 | E46: 3524 | F46: 1174152.3 | G46: 461072.75 | H46: 0.28426953 | I46: 647479.5 | J46: -0.20372096 | K46: 4181 | L46: 817239.5
A47: Kamal Medicine Company, Timergara | B47: Timergara | C47: 6556.073 | D47: 1415 | E47: 1011 | F47: 1079616.9 | G47: 180509 | H47: 0.18308074 | I47: 156395 | J47: 3.0827919 | K47: 2277 | L47: 356790
A48: Faiz Enterprises, Rajanpur | B48: Rajan pur | C48: 4870.053 | D48: 2547 | E48: 873 | F48: 553868.01 | G48: 272806 | H48: 0.7019154 | I48: 99682 | J48: 1.6800481 | K48: 1620 | L48: 190395
A49: Hashmani Health Care | B49: Karachi | C49: 0 | D49: 3090 | E49: 883 | F49: 0 | G49: 347015 | H49: -- | I49: 102666 | J49: 2.0763663 | K49: 2161 | L49: 280901
A50: Bukhari Medicine Company, MBD | B50: MBD | C50: 5055.9565 | D50: 835 | E50: 777 | F50: 795722.03 | G50: 92219 | H50: 0.14273488 | I50: 93212 | J50: 1.2528656 | K50: 1161 | L50: 167518
A51: Basher Pharma, Gujranwala | B51: Gujranwala | C51: 3961.08 | D51: 1219 | E51: 0 | F51: 452847.6 | G51: 145567 | H51: 0.32680102 | I51: 0 | J51: -- | K51: 2780 | L51: 317801
A52: Ruman Medicine, RYK | B52: R.Y.Khan | C52: 2719.56 | D52: 753 | E52: 137 | F52: 586288 | G52: 259485 | H52: 0.23544908 | I52: 18763 | J52: 6.1550139 | K52: 4750 | L52: 946912
A53: Global Pharma, SKP | B53: SKP | C53: 0 | D53: 130 | E53: 0 | F53: 0 | G53: 13650 | H53: -- | I53: 0 | J53: -- | K53: 2900 | L53: 322726
A54: Grand Total | C54: 242918.08 | D54: 83418 | E54: 82088 | F54: 33108492 | G54: 10666150 | H54: 0.26041 | I54: 10680825 | J54: 0.52416654 | K54: 140491 | L54: 19670268

Sheet Product Wise
B3: Values
A4: Product Name | B4: 'Target Units | C4: July Sales Units | D4: June LMTD Sales Unit | E4: 'Target Value | F4: April Sales Value | G4: 'Target Achv. % | H4: 'LMTD Sales Value | I4: 'LMTD %age | J4: 'Stock Unit | K4: 'Stock Value
A5: Nida 200mg/100ml Inf | B5: 33938.566 | C5: 11792 | D5: 14182 | E5: 3543751.5 | F5: 1232880 | G5: 0.23360951 | H5: 1482828 | I5: 0.018490899 | J5: 11046 | K5: 1156839
A6: Novagen 1g | B6: 28693.469 | C6: 6129 | D6: 9915 | E6: 2954212.4 | F6: 634746 | G6: 0.20161199 | H6: 1034684 | I6: 0.0026964195 | J6: 8272 | K6: 852155
A7: Novagen 500mg | B7: 19416.143 | C7: 2163 | D7: 1746 | E7: 1512205.2 | F7: 170710 | G7: 0.12030888 | H7: 136876 | I7: 0.68674417 | J7: 6178 | K7: 486670
A8: Salberry Sachet 10s | B8: 204 | C8: 98 | D8: 166 | E8: 21420 | F8: 10290 | G8: 0 | H8: 17430 | I8: -0.39335241 | J8: 577 | K8: 60585
A9: Mediscon Syp 120ml | B9: 22863.6 | C9: 17326 | D9: 15184 | E9: 2496312 | F9: 1896710 | G9: 0.66111308 | H9: 1660170 | I9: 0.55803378 | J9: 11012 | K9: 1203060
A10: Trenmed Tab | B10: 1627 | C10: 795 | D10: 677 | E10: 1106360 | F10: 540600 | G10: 0.47560606 | H10: 460360 | I10: 1.4030909 | J10: 1097 | K10: 745960
A11: Gee T.N Ointment | B11: 10519 | C11: 4593 | D11: 4142 | E11: 1861884 | F11: 819780 | G11: 0.42400348 | H11: 739810 | I11: 1.3356426 | J11: 3990 | K11: 711560
A12: Clan Plus Syp | B12: 2632 | C12: 1004 | D12: 659 | E12: 671160 | F12: 256020 | G12: 0.325 | H12: 168045 | I12: 1.1311831 | J12: 1221 | K12: 311355
A13: Medelac Syp 120ml | B13: 6656 | C13: 4630 | D13: 4504 | E13: 699600 | F13: 486280 | G13: 0.61422552 | H13: 473110 | I13: 0.25609883 | J13: 5883 | K13: 618365
A14: Berry Flow Sachet | B14: 4381.4553 | C14: 4090 | D14: 3819 | E14: 503867.35 | F14: 470350 | G14: 0.69869345 | H14: 439185 | I14: 0.17832632 | J14: 4410 | K14: 507150
A15: Grand Total | B15: 130931.23 | C15: 52620 | D15: 54994 | E15: 15370772 | F15: 6518366 | G15: 0.42548302 | H15: 6612498 | I15: 0.46966163 | J15: 53686 | K15: 6653699

Sheet DATA
A3: Distributor Name | B3: City | C3: Region | D3: Country | E3: Category | F3: Group | G3: Manager | H3: Product Name | I3: S.P | J3: Sales Units | K3: Closing Stock | L3: Sales Value | M3: Stock Value | N3: Yesterday | O3: Yesterday Sale Value | P3: Difference | Q3: Target Units | R3: Target Value | S3: Target Achv. % | T3: LMTD Sales Unit | U3: LMTD Difference | V3: LMTD Sales Value | W3: LMTD Difference | X3: LMTD %age | Y3: Inventory | Z3: Order | AA3: Order Value | AB3: Excess Stock | AC3: Excess Stock Value | AD3: Inventory Value | AE3: Transit
A4: AL-HARAM ENTERPRISES, Kohat | B4: =IFERROR(VLOOKUP(A4,'Distributor List'!$A$2:$D$77,2,0),"-") -> Kohat | C4: =IFERROR(VLOOKUP(A4,'Distributor List'!$A$2:$D$77,3,0),"-") -> North-1 | D4: =IFERROR(VLOOKUP(A4,'Distributor List'!$A$2:$F$77,6,0),"-") -> Pak-2 | E4: =IFERROR(VLOOKUP(A4,'Distributor List'!$A$2:$D$77,4,0),"-") -> Distributor | F4: =IFERROR(VLOOKUP(H4,'Price List'!$A$2:$H$109,8,0),"-") -> Transformer | G4: =IFERROR(VLOOKUP(A4,'Distributor List'!$A$2:$E$77,5,0),"-") -> Bannu Vacant | H4: Novagen 250mg T | I4: 161.5 | J4: 20 | K4: 384 | L4: =J4*I4 -> 3230 | M4: =K4*I4 -> 62016 | N4: 20 | O4: =N4*I4 -> 3230 | P4: =L4-O4 -> 0 | Q4: 218.025 | R4: =Q4*I4 -> 35211.037 | S4: =IFERROR(L4/R4,"-") -> 0.091732599 | T4: 0 | U4: =J4-T4 -> 20 | V4: =T4*I4 -> 0 | W4: =L4-V4 -> 3230 | X4: =IFERROR(L4/V4-1,"-") -> - | Y4: =(J4)/1*1.5 -> 30 | Z4: =IF(Y4>K4,Y4-K4,0) -> 0 | AA4: =Z4*I4 -> 0 | AB4: =IF(Y4<K4,K4-Y4,0) -> 354 | AC4: =AB4*I4 -> 57171 | AD4: =Y4*I4 -> 4845 | AE4: 0
A5: AL-HARAM ENTERPRISES, Kohat | B5: =IFERROR(VLOOKUP(A5,'Distributor List'!$A$2:$D$77,2,0),"-") -> Kohat | C5: =IFERROR(VLOOKUP(A5,'Distributor List'!$A$2:$D$77,3,0),"-") -> North-1 | D5: =IFERROR(VLOOKUP(A5,'Distributor List'!$A$2:$F$77,6,0),"-") -> Pak-2 | E5: =IFERROR(VLOOKUP(A5,'Distributor List'!$A$2:$D$77,4,0),"-") -> Distributor | F5: =IFERROR(VLOOKUP(H5,'Price List'!$A$2:$H$109,8,0),"-") -> Transformer | G5: =IFERROR(VLOOKUP(A5,'Distributor List'!$A$2:$E$77,5,0),"-") -> Bannu Vacant | H5: Novagen 500mg T | I5: 242.25 | J5: 40 | K5: 417 | L5: =J5*I5 -> 9690 | M5: =K5*I5 -> 101018.25 | N5: 40 | O5: =N5*I5 -> 9690 | P5: =L5-O5 -> 0 | Q5: 700.4475 | R5: =Q5*I5 -> 169683.41 | S5: =IFERROR(L5/R5,"-") -> 0.05710635 | T5: 20 | U5: =J5-T5 -> 20 | V5: =T5*I5 -> 4845 | W5: =L5-V5 -> 4845 | X5: =IFERROR(L5/V5-1,"-") -> 1 | Y5: =(J5)/1*1.5 -> 60 | Z5: =IF(Y5>K5,Y5-K5,0) -> 0 | AA5: =Z5*I5 -> 0 | AB5: =IF(Y5<K5,K5-Y5,0) -> 357 | AC5: =AB5*I5 -> 86483.25 | AD5: =Y5*I5 -> 14535 | AE5: 0
A6: AL-HARAM ENTERPRISES, Kohat | B6: =IFERROR(VLOOKUP(A6,'Distributor List'!$A$2:$D$77,2,0),"-") -> Kohat | C6: =IFERROR(VLOOKUP(A6,'Distributor List'!$A$2:$D$77,3,0),"-") -> North-1 | D6: =IFERROR(VLOOKUP(A6,'Distributor List'!$A$2:$F$77,6,0),"-") -> Pak-2 | E6: =IFERROR(VLOOKUP(A6,'Distributor List'!$A$2:$D$77,4,0),"-") -> Distributor | F6: =IFERROR(VLOOKUP(H6,'Price List'!$A$2:$H$109,8,0),"-") -> Transformer | G6: =IFERROR(VLOOKUP(A6,'Distributor List'!$A$2:$E$77,5,0),"-") -> Bannu Vacant | H6: Novagen 1g T | I6: 446.25 | J6: 82 | K6: 208 | L6: =J6*I6 -> 36592.5 | M6: =K6*I6 -> 92820 | N6: 82 | O6: =N6*I6 -> 36592.5 | P6: =L6-O6 -> 0 | Q6: 881.586 | R6: =Q6*I6 -> 393407.75 | S6: =IFERROR(L6/R6,"-") -> 0.093014181 | T6: 190 | U6: =J6-T6 -> -108 | V6: =T6*I6 -> 84787.5 | W6: =L6-V6 -> -48195 | X6: =IFERROR(L6/V6-1,"-") -> -0.56842105 | Y6: =(J6)/1*1.5 -> 123 | Z6: =IF(Y6>K6,Y6-K6,0) -> 0 | AA6: =Z6*I6 -> 0 | AB6: =IF(Y6<K6,K6-Y6,0) -> 85 | AC6: =AB6*I6 -> 37931.25 | AD6: =Y6*I6 -> 54888.75 | AE6: 0
A7: AL-HARAM ENTERPRISES, Kohat | B7: =IFERROR(VLOOKUP(A7,'Distributor List'!$A$2:$D$77,2,0),"-") -> Kohat | C7: =IFERROR(VLOOKUP(A7,'Distributor List'!$A$2:$D$77,3,0),"-") -> North-1 | D7: =IFERROR(VLOOKUP(A7,'Distributor List'!$A$2:$F$77,6,0),"-") -> Pak-2 | E7: =IFERROR(VLOOKUP(A7,'Distributor List'!$A$2:$D$77,4,0),"-") -> Distributor | F7: =IFERROR(VLOOKUP(H7,'Price List'!$A$2:$H$109,8,0),"-") -> Transformer | G7: =IFERROR(VLOOKUP(A7,'Distributor List'!$A$2:$E$77,5,0),"-") -> Bannu Vacant | H7: Ectafin 1G | I7: 297.5 | J7: 0 | K7: 80 | L7: =J7*I7 -> 0 | M7: =K7*I7 -> 23800 | N7: 0 | O7: =N7*I7 -> 0 | P7: =L7-O7 -> 0 | Q7: 0 | R7: =Q7*I7 -> 0 | S7: =IFERROR(L7/R7,"-") -> - | T7: 70 | U7: =J7-T7 -> -70 | V7: =T7*I7 -> 20825 | W7: =L7-V7 -> -20825 | X7: =IFERROR(L7/V7-1,"-") -> -1 | Y7: =(J7)/1*1.5 -> 0 | Z7: =IF(Y7>K7,Y7-K7,0) -> 0 | AA7: =Z7*I7 -> 0 | AB7: =IF(Y7<K7,K7-Y7,0) -> 80 | AC7: =AB7*I7 -> 23800 | AD7: =Y7*I7 -> 0 | AE7: 0
A8: AL-HARAM ENTERPRISES, Kohat | B8: =IFERROR(VLOOKUP(A8,'Distributor List'!$A$2:$D$77,2,0),"-") -> Kohat | C8: =IFERROR(VLOOKUP(A8,'Distributor List'!$A$2:$D$77,3,0),"-") -> North-1 | D8: =IFERROR(VLOOKUP(A8,'Distributor List'!$A$2:$F$77,6,0),"-") -> Pak-2 | E8: =IFERROR(VLOOKUP(A8,'Distributor List'!$A$2:$D$77,4,0),"-") -> Distributor | F8: =IFERROR(VLOOKUP(H8,'Price List'!$A$2:$H$109,8,0),"-") -> Transformer | G8: =IFERROR(VLOOKUP(A8,'Distributor List'!$A$2:$E$77,5,0),"-") -> Bannu Vacant | H8: Ectafin 2G | I8: 429.25 | J8: 0 | K8: 80 | L8: =J8*I8 -> 0 | M8: =K8*I8 -> 34340 | N8: 0 | O8: =N8*I8 -> 0 | P8: =L8-O8 -> 0 | Q8: 0 | R8: =Q8*I8 -> 0 | S8: =IFERROR(L8/R8,"-") -> - | T8: 70 | U8: =J8-T8 -> -70 | V8: =T8*I8 -> 30047.5 | W8: =L8-V8 -> -30047.5 | X8: =IFERROR(L8/V8-1,"-") -> -1 | Y8: =(J8)/1*1.5 -> 0 | Z8: =IF(Y8>K8,Y8-K8,0) -> 0 | AA8: =Z8*I8 -> 0 | AB8: =IF(Y8<K8,K8-Y8,0) -> 80 | AC8: =AB8*I8 -> 34340 | AD8: =Y8*I8 -> 0 | AE8: 0
A9: AL-HARAM ENTERPRISES, Kohat | B9: =IFERROR(VLOOKUP(A9,'Distributor List'!$A$2:$D$77,2,0),"-") -> Kohat | C9: =IFERROR(VLOOKUP(A9,'Distributor List'!$A$2:$D$77,3,0),"-") -> North-1 | D9: =IFERROR(VLOOKUP(A9,'Distributor List'!$A$2:$F$77,6,0),"-") -> Pak-2 | E9: =IFERROR(VLOOKUP(A9,'Distributor List'!$A$2:$D$77,4,0),"-") -> Distributor | F9: =IFERROR(VLOOKUP(H9,'Price List'!$A$2:$H$109,8,0),"-") -> Medicronis | G9: =IFERROR(VLOOKUP(A9,'Distributor List'!$A$2:$E$77,5,0),"-") -> Bannu Vacant | H9: Lancix Inj. 10s | I9: 270 | J9: 31 | K9: 463 | L9: =J9*I9 -> 8370 | M9: =K9*I9 -> 125010 | N9: 31 | O9: =N9*I9 -> 8370 | P9: =L9-O9 -> 0 | Q9: 388.773 | R9: =Q9*I9 -> 104968.71 | S9: =IFERROR(L9/R9,"-") -> 0.079738048 | T9: 96 | U9: =J9-T9 -> -65 | V9: =T9*I9 -> 25920 | W9: =L9-V9 -> -17550 | X9: =IFERROR(L9/V9-1,"-") -> -0.67708333 | Y9: =(J9)/1*1.5 -> 46.5 | Z9: =IF(Y9>K9,Y9-K9,0) -> 0 | AA9: =Z9*I9 -> 0 | AB9: =IF(Y9<K9,K9-Y9,0) -> 416.5 | AC9: =AB9*I9 -> 112455 | AD9: =Y9*I9 -> 12555 | AE9: 0
A10: AL-HARAM ENTERPRISES, Kohat | B10: =IFERROR(VLOOKUP(A10,'Distributor List'!$A$2:$D$77,2,0),"-") -> Kohat | C10: =IFERROR(VLOOKUP(A10,'Distributor List'!$A$2:$D$77,3,0),"-") -> North-1 | D10: =IFERROR(VLOOKUP(A10,'Distributor List'!$A$2:$F$77,6,0),"-") -> Pak-2 | E10: =IFERROR(VLOOKUP(A10,'Distributor List'!$A$2:$D$77,4,0),"-") -> Distributor | F10: =IFERROR(VLOOKUP(H10,'Price List'!$A$2:$H$109,8,0),"-") -> Medicronis | G10: =IFERROR(VLOOKUP(A10,'Distributor List'!$A$2:$E$77,5,0),"-") -> Bannu Vacant | H10: Lancix Inj. 25s | I10: 670 | J10: 6 | K10: 188 | L10: =J10*I10 -> 4020 | M10: =K10*I10 -> 125960 | N10: 6 | O10: =N10*I10 -> 4020 | P10: =L10-O10 -> 0 | Q10: 84.21 | R10: =Q10*I10 -> 56420.7 | S10: =IFERROR(L10/R10,"-") -> 0.071250445 | T10: 101 | U10: =J10-T10 -> -95 | V10: =T10*I10 -> 67670 | W10: =L10-V10 -> -63650 | X10: =IFERROR(L10/V10-1,"-") -> -0.94059406 | Y10: =(J10)/1*1.5 -> 9 | Z10: =IF(Y10>K10,Y10-K10,0) -> 0 | AA10: =Z10*I10 -> 0 | AB10: =IF(Y10<K10,K10-Y10,0) -> 179 | AC10: =AB10*I10 -> 119930 | AD10: =Y10*I10 -> 6030 | AE10: 0
A11: AL-HARAM ENTERPRISES, Kohat | B11: =IFERROR(VLOOKUP(A11,'Distributor List'!$A$2:$D$77,2,0),"-") -> Kohat | C11: =IFERROR(VLOOKUP(A11,'Distributor List'!$A$2:$D$77,3,0),"-") -> North-1 | D11: =IFERROR(VLOOKUP(A11,'Distributor List'!$A$2:$F$77,6,0),"-") -> Pak-2 | E11: =IFERROR(VLOOKUP(A11,'Distributor List'!$A$2:$D$77,4,0),"-") -> Distributor | F11: =IFERROR(VLOOKUP(H11,'Price List'!$A$2:$H$109,8,0),"-") -> Medicronis | G11: =IFERROR(VLOOKUP(A11,'Distributor List'!$A$2:$E$77,5,0),"-") -> Bannu Vacant | H11: G.Tax 250mg | I11: 58 | J11: 0 | K11: 235 | L11: =J11*I11 -> 0 | M11: =K11*I11 -> 13630 | N11: 0 | O11: =N11*I11 -> 0 | P11: =L11-O11 -> 0 | Q11: 81 | R11: =Q11*I11 -> 4698 | S11: =IFERROR(L11/R11,"-") -> 0 | T11: 0 | U11: =J11-T11 -> 0 | V11: =T11*I11 -> 0 | W11: =L11-V11 -> 0 | X11: =IFERROR(L11/V11-1,"-") -> - | Y11: =(J11)/1*1.5 -> 0 | Z11: =IF(Y11>K11,Y11-K11,0) -> 0 | AA11: =Z11*I11 -> 0 | AB11: =IF(Y11<K11,K11-Y11,0) -> 235 | AC11: =AB11*I11 -> 13630 | AD11: =Y11*I11 -> 0 | AE11: 0
A12: AL-HARAM ENTERPRISES, Kohat | B12: =IFERROR(VLOOKUP(A12,'Distributor List'!$A$2:$D$77,2,0),"-") -> Kohat | C12: =IFERROR(VLOOKUP(A12,'Distributor List'!$A$2:$D$77,3,0),"-") -> North-1 | D12: =IFERROR(VLOOKUP(A12,'Distributor List'!$A$2:$F$77,6,0),"-") -> Pak-2 | E12: =IFERROR(VLOOKUP(A12,'Distributor List'!$A$2:$D$77,4,0),"-") -> Distributor | F12: =IFERROR(VLOOKUP(H12,'Price List'!$A$2:$H$109,8,0),"-") -> Medicronis | G12: =IFERROR(VLOOKUP(A12,'Distributor List'!$A$2:$E$77,5,0),"-") -> Bannu Vacant | H12: G.Tax 500mg | I12: 72 | J12: 0 | K12: 40 | L12: =J12*I12 -> 0 | M12: =K12*I12 -> 2880 | N12: 0 | O12: =N12*I12 -> 0 | P12: =L12-O12 -> 0 | Q12: 81 | R12: =Q12*I12 -> 5832 | S12: =IFERROR(L12/R12,"-") -> 0 | T12: 10 | U12: =J12-T12 -> -10 | V12: =T12*I12 -> 720 | W12: =L12-V12 -> -720 | X12: =IFERROR(L12/V12-1,"-") -> -1 | Y12: =(J12)/1*1.5 -> 0 | Z12: =IF(Y12>K12,Y12-K12,0) -> 0 | AA12: =Z12*I12 -> 0 | AB12: =IF(Y12<K12,K12-Y12,0) -> 40 | AC12: =AB12*I12 -> 2880 | AD12: =Y12*I12 -> 0 | AE12: 0
A13: AL-HARAM ENTERPRISES, Kohat | B13: =IFERROR(VLOOKUP(A13,'Distributor List'!$A$2:$D$77,2,0),"-") -> Kohat | C13: =IFERROR(VLOOKUP(A13,'Distributor List'!$A$2:$D$77,3,0),"-") -> North-1 | D13: =IFERROR(VLOOKUP(A13,'Distributor List'!$A$2:$F$77,6,0),"-") -> Pak-2 | E13: =IFERROR(VLOOKUP(A13,'Distributor List'!$A$2:$D$77,4,0),"-") -> Distributor | F13: =IFERROR(VLOOKUP(H13,'Price List'!$A$2:$H$109,8,0),"-") -> Medicronis | G13: =IFERROR(VLOOKUP(A13,'Distributor List'!$A$2:$E$77,5,0),"-") -> Bannu Vacant | H13: G.Tax 1G | I13: 112 | J13: 186 | K13: 386 | L13: =J13*I13 -> 20832 | M13: =K13*I13 -> 43232 | N13: 186 | O13: =N13*I13 -> 20832 | P13: =L13-O13 -> 0 | Q13: 64.8 | R13: =Q13*I13 -> 7257.6 | S13: =IFERROR(L13/R13,"-") -> 2.8703704 | T13: 0 | U13: =J13-T13 -> 186 | V13: =T13*I13 -> 0 | W13: =L13-V13 -> 20832 | X13: =IFERROR(L13/V13-1,"-") -> - | Y13: =(J13)/1*1.5 -> 279 | Z13: =IF(Y13>K13,Y13-K13,0) -> 0 | AA13: =Z13*I13 -> 0 | AB13: =IF(Y13<K13,K13-Y13,0) -> 107 | AC13: =AB13*I13 -> 11984 | AD13: =Y13*I13 -> 31248 | AE13: 0
A14: AL-HARAM ENTERPRISES, Kohat | B14: =IFERROR(VLOOKUP(A14,'Distributor List'!$A$2:$D$77,2,0),"-") -> Kohat | C14: =IFERROR(VLOOKUP(A14,'Distributor List'!$A$2:$D$77,3,0),"-") -> North-1 | D14: =IFERROR(VLOOKUP(A14,'Distributor List'!$A$2:$F$77,6,0),"-") -> Pak-2 | E14: =IFERROR(VLOOKUP(A14,'Distributor List'!$A$2:$D$77,4,0),"-") -> Distributor | F14: =IFERROR(VLOOKUP(H14,'Price List'!$A$2:$H$109,8,0),"-") -> Medicronis | G14: =IFERROR(VLOOKUP(A14,'Distributor List'!$A$2:$E$77,5,0),"-") -> Bannu Vacant | H14: G-Sef 125mg Susp 60ml | I14: 140 | J14: 20 | K14: 154 | L14: =J14*I14 -> 2800 | M14: =K14*I14 -> 21560 | N14: 20 | O14: =N14*I14 -> 2800 | P14: =L14-O14 -> 0 | Q14: 63.04 | R14: =Q14*I14 -> 8825.6 | S14: =IFERROR(L14/R14,"-") -> 0.31725888 | T14: 0 | U14: =J14-T14 -> 20 | V14: =T14*I14 -> 0 | W14: =L14-V14 -> 2800 | X14: =IFERROR(L14/V14-1,"-") -> - | Y14: =(J14)/1*1.5 -> 30 | Z14: =IF(Y14>K14,Y14-K14,0) -> 0 | AA14: =Z14*I14 -> 0 | AB14: =IF(Y14<K14,K14-Y14,0) -> 124 | AC14: =AB14*I14 -> 17360 | AD14: =Y14*I14 -> 4200 | AE14: 0
A15: AL-HARAM ENTERPRISES, Kohat | B15: =IFERROR(VLOOKUP(A15,'Distributor List'!$A$2:$D$77,2,0),"-") -> Kohat | C15: =IFERROR(VLOOKUP(A15,'Distributor List'!$A$2:$D$77,3,0),"-") -> North-1 | D15: =IFERROR(VLOOKUP(A15,'Distributor List'!$A$2:$F$77,6,0),"-") -> Pak-2 | E15: =IFERROR(VLOOKUP(A15,'Distributor List'!$A$2:$D$77,4,0),"-") -> Distributor | F15: =IFERROR(VLOOKUP(H15,'Price List'!$A$2:$H$109,8,0),"-") -> Medicronis | G15: =IFERROR(VLOOKUP(A15,'Distributor List'!$A$2:$E$77,5,0),"-") -> Bannu Vacant | H15: G-Sef 250mg Susp 60ml | I15: 199 | J15: 0 | K15: 0 | L15: =J15*I15 -> 0 | M15: =K15*I15 -> 0 | N15: 0 | O15: =N15*I15 -> 0 | P15: =L15-O15 -> 0 | Q15: 52.904 | R15: =Q15*I15 -> 10527.896 | S15: =IFERROR(L15/R15,"-") -> 0 | T15: 0 | U15: =J15-T15 -> 0 | V15: =T15*I15 -> 0 | W15: =L15-V15 -> 0 | X15: =IFERROR(L15/V15-1,"-") -> - | Y15: =(J15)/1*1.5 -> 0 | Z15: =IF(Y15>K15,Y15-K15,0) -> 0 | AA15: =Z15*I15 -> 0 | AB15: =IF(Y15<K15,K15-Y15,0) -> 0 | AC15: =AB15*I15 -> 0 | AD15: =Y15*I15 -> 0 | AE15: 0
... A42: AL-HARAM ENTERPRISES, Kohat | B42: =IFERROR(VLOOKUP(A42,'Distributor List'!$A$2:$D$77,2,0),"-") -> Kohat | C42: =IFERROR(VLOOKUP(A42,'Distributor List'!$A$2:$D$77,3,0),"-") -> North-1 | D42: =IFERROR(VLOOKUP(A42,'Distributor List'!$A$2:$F$77,6,0),"-") -> Pak-2 | E42: =IFERROR(VLOOKUP(A42,'Distributor List'!$A$2:$D$77,4,0),"-") -> Distributor | F42: =IFERROR(VLOOKUP(H42,'Price List'!$A$2:$H$109,8,0),"-") -> Medicronis | G42: =IFERROR(VLOOKUP(A42,'Distributor List'!$A$2:$E$77,5,0),"-") -> Bannu Vacant | H42: Medelac Syp 120ml | I42: 105 | J42: 63 | K42: 47 | L42: =J42*I42 -> 6615 | M42: =K42*I42 -> 4935 | N42: 63 | O42: =N42*I42 -> 6615 | P42: =L42-O42 -> 0 | Q42: 144 | R42: =Q42*I42 -> 15120 | S42: =IFERROR(L42/R42,"-") -> 0.4375 | T42: 75 | U42: =J42-T42 -> -12 | V42: =T42*I42 -> 7875 | W42: =L42-V42 -> -1260 | X42: =IFERROR(L42/V42-1,"-") -> -0.16 | Y42: =(J42)/1*1.5 -> 94.5 | Z42: =IF(Y42>K42,Y42-K42,0) -> 47.5 | AA42: =Z42*I42 -> 4987.5 | AB42: =IF(Y42<K42,K42-Y42,0) -> 0 | AC42: =AB42*I42 -> 0 | AD42: =Y42*I42 -> 9922.5 | AE42: 0
A43: AL-HARAM ENTERPRISES, Kohat | B43: =IFERROR(VLOOKUP(A43,'Distributor List'!$A$2:$D$77,2,0),"-") -> Kohat | C43: =IFERROR(VLOOKUP(A43,'Distributor List'!$A$2:$D$77,3,0),"-") -> North-1 | D43: =IFERROR(VLOOKUP(A43,'Distributor List'!$A$2:$F$77,6,0),"-") -> Pak-2 | E43: =IFERROR(VLOOKUP(A43,'Distributor List'!$A$2:$D$77,4,0),"-") -> Distributor | F43: =IFERROR(VLOOKUP(H43,'Price List'!$A$2:$H$109,8,0),"-") -> Medicronis | G43: =IFERROR(VLOOKUP(A43,'Distributor List'!$A$2:$E$77,5,0),"-") -> Bannu Vacant | H43: Medizek 20mg | I43: 90 | J43: 0 | K43: 0 | L43: =J43*I43 -> 0 | M43: =K43*I43 -> 0 | N43: 0 | O43: =N43*I43 -> 0 | P43: =L43-O43 -> 0 | Q43: 0 | R43: 0 | S43: =IFERROR(L43/R43,"-") -> - | T43: 0 | U43: 0 | V43: =T43*I43 -> 0 | W43: =L43-V43 -> 0 | X43: =IFERROR(L43/V43-1,"-") -> - | Y43: =(J43)/1*1.5 -> 0 | Z43: =IF(Y43>K43,Y43-K43,0) -> 0 | AA43: =Z43*I43 -> 0 | AB43: =IF(Y43<K43,K43-Y43,0) -> 0 | AC43: =AB43*I43 -> 0 | AD43: =Y43*I43 -> 0 | AE43: 0
A44: AL-HARAM ENTERPRISES, Kohat | B44: =IFERROR(VLOOKUP(A44,'Distributor List'!$A$2:$D$77,2,0),"-") -> Kohat | C44: =IFERROR(VLOOKUP(A44,'Distributor List'!$A$2:$D$77,3,0),"-") -> North-1 | D44: =IFERROR(VLOOKUP(A44,'Distributor List'!$A$2:$F$77,6,0),"-") -> Pak-2 | E44: =IFERROR(VLOOKUP(A44,'Distributor List'!$A$2:$D$77,4,0),"-") -> Distributor | F44: =IFERROR(VLOOKUP(H44,'Price List'!$A$2:$H$109,8,0),"-") -> Medicronis | G44: =IFERROR(VLOOKUP(A44,'Distributor List'!$A$2:$E$77,5,0),"-") -> Bannu Vacant | H44: Medizek 40mg | I44: 105 | J44: 0 | K44: 0 | L44: =J44*I44 -> 0 | M44: =K44*I44 -> 0 | N44: 0 | O44: =N44*I44 -> 0 | P44: =L44-O44 -> 0 | Q44: 0 | R44: 0 | S44: =IFERROR(L44/R44,"-") -> - | T44: 0 | U44: 0 | V44: =T44*I44 -> 0 | W44: =L44-V44 -> 0 | X44: =IFERROR(L44/V44-1,"-") -> - | Y44: =(J44)/1*1.5 -> 0 | Z44: =IF(Y44>K44,Y44-K44,0) -> 0 | AA44: =Z44*I44 -> 0 | AB44: =IF(Y44<K44,K44-Y44,0) -> 0 | AC44: =AB44*I44 -> 0 | AD44: =Y44*I44 -> 0 | AE44: 0
A45: AL-HARAM ENTERPRISES, Kohat | B45: =IFERROR(VLOOKUP(A45,'Distributor List'!$A$2:$D$77,2,0),"-") -> Kohat | C45: =IFERROR(VLOOKUP(A45,'Distributor List'!$A$2:$D$77,3,0),"-") -> North-1 | D45: =IFERROR(VLOOKUP(A45,'Distributor List'!$A$2:$F$77,6,0),"-") -> Pak-2 | E45: =IFERROR(VLOOKUP(A45,'Distributor List'!$A$2:$D$77,4,0),"-") -> Distributor | F45: =IFERROR(VLOOKUP(H45,'Price List'!$A$2:$H$109,8,0),"-") -> Medicronis | G45: =IFERROR(VLOOKUP(A45,'Distributor List'!$A$2:$E$77,5,0),"-") -> Bannu Vacant | H45: Medizek INJ | I45: 120 | J45: 0 | K45: 0 | L45: =J45*I45 -> 0 | M45: =K45*I45 -> 0 | N45: 0 | O45: =N45*I45 -> 0 | P45: =L45-O45 -> 0 | Q45: 0 | R45: 0 | S45: =IFERROR(L45/R45,"-") -> - | T45: 0 | U45: 0 | V45: =T45*I45 -> 0 | W45: =L45-V45 -> 0 | X45: =IFERROR(L45/V45-1,"-") -> - | Y45: =(J45)/1*1.5 -> 0 | Z45: =IF(Y45>K45,Y45-K45,0) -> 0 | AA45: =Z45*I45 -> 0 | AB45: =IF(Y45<K45,K45-Y45,0) -> 0 | AC45: =AB45*I45 -> 0 | AD45: =Y45*I45 -> 0 | AE45: 0
A46: AL-HARAM ENTERPRISES, Kohat | B46: =IFERROR(VLOOKUP(A46,'Distributor List'!$A$2:$D$77,2,0),"-") -> Kohat | C46: =IFERROR(VLOOKUP(A46,'Distributor List'!$A$2:$D$77,3,0),"-") -> North-1 | D46: =IFERROR(VLOOKUP(A46,'Distributor List'!$A$2:$F$77,6,0),"-") -> Pak-2 | E46: =IFERROR(VLOOKUP(A46,'Distributor List'!$A$2:$D$77,4,0),"-") -> Distributor | F46: =IFERROR(VLOOKUP(H46,'Price List'!$A$2:$H$109,8,0),"-") -> Medicronis | G46: =IFERROR(VLOOKUP(A46,'Distributor List'!$A$2:$E$77,5,0),"-") -> Bannu Vacant | H46: Paxcal Syrup 120ml | I46: 105 | J46: 10 | K46: 113 | L46: =J46*I46 -> 1050 | M46: =K46*I46 -> 11865 | N46: 10 | O46: =N46*I46 -> 1050 | P46: =L46-O46 -> 0 | Q46: 75 | R46: =Q46*I46 -> 7875 | S46: =IFERROR(L46/R46,"-") -> 0.13333333 | T46: 15 | U46: =J46-T46 -> -5 | V46: =T46*I46 -> 1575 | W46: =L46-V46 -> -525 | X46: =IFERROR(L46/V46-1,"-") -> -0.33333333 | Y46: =(J46)/1*1.5 -> 15 | Z46: =IF(Y46>K46,Y46-K46,0) -> 0 | AA46: =Z46*I46 -> 0 | AB46: =IF(Y46<K46,K46-Y46,0) -> 98 | AC46: =AB46*I46 -> 10290 | AD46: =Y46*I46 -> 1575 | AE46: 0
A47: AL-HARAM ENTERPRISES, Kohat | B47: =IFERROR(VLOOKUP(A47,'Distributor List'!$A$2:$D$77,2,0),"-") -> Kohat | C47: =IFERROR(VLOOKUP(A47,'Distributor List'!$A$2:$D$77,3,0),"-") -> North-1 | D47: =IFERROR(VLOOKUP(A47,'Distributor List'!$A$2:$F$77,6,0),"-") -> Pak-2 | E47: =IFERROR(VLOOKUP(A47,'Distributor List'!$A$2:$D$77,4,0),"-") -> Distributor | F47: =IFERROR(VLOOKUP(H47,'Price List'!$A$2:$H$109,8,0),"-") -> Medicronis | G47: =IFERROR(VLOOKUP(A47,'Distributor List'!$A$2:$E$77,5,0),"-") -> Bannu Vacant | H47: Paxcal Tab 20's | I47: 170 | J47: 3 | K47: 28 | L47: =J47*I47 -> 510 | M47: =K47*I47 -> 4760 | N47: 3 | O47: =N47*I47 -> 510 | P47: =L47-O47 -> 0 | Q47: 75 | R47: =Q47*I47 -> 12750 | S47: =IFERROR(L47/R47,"-") -> 0.04 | T47: 5 | U47: =J47-T47 -> -2 | V47: =T47*I47 -> 850 | W47: =L47-V47 -> -340 | X47: =IFERROR(L47/V47-1,"-") -> -0.4 | Y47: =(J47)/1*1.5 -> 4.5 | Z47: =IF(Y47>K47,Y47-K47,0) -> 0 | AA47: =Z47*I47 -> 0 | AB47: =IF(Y47<K47,K47-Y47,0) -> 23.5 | AC47: =AB47*I47 -> 3995 | AD47: =Y47*I47 -> 765 | AE47: 0
A48: AL-HARAM ENTERPRISES, Kohat | B48: =IFERROR(VLOOKUP(A48,'Distributor List'!$A$2:$D$77,2,0),"-") -> Kohat | C48: =IFERROR(VLOOKUP(A48,'Distributor List'!$A$2:$D$77,3,0),"-") -> North-1 | D48: =IFERROR(VLOOKUP(A48,'Distributor List'!$A$2:$F$77,6,0),"-") -> Pak-2 | E48: =IFERROR(VLOOKUP(A48,'Distributor List'!$A$2:$D$77,4,0),"-") -> Distributor | F48: =IFERROR(VLOOKUP(H48,'Price List'!$A$2:$H$109,8,0),"-") -> Medicronis | G48: =IFERROR(VLOOKUP(A48,'Distributor List'!$A$2:$E$77,5,0),"-") -> Bannu Vacant | H48: V-Fol 400mcg | I48: 120 | J48: 65 | K48: 0 | L48: =J48*I48 -> 7800 | M48: =K48*I48 -> 0 | N48: 65 | O48: =N48*I48 -> 7800 | P48: =L48-O48 -> 0 | Q48: 81 | R48: =Q48*I48 -> 9720 | S48: =IFERROR(L48/R48,"-") -> 0.80246914 | T48: 52 | U48: =J48-T48 -> 13 | V48: =T48*I48 -> 6240 | W48: =L48-V48 -> 1560 | X48: =IFERROR(L48/V48-1,"-") -> 0.25 | Y48: =(J48)/1*1.5 -> 97.5 | Z48: =IF(Y48>K48,Y48-K48,0) -> 97.5 | AA48: =Z48*I48 -> 11700 | AB48: =IF(Y48<K48,K48-Y48,0) -> 0 | AC48: =AB48*I48 -> 0 | AD48: =Y48*I48 -> 11700 | AE48: 0
A49: MEHRAN TRADERS, Mardan | B49: =IFERROR(VLOOKUP(A49,'Distributor List'!$A$2:$D$77,2,0),"-") -> Mardan | C49: =IFERROR(VLOOKUP(A49,'Distributor List'!$A$2:$D$77,3,0),"-") -> North-2 | D49: =IFERROR(VLOOKUP(A49,'Distributor List'!$A$2:$F$77,6,0),"-") -> Pak-2 | E49: =IFERROR(VLOOKUP(A49,'Distributor List'!$A$2:$D$77,4,0),"-") -> Distributor | F49: =IFERROR(VLOOKUP(H49,'Price List'!$A$2:$H$109,8,0),"-") -> Medicronis | G49: =IFERROR(VLOOKUP(A49,'Distributor List'!$A$2:$E$77,5,0),"-") -> Rooh Ul Ameen | H49: Novagen 250mg | I49: 54 | J49: 0 | K49: 0 | L49: =J49*I49 -> 0 | M49: =K49*I49 -> 0 | N49: 0 | O49: =N49*I49 -> 0 | P49: =L49-O49 -> 0 | Q49: 172.8 | R49: =Q49*I49 -> 9331.2 | S49: =IFERROR(L49/R49,"-") -> 0 | T49: 0 | U49: =J49-T49 -> 0 | V49: =T49*I49 -> 0 | W49: =L49-V49 -> 0 | X49: =IFERROR(L49/V49-1,"-") -> - | Y49: =(J49)/1*1.5 -> 0 | Z49: =IF(Y49>K49,Y49-K49,0) -> 0 | AA49: =Z49*I49 -> 0 | AB49: =IF(Y49<K49,K49-Y49,0) -> 0 | AC49: =AB49*I49 -> 0 | AD49: =Y49*I49 -> 0 | AE49: 0
A50: MEHRAN TRADERS, Mardan | B50: =IFERROR(VLOOKUP(A50,'Distributor List'!$A$2:$D$77,2,0),"-") -> Mardan | C50: =IFERROR(VLOOKUP(A50,'Distributor List'!$A$2:$D$77,3,0),"-") -> North-2 | D50: =IFERROR(VLOOKUP(A50,'Distributor List'!$A$2:$F$77,6,0),"-") -> Pak-2 | E50: =IFERROR(VLOOKUP(A50,'Distributor List'!$A$2:$D$77,4,0),"-") -> Distributor | F50: =IFERROR(VLOOKUP(H50,'Price List'!$A$2:$H$109,8,0),"-") -> Medicronis | G50: =IFERROR(VLOOKUP(A50,'Distributor List'!$A$2:$E$77,5,0),"-") -> Rooh Ul Ameen | H50: Novagen 500mg | I50: 72 | J50: 0 | K50: 131 | L50: =J50*I50 -> 0 | M50: =K50*I50 -> 9432 | N50: 0 | O50: =N50*I50 -> 0 | P50: =L50-O50 -> 0 | Q50: 414.72 | R50: =Q50*I50 -> 29859.84 | S50: =IFERROR(L50/R50,"-") -> 0 | T50: 0 | U50: =J50-T50 -> 0 | V50: =T50*I50 -> 0 | W50: =L50-V50 -> 0 | X50: =IFERROR(L50/V50-1,"-") -> - | Y50: =(J50)/1*1.5 -> 0 | Z50: =IF(Y50>K50,Y50-K50,0) -> 0 | AA50: =Z50*I50 -> 0 | AB50: =IF(Y50<K50,K50-Y50,0) -> 131 | AC50: =AB50*I50 -> 9432 | AD50: =Y50*I50 -> 0 | AE50: 0
A51: MEHRAN TRADERS, Mardan | B51: =IFERROR(VLOOKUP(A51,'Distributor List'!$A$2:$D$77,2,0),"-") -> Mardan | C51: =IFERROR(VLOOKUP(A51,'Distributor List'!$A$2:$D$77,3,0),"-") -> North-2 | D51: =IFERROR(VLOOKUP(A51,'Distributor List'!$A$2:$F$77,6,0),"-") -> Pak-2 | E51: =IFERROR(VLOOKUP(A51,'Distributor List'!$A$2:$D$77,4,0),"-") -> Distributor | F51: =IFERROR(VLOOKUP(H51,'Price List'!$A$2:$H$109,8,0),"-") -> Medicronis | G51: =IFERROR(VLOOKUP(A51,'Distributor List'!$A$2:$E$77,5,0),"-") -> Rooh Ul Ameen | H51: Novagen 1g | I51: 95 | J51: 0 | K51: 254 | L51: =J51*I51 -> 0 | M51: =K51*I51 -> 24130 | N51: 0 | O51: =N51*I51 -> 0 | P51: =L51-O51 -> 0 | Q51: 829.44 | R51: =Q51*I51 -> 78796.8 | S51: =IFERROR(L51/R51,"-") -> 0 | T51: 0 | U51: =J51-T51 -> 0 | V51: =T51*I51 -> 0 | W51: =L51-V51 -> 0 | X51: =IFERROR(L51/V51-1,"-") -> - | Y51: =(J51)/1*1.5 -> 0 | Z51: =IF(Y51>K51,Y51-K51,0) -> 0 | AA51: =Z51*I51 -> 0 | AB51: =IF(Y51<K51,K51-Y51,0) -> 254 | AC51: =AB51*I51 -> 24130 | AD51: =Y51*I51 -> 0 | AE51: 0
A52: MEHRAN TRADERS, Mardan | B52: =IFERROR(VLOOKUP(A52,'Distributor List'!$A$2:$D$77,2,0),"-") -> Mardan | C52: =IFERROR(VLOOKUP(A52,'Distributor List'!$A$2:$D$77,3,0),"-") -> North-2 | D52: =IFERROR(VLOOKUP(A52,'Distributor List'!$A$2:$F$77,6,0),"-") -> Pak-2 | E52: =IFERROR(VLOOKUP(A52,'Distributor List'!$A$2:$D$77,4,0),"-") -> Distributor | F52: =IFERROR(VLOOKUP(H52,'Price List'!$A$2:$H$109,8,0),"-") -> Transformer | G52: =IFERROR(VLOOKUP(A52,'Distributor List'!$A$2:$E$77,5,0),"-") -> Rooh Ul Ameen | H52: Ectafin 1G | I52: 391 | J52: 0 | K52: 4 | L52: =J52*I52 -> 0 | M52: =K52*I52 -> 1564 | N52: 0 | O52: =N52*I52 -> 0 | P52: =L52-O52 -> 0 | Q52: 0 | R52: =Q52*I52 -> 0 | S52: =IFERROR(L52/R52,"-") -> - | T52: 0 | U52: =J52-T52 -> 0 | V52: =T52*I52 -> 0 | W52: =L52-V52 -> 0 | X52: =IFERROR(L52/V52-1,"-") -> - | Y52: =(J52)/1*1.5 -> 0 | Z52: =IF(Y52>K52,Y52-K52,0) -> 0 | AA52: =Z52*I52 -> 0 | AB52: =IF(Y52<K52,K52-Y52,0) -> 4 | AC52: =AB52*I52 -> 1564 | AD52: =Y52*I52 -> 0 | AE52: 0
A53: MEHRAN TRADERS, Mardan | B53: =IFERROR(VLOOKUP(A53,'Distributor List'!$A$2:$D$77,2,0),"-") -> Mardan | C53: =IFERROR(VLOOKUP(A53,'Distributor List'!$A$2:$D$77,3,0),"-") -> North-2 | D53: =IFERROR(VLOOKUP(A53,'Distributor List'!$A$2:$F$77,6,0),"-") -> Pak-2 | E53: =IFERROR(VLOOKUP(A53,'Distributor List'!$A$2:$D$77,4,0),"-") -> Distributor | F53: =IFERROR(VLOOKUP(H53,'Price List'!$A$2:$H$109,8,0),"-") -> Transformer | G53: =IFERROR(VLOOKUP(A53,'Distributor List'!$A$2:$E$77,5,0),"-") -> Rooh Ul Ameen | H53: Ectafin 2G | I53: 616.25 | J53: 0 | K53: 5 | L53: =J53*I53 -> 0 | M53: =K53*I53 -> 3081.25 | N53: 0 | O53: =N53*I53 -> 0 | P53: =L53-O53 -> 0 | Q53: 0 | R53: =Q53*I53 -> 0 | S53: =IFERROR(L53/R53,"-") -> - | T53: 0 | U53: =J53-T53 -> 0 | V53: =T53*I53 -> 0 | W53: =L53-V53 -> 0 | X53: =IFERROR(L53/V53-1,"-") -> - | Y53: =(J53)/1*1.5 -> 0 | Z53: =IF(Y53>K53,Y53-K53,0) -> 0 | AA53: =Z53*I53 -> 0 | AB53: =IF(Y53<K53,K53-Y53,0) -> 5 | AC53: =AB53*I53 -> 3081.25 | AD53: =Y53*I53 -> 0 | AE53: 0
A54: MEHRAN TRADERS, Mardan | B54: =IFERROR(VLOOKUP(A54,'Distributor List'!$A$2:$D$77,2,0),"-") -> Mardan | C54: =IFERROR(VLOOKUP(A54,'Distributor List'!$A$2:$D$77,3,0),"-") -> North-2 | D54: =IFERROR(VLOOKUP(A54,'Distributor List'!$A$2:$F$77,6,0),"-") -> Pak-2 | E54: =IFERROR(VLOOKUP(A54,'Distributor List'!$A$2:$D$77,4,0),"-") -> Distributor | F54: =IFERROR(VLOOKUP(H54,'Price List'!$A$2:$H$109,8,0),"-") -> Medicronis | G54: =IFERROR(VLOOKUP(A54,'Distributor List'!$A$2:$E$77,5,0),"-") -> Rooh Ul Ameen | H54: Lancix Inj. 10s | I54: 270 | J54: 0 | K54: 397 | L54: =J54*I54 -> 0 | M54: =K54*I54 -> 107190 | N54: 1 | O54: =N54*I54 -> 270 | P54: =L54-O54 -> -270 | Q54: 84 | R54: =Q54*I54 -> 22680 | S54: =IFERROR(L54/R54,"-") -> 0 | T54: -3 | U54: =J54-T54 -> 3 | V54: =T54*I54 -> -810 | W54: =L54-V54 -> 810 | X54: =IFERROR(L54/V54-1,"-") -> -1 | Y54: =(J54)/1*1.5 -> 0 | Z54: =IF(Y54>K54,Y54-K54,0) -> 0 | AA54: =Z54*I54 -> 0 | AB54: =IF(Y54<K54,K54-Y54,0) -> 397 | AC54: =AB54*I54 -> 107190 | AD54: =Y54*I54 -> 0 | AE54: 0
A55: MEHRAN TRADERS, Mardan | B55: =IFERROR(VLOOKUP(A55,'Distributor List'!$A$2:$D$77,2,0),"-") -> Mardan | C55: =IFERROR(VLOOKUP(A55,'Distributor List'!$A$2:$D$77,3,0),"-") -> North-2 | D55: =IFERROR(VLOOKUP(A55,'Distributor List'!$A$2:$F$77,6,0),"-") -> Pak-2 | E55: =IFERROR(VLOOKUP(A55,'Distributor List'!$A$2:$D$77,4,0),"-") -> Distributor | F55: =IFERROR(VLOOKUP(H55,'Price List'!$A$2:$H$109,8,0),"-") -> Medicronis | G55: =IFERROR(VLOOKUP(A55,'Distributor List'!$A$2:$E$77,5,0),"-") -> Rooh Ul Ameen | H55: Lancix Inj. 25s | I55: 670 | J55: 1 | K55: 164 | L55: =J55*I55 -> 670 | M55: =K55*I55 -> 109880 | N55: 0 | O55: =N55*I55 -> 0 | P55: =L55-O55 -> 670 | Q55: 42 | R55: =Q55*I55 -> 28140 | S55: =IFERROR(L55/R55,"-") -> 0.023809524 | T55: 2 | U55: =J55-T55 -> -1 | V55: =T55*I55 -> 1340 | W55: =L55-V55 -> -670 | X55: =IFERROR(L55/V55-1,"-") -> -0.5 | Y55: =(J55)/1*1.5 -> 1.5 | Z55: =IF(Y55>K55,Y55-K55,0) -> 0 | AA55: =Z55*I55 -> 0 | AB55: =IF(Y55<K55,K55-Y55,0) -> 162.5 | AC55: =AB55*I55 -> 108875 | AD55: =Y55*I55 -> 1005 | AE55: 0
A56: MEHRAN TRADERS, Mardan | B56: =IFERROR(VLOOKUP(A56,'Distributor List'!$A$2:$D$77,2,0),"-") -> Mardan | C56: =IFERROR(VLOOKUP(A56,'Distributor List'!$A$2:$D$77,3,0),"-") -> North-2 | D56: =IFERROR(VLOOKUP(A56,'Distributor List'!$A$2:$F$77,6,0),"-") -> Pak-2 | E56: =IFERROR(VLOOKUP(A56,'Distributor List'!$A$2:$D$77,4,0),"-") -> Distributor | F56: =IFERROR(VLOOKUP(H56,'Price List'!$A$2:$H$109,8,0),"-") -> Medicronis | G56: =IFERROR(VLOOKUP(A56,'Distributor List'!$A$2:$E$77,5,0),"-") -> Rooh Ul Ameen | H56: G.Tax 250mg | I56: 58 | J56: 0 | K56: 221 | L56: =J56*I56 -> 0 | M56: =K56*I56 -> 12818 | N56: 0 | O56: =N56*I56 -> 0 | P56: =L56-O56 -> 0 | Q56: 83.34 | R56: =Q56*I56 -> 4833.72 | S56: =IFERROR(L56/R56,"-") -> 0 | T56: 0 | U56: =J56-T56 -> 0 | V56: =T56*I56 -> 0 | W56: =L56-V56 -> 0 | X56: =IFERROR(L56/V56-1,"-") -> - | Y56: =(J56)/1*1.5 -> 0 | Z56: =IF(Y56>K56,Y56-K56,0) -> 0 | AA56: =Z56*I56 -> 0 | AB56: =IF(Y56<K56,K56-Y56,0) -> 221 | AC56: =AB56*I56 -> 12818 | AD56: =Y56*I56 -> 0 | AE56: 0
A57: MEHRAN TRADERS, Mardan | B57: =IFERROR(VLOOKUP(A57,'Distributor List'!$A$2:$D$77,2,0),"-") -> Mardan | C57: =IFERROR(VLOOKUP(A57,'Distributor List'!$A$2:$D$77,3,0),"-") -> North-2 | D57: =IFERROR(VLOOKUP(A57,'Distributor List'!$A$2:$F$77,6,0),"-") -> Pak-2 | E57: =IFERROR(VLOOKUP(A57,'Distributor List'!$A$2:$D$77,4,0),"-") -> Distributor | F57: =IFERROR(VLOOKUP(H57,'Price List'!$A$2:$H$109,8,0),"-") -> Medicronis | G57: =IFERROR(VLOOKUP(A57,'Distributor List'!$A$2:$E$77,5,0),"-") -> Rooh Ul Ameen | H57: G.Tax 500mg | I57: 56 | J57: 0 | K57: 23 | L57: =J57*I57 -> 0 | M57: =K57*I57 -> 1288 | N57: 0 | O57: =N57*I57 -> 0 | P57: =L57-O57 -> 0 | Q57: 80.37 | R57: =Q57*I57 -> 4500.72 | S57: =IFERROR(L57/R57,"-") -> 0 | T57: 0 | U57: =J57-T57 -> 0 | V57: =T57*I57 -> 0 | W57: =L57-V57 -> 0 | X57: =IFERROR(L57/V57-1,"-") -> - | Y57: =(J57)/1*1.5 -> 0 | Z57: =IF(Y57>K57,Y57-K57,0) -> 0 | AA57: =Z57*I57 -> 0 | AB57: =IF(Y57<K57,K57-Y57,0) -> 23 | AC57: =AB57*I57 -> 1288 | AD57: =Y57*I57 -> 0 | AE57: 0
... A66: MEHRAN TRADERS, Mardan | B66: =IFERROR(VLOOKUP(A66,'Distributor List'!$A$2:$D$77,2,0),"-") -> Mardan | C66: =IFERROR(VLOOKUP(A66,'Distributor List'!$A$2:$D$77,3,0),"-") -> North-2 | D66: =IFERROR(VLOOKUP(A66,'Distributor List'!$A$2:$F$77,6,0),"-") -> Pak-2 | E66: =IFERROR(VLOOKUP(A66,'Distributor List'!$A$2:$D$77,4,0),"-") -> Distributor | F66: =IFERROR(VLOOKUP(H66,'Price List'!$A$2:$H$109,8,0),"-") -> Medicronis | G66: =IFERROR(VLOOKUP(A66,'Distributor List'!$A$2:$E$77,5,0),"-") -> Rooh Ul Ameen | H66: Hostenil Syrup 120ml | I66: 90 | J66: 0 | K66: 11 | L66: =J66*I66 -> 0 | M66: =K66*I66 -> 990 | N66: 0 | O66: =N66*I66 -> 0 | P66: =L66-O66 -> 0 | Q66: 0 | R66: =Q66*I66 -> 0 | S66: =IFERROR(L66/R66,"-") -> - | T66: 0 | U66: =J66-T66 -> 0 | V66: =T66*I66 -> 0 | W66: =L66-V66 -> 0 | X66: =IFERROR(L66/V66-1,"-") -> - | Y66: =(J66)/1*1.5 -> 0 | Z66: =IF(Y66>K66,Y66-K66,0) -> 0 | AA66: =Z66*I66 -> 0 | AB66: =IF(Y66<K66,K66-Y66,0) -> 11 | AC66: =AB66*I66 -> 990 | AD66: =Y66*I66 -> 0 | AE66: 0
A67: MEHRAN TRADERS, Mardan | B67: =IFERROR(VLOOKUP(A67,'Distributor List'!$A$2:$D$77,2,0),"-") -> Mardan | C67: =IFERROR(VLOOKUP(A67,'Distributor List'!$A$2:$D$77,3,0),"-") -> North-2 | D67: =IFERROR(VLOOKUP(A67,'Distributor List'!$A$2:$F$77,6,0),"-") -> Pak-2 | E67: =IFERROR(VLOOKUP(A67,'Distributor List'!$A$2:$D$77,4,0),"-") -> Distributor | F67: =IFERROR(VLOOKUP(H67,'Price List'!$A$2:$H$109,8,0),"-") -> Medicronis | G67: =IFERROR(VLOOKUP(A67,'Distributor List'!$A$2:$E$77,5,0),"-") -> Rooh Ul Ameen | H67: kufxy Syp 120ml | I67: 99 | J67: 10 | K67: 327 | L67: =J67*I67 -> 990 | N67: 15 | O67: =N67*I67 -> 1485 | P67: =L67-O67 -> -495 | Q67: 84 | R67: =Q67*I67 -> 8316 | S67: =IFERROR(L67/R67,"-") -> 0.11904762 | T67: 13 | U67: =J67-T67 -> -3 | V67: =T67*I67 -> 1287 | W67: =L67-V67 -> -297 | X67: =IFERROR(L67/V67-1,"-") -> -0.23076923 | Y67: =(J67)/1*1.5 -> 15 | Z67: =IF(Y67>K67,Y67-K67,0) -> 0 | AA67: =Z67*I67 -> 0 | AB67: =IF(Y67<K67,K67-Y67,0) -> 312 | AC67: =AB67*I67 -> 30888 | AD67: =Y67*I67 -> 1485
A68: MEHRAN TRADERS, Mardan | B68: =IFERROR(VLOOKUP(A68,'Distributor List'!$A$2:$D$77,2,0),"-") -> Mardan | C68: =IFERROR(VLOOKUP(A68,'Distributor List'!$A$2:$D$77,3,0),"-") -> North-2 | D68: =IFERROR(VLOOKUP(A68,'Distributor List'!$A$2:$F$77,6,0),"-") -> Pak-2 | E68: =IFERROR(VLOOKUP(A68,'Distributor List'!$A$2:$D$77,4,0),"-") -> Distributor | F68: =IFERROR(VLOOKUP(H68,'Price List'!$A$2:$H$109,8,0),"-") -> Medicronis | G68: =IFERROR(VLOOKUP(A68,'Distributor List'!$A$2:$E$77,5,0),"-") -> Rooh Ul Ameen | H68: Salberry Sachet 10s | I68: 105 | J68: 0 | K68: 67 | L68: =J68*I68 -> 0 | M68: =K68*I68 -> 7035 | N68: 0 | O68: =N68*I68 -> 0 | P68: =L68-O68 -> 0 | Q68: 0 | R68: =Q68*I68 -> 0 | S68: =IFERROR(L68/R68,"-") -> - | T68: 6 | U68: =J68-T68 -> -6 | V68: =T68*I68 -> 630 | W68: =L68-V68 -> -630 | X68: =IFERROR(L68/V68-1,"-") -> -1 | Y68: =(J68)/1*1.5 -> 0 | Z68: =IF(Y68>K68,Y68-K68,0) -> 0 | AA68: =Z68*I68 -> 0 | AB68: =IF(Y68<K68,K68-Y68,0) -> 67 | AC68: =AB68*I68 -> 7035 | AD68: =Y68*I68 -> 0 | AE68: 0
A69: MEHRAN TRADERS, Mardan | B69: =IFERROR(VLOOKUP(A69,'Distributor List'!$A$2:$D$77,2,0),"-") -> Mardan | C69: =IFERROR(VLOOKUP(A69,'Distributor List'!$A$2:$D$77,3,0),"-") -> North-2 | D69: =IFERROR(VLOOKUP(A69,'Distributor List'!$A$2:$F$77,6,0),"-") -> Pak-2 | E69: =IFERROR(VLOOKUP(A69,'Distributor List'!$A$2:$D$77,4,0),"-") -> Distributor | F69: =IFERROR(VLOOKUP(H69,'Price List'!$A$2:$H$109,8,0),"-") -> Medicronis | G69: =IFERROR(VLOOKUP(A69,'Distributor List'!$A$2:$E$77,5,0),"-") -> Rooh Ul Ameen | H69: Berry Flow Sachet | I69: 115 | J69: 50 | K69: 0 | L69: =J69*I69 -> 5750 | M69: =K69*I69 -> 0 | N69: 50 | O69: =N69*I69 -> 5750 | P69: =L69-O69 -> 0 | Q69: 72 | R69: =Q69*I69 -> 8280 | S69: =IFERROR(L69/R69,"-") -> 0.69444444 | T69: 0 | U69: =J69-T69 -> 50 | V69: =T69*I69 -> 0 | W69: =L69-V69 -> 5750 | X69: =IFERROR(L69/V69-1,"-") -> - | Y69: =(J69)/1*1.5 -> 75 | Z69: =IF(Y69>K69,Y69-K69,0) -> 75 | AA69: =Z69*I69 -> 8625 | AB69: =IF(Y69<K69,K69-Y69,0) -> 0 | AC69: =AB69*I69 -> 0 | AD69: =Y69*I69 -> 8625 | AE69: 0
A70: MEHRAN TRADERS, Mardan | B70: =IFERROR(VLOOKUP(A70,'Distributor List'!$A$2:$D$77,2,0),"-") -> Mardan | C70: =IFERROR(VLOOKUP(A70,'Distributor List'!$A$2:$D$77,3,0),"-") -> North-2 | D70: =IFERROR(VLOOKUP(A70,'Distributor List'!$A$2:$F$77,6,0),"-") -> Pak-2 | E70: =IFERROR(VLOOKUP(A70,'Distributor List'!$A$2:$D$77,4,0),"-") -> Distributor | F70: =IFERROR(VLOOKUP(H70,'Price List'!$A$2:$H$109,8,0),"-") -> Medicronis | G70: =IFERROR(VLOOKUP(A70,'Distributor List'!$A$2:$E$77,5,0),"-") -> Rooh Ul Ameen | H70: Cipak 200mg/100ml Inf | I70: 102 | J70: 0 | K70: 1 | L70: =J70*I70 -> 0 | M70: =K70*I70 -> 102 | N70: 0 | O70: =N70*I70 -> 0 | P70: =L70-O70 -> 0 | Q70: 316.4925 | R70: =Q70*I70 -> 32282.235 | S70: =IFERROR(L70/R70,"-") -> 0 | T70: 0 | U70: =J70-T70 -> 0 | V70: =T70*I70 -> 0 | W70: =L70-V70 -> 0 | X70: =IFERROR(L70/V70-1,"-") -> - | Y70: =(J70)/1*1.5 -> 0 | Z70: =IF(Y70>K70,Y70-K70,0) -> 0 | AA70: =Z70*I70 -> 0 | AB70: =IF(Y70<K70,K70-Y70,0) -> 1 | AC70: =AB70*I70 -> 102 | AD70: =Y70*I70 -> 0 | AE70: 0
A71: MEHRAN TRADERS, Mardan | B71: =IFERROR(VLOOKUP(A71,'Distributor List'!$A$2:$D$77,2,0),"-") -> Mardan | C71: =IFERROR(VLOOKUP(A71,'Distributor List'!$A$2:$D$77,3,0),"-") -> North-2 | D71: =IFERROR(VLOOKUP(A71,'Distributor List'!$A$2:$F$77,6,0),"-") -> Pak-2 | E71: =IFERROR(VLOOKUP(A71,'Distributor List'!$A$2:$D$77,4,0),"-") -> Distributor | F71: =IFERROR(VLOOKUP(H71,'Price List'!$A$2:$H$109,8,0),"-") -> Transformer | G71: =IFERROR(VLOOKUP(A71,'Distributor List'!$A$2:$E$77,5,0),"-") -> Rooh Ul Ameen | H71: Maxy 400mg/250ml Inf | I71: 299 | J71: 0 | K71: 10 | L71: =J71*I71 -> 0 | M71: =K71*I71 -> 2990 | N71: 0 | O71: =N71*I71 -> 0 | P71: =L71-O71 -> 0 | Q71: 0 | R71: =Q71*I71 -> 0 | S71: =IFERROR(L71/R71,"-") -> - | T71: 0 | U71: =J71-T71 -> 0 | V71: =T71*I71 -> 0 | W71: =L71-V71 -> 0 | X71: =IFERROR(L71/V71-1,"-") -> - | Y71: =(J71)/1*1.5 -> 0 | Z71: =IF(Y71>K71,Y71-K71,0) -> 0 | AA71: =Z71*I71 -> 0 | AB71: =IF(Y71<K71,K71-Y71,0) -> 10 | AC71: =AB71*I71 -> 2990 | AD71: =Y71*I71 -> 0 | AE71: 0
A72: MEHRAN TRADERS, Mardan | B72: =IFERROR(VLOOKUP(A72,'Distributor List'!$A$2:$D$77,2,0),"-") -> Mardan | C72: =IFERROR(VLOOKUP(A72,'Distributor List'!$A$2:$D$77,3,0),"-") -> North-2 | D72: =IFERROR(VLOOKUP(A72,'Distributor List'!$A$2:$F$77,6,0),"-") -> Pak-2 | E72: =IFERROR(VLOOKUP(A72,'Distributor List'!$A$2:$D$77,4,0),"-") -> Distributor | F72: =IFERROR(VLOOKUP(H72,'Price List'!$A$2:$H$109,8,0),"-") -> Transformer | G72: =IFERROR(VLOOKUP(A72,'Distributor List'!$A$2:$E$77,5,0),"-") -> Rooh Ul Ameen | H72: Evox 500mg/100ml Inf | I72: 403.75 | J72: 0 | K72: 1 | L72: =J72*I72 -> 0 | M72: =K72*I72 -> 403.75 | N72: 0 | O72: =N72*I72 -> 0 | P72: =L72-O72 -> 0 | Q72: 0 | R72: =Q72*I72 -> 0 | S72: =IFERROR(L72/R72,"-") -> - | T72: 0 | U72: =J72-T72 -> 0 | V72: =T72*I72 -> 0 | W72: =L72-V72 -> 0 | X72: =IFERROR(L72/V72-1,"-") -> - | Y72: =(J72)/1*1.5 -> 0 | Z72: =IF(Y72>K72,Y72-K72,0) -> 0 | AA72: =Z72*I72 -> 0 | AB72: =IF(Y72<K72,K72-Y72,0) -> 1 | AC72: =AB72*I72 -> 403.75 | AD72: =Y72*I72 -> 0 | AE72: 0
A73: MEHRAN TRADERS, Mardan | B73: =IFERROR(VLOOKUP(A73,'Distributor List'!$A$2:$D$77,2,0),"-") -> Mardan | C73: =IFERROR(VLOOKUP(A73,'Distributor List'!$A$2:$D$77,3,0),"-") -> North-2 | D73: =IFERROR(VLOOKUP(A73,'Distributor List'!$A$2:$F$77,6,0),"-") -> Pak-2 | E73: =IFERROR(VLOOKUP(A73,'Distributor List'!$A$2:$D$77,4,0),"-") -> Distributor | F73: =IFERROR(VLOOKUP(H73,'Price List'!$A$2:$H$109,8,0),"-") -> Medicronis | G73: =IFERROR(VLOOKUP(A73,'Distributor List'!$A$2:$E$77,5,0),"-") -> Rooh Ul Ameen | H73: Nida 200mg/100ml Inf | I73: 102 | J73: 18 | K73: 2 | L73: =J73*I73 -> 1836 | M73: =K73*I73 -> 204 | N73: 18 | O73: =N73*I73 -> 1836 | P73: =L73-O73 -> 0 | Q73: 782.44375 | R73: =Q73*I73 -> 79809.262 | S73: =IFERROR(L73/R73,"-") -> 0.023004849 | T73: 140 | U73: =J73-T73 -> -122 | V73: =T73*I73 -> 14280 | W73: =L73-V73 -> -12444 | X73: =IFERROR(L73/V73-1,"-") -> -0.87142857 | Y73: =(J73)/1*1.5 -> 27 | Z73: =IF(Y73>K73,Y73-K73,0) -> 25 | AA73: =Z73*I73 -> 2550 | AB73: =IF(Y73<K73,K73-Y73,0) -> 0 | AC73: =AB73*I73 -> 0 | AD73: =Y73*I73 -> 2754 | AE73: 0
A74: MEHRAN TRADERS, Mardan | B74: =IFERROR(VLOOKUP(A74,'Distributor List'!$A$2:$D$77,2,0),"-") -> Mardan | C74: =IFERROR(VLOOKUP(A74,'Distributor List'!$A$2:$D$77,3,0),"-") -> North-2 | D74: =IFERROR(VLOOKUP(A74,'Distributor List'!$A$2:$F$77,6,0),"-") -> Pak-2 | E74: =IFERROR(VLOOKUP(A74,'Distributor List'!$A$2:$D$77,4,0),"-") -> Distributor | F74: =IFERROR(VLOOKUP(H74,'Price List'!$A$2:$H$109,8,0),"-") -> Medicronis | G74: =IFERROR(VLOOKUP(A74,'Distributor List'!$A$2:$E$77,5,0),"-") -> Rooh Ul Ameen | H74: CefPak 250mg Iv Inj | I74: 53 | J74: 0 | K74: 186 | L74: =J74*I74 -> 0 | M74: =K74*I74 -> 9858 | N74: 0 | O74: =N74*I74 -> 0 | P74: =L74-O74 -> 0 | Q74: 0 | R74: =Q74*I74 -> 0 | S74: =IFERROR(L74/R74,"-") -> - | T74: 0 | U74: =J74-T74 -> 0 | V74: =T74*I74 -> 0 | W74: =L74-V74 -> 0 | X74: =IFERROR(L74/V74-1,"-") -> - | Y74: =(J74)/1*1.5 -> 0 | Z74: =IF(Y74>K74,Y74-K74,0) -> 0 | AA74: =Z74*I74 -> 0 | AB74: =IF(Y74<K74,K74-Y74,0) -> 186 | AC74: =AB74*I74 -> 9858 | AD74: =Y74*I74 -> 0 | AE74: 0
A75: MEHRAN TRADERS, Mardan | B75: =IFERROR(VLOOKUP(A75,'Distributor List'!$A$2:$D$77,2,0),"-") -> Mardan | C75: =IFERROR(VLOOKUP(A75,'Distributor List'!$A$2:$D$77,3,0),"-") -> North-2 | D75: =IFERROR(VLOOKUP(A75,'Distributor List'!$A$2:$F$77,6,0),"-") -> Pak-2 | E75: =IFERROR(VLOOKUP(A75,'Distributor List'!$A$2:$D$77,4,0),"-") -> Distributor | F75: =IFERROR(VLOOKUP(H75,'Price List'!$A$2:$H$109,8,0),"-") -> Medicronis | G75: =IFERROR(VLOOKUP(A75,'Distributor List'!$A$2:$E$77,5,0),"-") -> Rooh Ul Ameen | H75: CefPak 500mg Iv Inj | I75: 69 | J75: 0 | K75: 0 | L75: =J75*I75 -> 0 | M75: =K75*I75 -> 0 | N75: 0 | O75: =N75*I75 -> 0 | P75: =L75-O75 -> 0 | Q75: 0 | R75: =Q75*I75 -> 0 | S75: =IFERROR(L75/R75,"-") -> - | T75: 0 | U75: =J75-T75 -> 0 | V75: =T75*I75 -> 0 | W75: =L75-V75 -> 0 | X75: =IFERROR(L75/V75-1,"-") -> - | Y75: =(J75)/1*1.5 -> 0 | Z75: =IF(Y75>K75,Y75-K75,0) -> 0 | AA75: =Z75*I75 -> 0 | AB75: =IF(Y75<K75,K75-Y75,0) -> 0 | AC75: =AB75*I75 -> 0 | AD75: =Y75*I75 -> 0 | AE75: 0
A76: MEHRAN TRADERS, Mardan | B76: =IFERROR(VLOOKUP(A76,'Distributor List'!$A$2:$D$77,2,0),"-") -> Mardan | C76: =IFERROR(VLOOKUP(A76,'Distributor List'!$A$2:$D$77,3,0),"-") -> North-2 | D76: =IFERROR(VLOOKUP(A76,'Distributor List'!$A$2:$F$77,6,0),"-") -> Pak-2 | E76: =IFERROR(VLOOKUP(A76,'Distributor List'!$A$2:$D$77,4,0),"-") -> Distributor | F76: =IFERROR(VLOOKUP(H76,'Price List'!$A$2:$H$109,8,0),"-") -> Medicronis | G76: =IFERROR(VLOOKUP(A76,'Distributor List'!$A$2:$E$77,5,0),"-") -> Rooh Ul Ameen | H76: CefPak 1G Iv Inj | I76: 90 | J76: 0 | K76: 0 | L76: =J76*I76 -> 0 | M76: =K76*I76 -> 0 | N76: 0 | O76: =N76*I76 -> 0 | P76: =L76-O76 -> 0 | Q76: 0 | R76: =Q76*I76 -> 0 | S76: =IFERROR(L76/R76,"-") -> - | T76: 0 | U76: =J76-T76 -> 0 | V76: =T76*I76 -> 0 | W76: =L76-V76 -> 0 | X76: =IFERROR(L76/V76-1,"-") -> - | Y76: =(J76)/1*1.5 -> 0 | Z76: =IF(Y76>K76,Y76-K76,0) -> 0 | AA76: =Z76*I76 -> 0 | AB76: =IF(Y76<K76,K76-Y76,0) -> 0 | AC76: =AB76*I76 -> 0 | AD76: =Y76*I76 -> 0 | AE76: 0
A77: MEHRAN TRADERS, Mardan | B77: =IFERROR(VLOOKUP(A77,'Distributor List'!$A$2:$D$77,2,0),"-") -> Mardan | C77: =IFERROR(VLOOKUP(A77,'Distributor List'!$A$2:$D$77,3,0),"-") -> North-2 | D77: =IFERROR(VLOOKUP(A77,'Distributor List'!$A$2:$F$77,6,0),"-") -> Pak-2 | E77: =IFERROR(VLOOKUP(A77,'Distributor List'!$A$2:$D$77,4,0),"-") -> Distributor | F77: =IFERROR(VLOOKUP(H77,'Price List'!$A$2:$H$109,8,0),"-") -> Medicronis | G77: =IFERROR(VLOOKUP(A77,'Distributor List'!$A$2:$E$77,5,0),"-") -> Rooh Ul Ameen | H77: PeerGo Gel 30g | I77: 110 | J77: 9 | K77: 1 | L77: =J77*I77 -> 990 | M77: =K77*I77 -> 110 | N77: 8 | O77: =N77*I77 -> 880 | P77: =L77-O77 -> 110 | Q77: 48 | R77: =Q77*I77 -> 5280 | S77: =IFERROR(L77/R77,"-") -> 0.1875 | T77: 8 | U77: =J77-T77 -> 1 | V77: =T77*I77 -> 880 | W77: =L77-V77 -> 110 | X77: =IFERROR(L77/V77-1,"-") -> 0.125 | Y77: =(J77)/1*1.5 -> 13.5 | Z77: =IF(Y77>K77,Y77-K77,0) -> 12.5 | AA77: =Z77*I77 -> 1375 | AB77: =IF(Y77<K77,K77-Y77,0) -> 0 | AC77: =AB77*I77 -> 0 | AD77: =Y77*I77 -> 1485 | AE77: 0
A78: MEHRAN TRADERS, Mardan | B78: =IFERROR(VLOOKUP(A78,'Distributor List'!$A$2:$D$77,2,0),"-") -> Mardan | C78: =IFERROR(VLOOKUP(A78,'Distributor List'!$A$2:$D$77,3,0),"-") -> North-2 | D78: =IFERROR(VLOOKUP(A78,'Distributor List'!$A$2:$F$77,6,0),"-") -> Pak-2 | E78: =IFERROR(VLOOKUP(A78,'Distributor List'!$A$2:$D$77,4,0),"-") -> Distributor | F78: =IFERROR(VLOOKUP(H78,'Price List'!$A$2:$H$109,8,0),"-") -> Medicronis | G78: =IFERROR(VLOOKUP(A78,'Distributor List'!$A$2:$E$77,5,0),"-") -> Rooh Ul Ameen | H78: Mediscon Syp 120ml | I78: 105 | J78: 260 | K78: 159 | L78: =J78*I78 -> 27300 | M78: =K78*I78 -> 16695 | N78: 151 | O78: =N78*I78 -> 15855 | P78: =L78-O78 -> 11445 | Q78: 486 | R78: =Q78*I78 -> 51030 | S78: =IFERROR(L78/R78,"-") -> 0.53497942 | T78: 61 | U78: =J78-T78 -> 199 | V78: =T78*I78 -> 6405 | W78: =L78-V78 -> 20895 | X78: =IFERROR(L78/V78-1,"-") -> 3.2622951 | Y78: =(J78)/1*1.5 -> 390 | Z78: =IF(Y78>K78,Y78-K78,0) -> 231 | AA78: =Z78*I78 -> 24255 | AB78: =IF(Y78<K78,K78-Y78,0) -> 0 | AC78: =AB78*I78 -> 0 | AD78: =Y78*I78 -> 40950 | AE78: 0
A79: MEHRAN TRADERS, Mardan | B79: =IFERROR(VLOOKUP(A79,'Distributor List'!$A$2:$D$77,2,0),"-") -> Mardan | C79: =IFERROR(VLOOKUP(A79,'Distributor List'!$A$2:$D$77,3,0),"-") -> North-2 | D79: =IFERROR(VLOOKUP(A79,'Distributor List'!$A$2:$F$77,6,0),"-") -> Pak-2 | E79: =IFERROR(VLOOKUP(A79,'Distributor List'!$A$2:$D$77,4,0),"-") -> Distributor | F79: =IFERROR(VLOOKUP(H79,'Price List'!$A$2:$H$109,8,0),"-") -> Medicronis | G79: =IFERROR(VLOOKUP(A79,'Distributor List'!$A$2:$E$77,5,0),"-") -> Rooh Ul Ameen | H79: KhaajGo Soap Bar | I79: 120 | J79: 0 | K79: 15 | L79: =J79*I79 -> 0 | M79: =K79*I79 -> 1800 | N79: 0 | O79: =N79*I79 -> 0 | P79: =L79-O79 -> 0 | Q79: 54 | R79: =Q79*I79 -> 6480 | S79: =IFERROR(L79/R79,"-") -> 0 | T79: 13 | U79: =J79-T79 -> -13 | V79: =T79*I79 -> 1560 | W79: =L79-V79 -> -1560 | X79: =IFERROR(L79/V79-1,"-") -> -1 | Y79: =(J79)/1*1.5 -> 0 | Z79: =IF(Y79>K79,Y79-K79,0) -> 0 | AA79: =Z79*I79 -> 0 | AB79: =IF(Y79<K79,K79-Y79,0) -> 15 | AC79: =AB79*I79 -> 1800 | AD79: =Y79*I79 -> 0 | AE79: 0
... A87: MEHRAN TRADERS, Mardan | B87: =IFERROR(VLOOKUP(A87,'Distributor List'!$A$2:$D$77,2,0),"-") -> Mardan | C87: =IFERROR(VLOOKUP(A87,'Distributor List'!$A$2:$D$77,3,0),"-") -> North-2 | D87: =IFERROR(VLOOKUP(A87,'Distributor List'!$A$2:$F$77,6,0),"-") -> Pak-2 | E87: =IFERROR(VLOOKUP(A87,'Distributor List'!$A$2:$D$77,4,0),"-") -> Distributor | F87: =IFERROR(VLOOKUP(H87,'Price List'!$A$2:$H$109,8,0),"-") -> Medicronis | G87: =IFERROR(VLOOKUP(A87,'Distributor List'!$A$2:$E$77,5,0),"-") -> Rooh Ul Ameen | H87: Medelac Syp 120ml | I87: 105 | J87: 64 | K87: 315 | L87: =J87*I87 -> 6720 | M87: =K87*I87 -> 33075 | N87: 44 | O87: =N87*I87 -> 4620 | P87: =L87-O87 -> 2100 | Q87: 144 | R87: =Q87*I87 -> 15120 | S87: =IFERROR(L87/R87,"-") -> 0.44444444 | T87: 161 | U87: =J87-T87 -> -97 | V87: =T87*I87 -> 16905 | W87: =L87-V87 -> -10185 | X87: =IFERROR(L87/V87-1,"-") -> -0.60248447 | Y87: =(J87)/1*1.5 -> 96 | Z87: =IF(Y87>K87,Y87-K87,0) -> 0 | AA87: =Z87*I87 -> 0 | AB87: =IF(Y87<K87,K87-Y87,0) -> 219 | AC87: =AB87*I87 -> 22995 | AD87: =Y87*I87 -> 10080 | AE87: 0
A88: MEHRAN TRADERS, Mardan | B88: =IFERROR(VLOOKUP(A88,'Distributor List'!$A$2:$D$77,2,0),"-") -> Mardan | C88: =IFERROR(VLOOKUP(A88,'Distributor List'!$A$2:$D$77,3,0),"-") -> North-2 | D88: =IFERROR(VLOOKUP(A88,'Distributor List'!$A$2:$F$77,6,0),"-") -> Pak-2 | E88: =IFERROR(VLOOKUP(A88,'Distributor List'!$A$2:$D$77,4,0),"-") -> Distributor | F88: =IFERROR(VLOOKUP(H88,'Price List'!$A$2:$H$109,8,0),"-") -> Medicronis | G88: =IFERROR(VLOOKUP(A88,'Distributor List'!$A$2:$E$77,5,0),"-") -> Rooh Ul Ameen | H88: Medizek 20mg | I88: 90 | J88: 0 | K88: 0 | L88: =J88*I88 -> 0 | M88: =K88*I88 -> 0 | N88: 0 | O88: =N88*I88 -> 0 | P88: =L88-O88 -> 0 | Q88: 0 | R88: 0 | S88: =IFERROR(L88/R88,"-") -> - | T88: 0 | U88: 0 | V88: =T88*I88 -> 0 | W88: =L88-V88 -> 0 | X88: =IFERROR(L88/V88-1,"-") -> - | Y88: =(J88)/1*1.5 -> 0 | Z88: =IF(Y88>K88,Y88-K88,0) -> 0 | AA88: =Z88*I88 -> 0 | AB88: =IF(Y88<K88,K88-Y88,0) -> 0 | AC88: =AB88*I88 -> 0 | AD88: =Y88*I88 -> 0 | AE88: 0
A89: MEHRAN TRADERS, Mardan | B89: =IFERROR(VLOOKUP(A89,'Distributor List'!$A$2:$D$77,2,0),"-") -> Mardan | C89: =IFERROR(VLOOKUP(A89,'Distributor List'!$A$2:$D$77,3,0),"-") -> North-2 | D89: =IFERROR(VLOOKUP(A89,'Distributor List'!$A$2:$F$77,6,0),"-") -> Pak-2 | E89: =IFERROR(VLOOKUP(A89,'Distributor List'!$A$2:$D$77,4,0),"-") -> Distributor | F89: =IFERROR(VLOOKUP(H89,'Price List'!$A$2:$H$109,8,0),"-") -> Medicronis | G89: =IFERROR(VLOOKUP(A89,'Distributor List'!$A$2:$E$77,5,0),"-") -> Rooh Ul Ameen | H89: Medizek 40mg | I89: 105 | J89: 0 | K89: 0 | L89: =J89*I89 -> 0 | M89: =K89*I89 -> 0 | N89: 0 | O89: =N89*I89 -> 0 | P89: =L89-O89 -> 0 | Q89: 0 | R89: 0 | S89: =IFERROR(L89/R89,"-") -> - | T89: 0 | U89: 0 | V89: =T89*I89 -> 0 | W89: =L89-V89 -> 0 | X89: =IFERROR(L89/V89-1,"-") -> - | Y89: =(J89)/1*1.5 -> 0 | Z89: =IF(Y89>K89,Y89-K89,0) -> 0 | AA89: =Z89*I89 -> 0 | AB89: =IF(Y89<K89,K89-Y89,0) -> 0 | AC89: =AB89*I89 -> 0 | AD89: =Y89*I89 -> 0 | AE89: 0
A90: MEHRAN TRADERS, Mardan | B90: =IFERROR(VLOOKUP(A90,'Distributor List'!$A$2:$D$77,2,0),"-") -> Mardan | C90: =IFERROR(VLOOKUP(A90,'Distributor List'!$A$2:$D$77,3,0),"-") -> North-2 | D90: =IFERROR(VLOOKUP(A90,'Distributor List'!$A$2:$F$77,6,0),"-") -> Pak-2 | E90: =IFERROR(VLOOKUP(A90,'Distributor List'!$A$2:$D$77,4,0),"-") -> Distributor | F90: =IFERROR(VLOOKUP(H90,'Price List'!$A$2:$H$109,8,0),"-") -> Medicronis | G90: =IFERROR(VLOOKUP(A90,'Distributor List'!$A$2:$E$77,5,0),"-") -> Rooh Ul Ameen | H90: Medizek INJ | I90: 120 | J90: 0 | K90: 0 | L90: =J90*I90 -> 0 | M90: =K90*I90 -> 0 | N90: 0 | O90: =N90*I90 -> 0 | P90: =L90-O90 -> 0 | Q90: 0 | R90: 0 | S90: =IFERROR(L90/R90,"-") -> - | T90: 0 | U90: 0 | V90: =T90*I90 -> 0 | W90: =L90-V90 -> 0 | X90: =IFERROR(L90/V90-1,"-") -> - | Y90: =(J90)/1*1.5 -> 0 | Z90: =IF(Y90>K90,Y90-K90,0) -> 0 | AA90: =Z90*I90 -> 0 | AB90: =IF(Y90<K90,K90-Y90,0) -> 0 | AC90: =AB90*I90 -> 0 | AD90: =Y90*I90 -> 0 | AE90: 0
A91: MEHRAN TRADERS, Mardan | B91: =IFERROR(VLOOKUP(A91,'Distributor List'!$A$2:$D$77,2,0),"-") -> Mardan | C91: =IFERROR(VLOOKUP(A91,'Distributor List'!$A$2:$D$77,3,0),"-") -> North-2 | D91: =IFERROR(VLOOKUP(A91,'Distributor List'!$A$2:$F$77,6,0),"-") -> Pak-2 | E91: =IFERROR(VLOOKUP(A91,'Distributor List'!$A$2:$D$77,4,0),"-") -> Distributor | F91: =IFERROR(VLOOKUP(H91,'Price List'!$A$2:$H$109,8,0),"-") -> Medicronis | G91: =IFERROR(VLOOKUP(A91,'Distributor List'!$A$2:$E$77,5,0),"-") -> Rooh Ul Ameen | H91: Paxcal Syrup 120ml | I91: 105 | J91: 65 | K91: 81 | L91: =J91*I91 -> 6825 | M91: =K91*I91 -> 8505 | N91: 29 | O91: =N91*I91 -> 3045 | P91: =L91-O91 -> 3780 | Q91: 75 | R91: =Q91*I91 -> 7875 | S91: =IFERROR(L91/R91,"-") -> 0.86666667 | T91: 3 | U91: =J91-T91 -> 62 | V91: =T91*I91 -> 315 | W91: =L91-V91 -> 6510 | X91: =IFERROR(L91/V91-1,"-") -> 20.666667 | Y91: =(J91)/1*1.5 -> 97.5 | Z91: =IF(Y91>K91,Y91-K91,0) -> 16.5 | AA91: =Z91*I91 -> 1732.5 | AB91: =IF(Y91<K91,K91-Y91,0) -> 0 | AC91: =AB91*I91 -> 0 | AD91: =Y91*I91 -> 10237.5 | AE91: 0
A92: MEHRAN TRADERS, Mardan | B92: =IFERROR(VLOOKUP(A92,'Distributor List'!$A$2:$D$77,2,0),"-") -> Mardan | C92: =IFERROR(VLOOKUP(A92,'Distributor List'!$A$2:$D$77,3,0),"-") -> North-2 | D92: =IFERROR(VLOOKUP(A92,'Distributor List'!$A$2:$F$77,6,0),"-") -> Pak-2 | E92: =IFERROR(VLOOKUP(A92,'Distributor List'!$A$2:$D$77,4,0),"-") -> Distributor | F92: =IFERROR(VLOOKUP(H92,'Price List'!$A$2:$H$109,8,0),"-") -> Medicronis | G92: =IFERROR(VLOOKUP(A92,'Distributor List'!$A$2:$E$77,5,0),"-") -> Rooh Ul Ameen | H92: Paxcal Tab 20's | I92: 170 | J92: 33 | K92: 105 | L92: =J92*I92 -> 5610 | M92: =K92*I92 -> 17850 | N92: 20 | O92: =N92*I92 -> 3400 | P92: =L92-O92 -> 2210 | Q92: 75 | R92: =Q92*I92 -> 12750 | S92: =IFERROR(L92/R92,"-") -> 0.44 | T92: 0 | U92: =J92-T92 -> 33 | V92: =T92*I92 -> 0 | W92: =L92-V92 -> 5610 | X92: =IFERROR(L92/V92-1,"-") -> - | Y92: =(J92)/1*1.5 -> 49.5 | Z92: =IF(Y92>K92,Y92-K92,0) -> 0 | AA92: =Z92*I92 -> 0 | AB92: =IF(Y92<K92,K92-Y92,0) -> 55.5 | AC92: =AB92*I92 -> 9435 | AD92: =Y92*I92 -> 8415 | AE92: 0
A93: MEHRAN TRADERS, Mardan | B93: =IFERROR(VLOOKUP(A93,'Distributor List'!$A$2:$D$77,2,0),"-") -> Mardan | C93: =IFERROR(VLOOKUP(A93,'Distributor List'!$A$2:$D$77,3,0),"-") -> North-2 | D93: =IFERROR(VLOOKUP(A93,'Distributor List'!$A$2:$F$77,6,0),"-") -> Pak-2 | E93: =IFERROR(VLOOKUP(A93,'Distributor List'!$A$2:$D$77,4,0),"-") -> Distributor | F93: =IFERROR(VLOOKUP(H93,'Price List'!$A$2:$H$109,8,0),"-") -> Medicronis | G93: =IFERROR(VLOOKUP(A93,'Distributor List'!$A$2:$E$77,5,0),"-") -> Rooh Ul Ameen | H93: V-Fol 400mcg | I93: 102 | J93: 38 | K93: 102 | L93: =J93*I93 -> 3876 | M93: =K93*I93 -> 10404 | N93: 26 | O93: =N93*I93 -> 2652 | P93: =L93-O93 -> 1224 | Q93: 81 | R93: =Q93*I93 -> 8262 | S93: =IFERROR(L93/R93,"-") -> 0.4691358 | T93: 10 | U93: =J93-T93 -> 28 | V93: =T93*I93 -> 1020 | W93: =L93-V93 -> 2856 | X93: =IFERROR(L93/V93-1,"-") -> 2.8 | Y93: =(J93)/1*1.5 -> 57 | Z93: =IF(Y93>K93,Y93-K93,0) -> 0 | AA93: =Z93*I93 -> 0 | AB93: =IF(Y93<K93,K93-Y93,0) -> 45 | AC93: =AB93*I93 -> 4590 | AD93: =Y93*I93 -> 5814 | AE93: 0
A94: SR Traders, Charsadda | B94: =IFERROR(VLOOKUP(A94,'Distributor List'!$A$2:$D$77,2,0),"-") -> Charsadda | C94: =IFERROR(VLOOKUP(A94,'Distributor List'!$A$2:$D$77,3,0),"-") -> North-1 | D94: =IFERROR(VLOOKUP(A94,'Distributor List'!$A$2:$F$77,6,0),"-") -> Pak-2 | E94: =IFERROR(VLOOKUP(A94,'Distributor List'!$A$2:$D$77,4,0),"-") -> Distributor | F94: =IFERROR(VLOOKUP(H94,'Price List'!$A$2:$H$109,8,0),"-") -> Medicronis | G94: =IFERROR(VLOOKUP(A94,'Distributor List'!$A$2:$E$77,5,0),"-") -> PSW Vacant | H94: Novagen 250mg | I94: 60 | J94: 0 | K94: 58 | L94: =J94*I94 -> 0 | M94: =K94*I94 -> 3480 | N94: 0 | O94: =N94*I94 -> 0 | P94: =L94-O94 -> 0 | Q94: 115.2 | R94: =Q94*I94 -> 6912 | S94: =IFERROR(L94/R94,"-") -> 0 | T94: 0 | U94: =J94-T94 -> 0 | V94: =T94*I94 -> 0 | W94: =L94-V94 -> 0 | X94: =IFERROR(L94/V94-1,"-") -> - | Y94: =(J94)/1*1.5 -> 0 | Z94: =IF(Y94>K94,Y94-K94,0) -> 0 | AA94: =Z94*I94 -> 0 | AB94: =IF(Y94<K94,K94-Y94,0) -> 58 | AC94: =AB94*I94 -> 3480 | AD94: =Y94*I94 -> 0 | AE94: 0
A95: SR Traders, Charsadda | B95: =IFERROR(VLOOKUP(A95,'Distributor List'!$A$2:$D$77,2,0),"-") -> Charsadda | C95: =IFERROR(VLOOKUP(A95,'Distributor List'!$A$2:$D$77,3,0),"-") -> North-1 | D95: =IFERROR(VLOOKUP(A95,'Distributor List'!$A$2:$F$77,6,0),"-") -> Pak-2 | E95: =IFERROR(VLOOKUP(A95,'Distributor List'!$A$2:$D$77,4,0),"-") -> Distributor | F95: =IFERROR(VLOOKUP(H95,'Price List'!$A$2:$H$109,8,0),"-") -> Medicronis | G95: =IFERROR(VLOOKUP(A95,'Distributor List'!$A$2:$E$77,5,0),"-") -> PSW Vacant | H95: Novagen 500mg | I95: 80 | J95: 0 | K95: 83 | L95: =J95*I95 -> 0 | M95: =K95*I95 -> 6640 | N95: 0 | O95: =N95*I95 -> 0 | P95: =L95-O95 -> 0 | Q95: 322.56 | R95: =Q95*I95 -> 25804.8 | S95: =IFERROR(L95/R95,"-") -> 0 | T95: 0 | U95: =J95-T95 -> 0 | V95: =T95*I95 -> 0 | W95: =L95-V95 -> 0 | X95: =IFERROR(L95/V95-1,"-") -> - | Y95: =(J95)/1*1.5 -> 0 | Z95: =IF(Y95>K95,Y95-K95,0) -> 0 | AA95: =Z95*I95 -> 0 | AB95: =IF(Y95<K95,K95-Y95,0) -> 83 | AC95: =AB95*I95 -> 6640 | AD95: =Y95*I95 -> 0 | AE95: 0
A96: SR Traders, Charsadda | B96: =IFERROR(VLOOKUP(A96,'Distributor List'!$A$2:$D$77,2,0),"-") -> Charsadda | C96: =IFERROR(VLOOKUP(A96,'Distributor List'!$A$2:$D$77,3,0),"-") -> North-1 | D96: =IFERROR(VLOOKUP(A96,'Distributor List'!$A$2:$F$77,6,0),"-") -> Pak-2 | E96: =IFERROR(VLOOKUP(A96,'Distributor List'!$A$2:$D$77,4,0),"-") -> Distributor | F96: =IFERROR(VLOOKUP(H96,'Price List'!$A$2:$H$109,8,0),"-") -> Medicronis | G96: =IFERROR(VLOOKUP(A96,'Distributor List'!$A$2:$E$77,5,0),"-") -> PSW Vacant | H96: Novagen 1g | I96: 105 | J96: 0 | K96: 0 | L96: =J96*I96 -> 0 | M96: =K96*I96 -> 0 | N96: 0 | O96: =N96*I96 -> 0 | P96: =L96-O96 -> 0 | Q96: 645.12 | R96: =Q96*I96 -> 67737.6 | S96: =IFERROR(L96/R96,"-") -> 0 | T96: 0 | U96: =J96-T96 -> 0 | V96: =T96*I96 -> 0 | W96: =L96-V96 -> 0 | X96: =IFERROR(L96/V96-1,"-") -> - | Y96: =(J96)/1*1.5 -> 0 | Z96: =IF(Y96>K96,Y96-K96,0) -> 0 | AA96: =Z96*I96 -> 0 | AB96: =IF(Y96<K96,K96-Y96,0) -> 0 | AC96: =AB96*I96 -> 0 | AD96: =Y96*I96 -> 0 | AE96: 0
A97: SR Traders, Charsadda | B97: =IFERROR(VLOOKUP(A97,'Distributor List'!$A$2:$D$77,2,0),"-") -> Charsadda | C97: =IFERROR(VLOOKUP(A97,'Distributor List'!$A$2:$D$77,3,0),"-") -> North-1 | D97: =IFERROR(VLOOKUP(A97,'Distributor List'!$A$2:$F$77,6,0),"-") -> Pak-2 | E97: =IFERROR(VLOOKUP(A97,'Distributor List'!$A$2:$D$77,4,0),"-") -> Distributor | F97: =IFERROR(VLOOKUP(H97,'Price List'!$A$2:$H$109,8,0),"-") -> Transformer | G97: =IFERROR(VLOOKUP(A97,'Distributor List'!$A$2:$E$77,5,0),"-") -> PSW Vacant | H97: Ectafin 1G | I97: 391 | J97: 0 | K97: 0 | L97: =J97*I97 -> 0 | M97: =K97*I97 -> 0 | N97: 0 | O97: =N97*I97 -> 0 | P97: =L97-O97 -> 0 | Q97: 0 | R97: =Q97*I97 -> 0 | S97: =IFERROR(L97/R97,"-") -> - | T97: 0 | U97: =J97-T97 -> 0 | V97: =T97*I97 -> 0 | W97: =L97-V97 -> 0 | X97: =IFERROR(L97/V97-1,"-") -> - | Y97: =(J97)/1*1.5 -> 0 | Z97: =IF(Y97>K97,Y97-K97,0) -> 0 | AA97: =Z97*I97 -> 0 | AB97: =IF(Y97<K97,K97-Y97,0) -> 0 | AC97: =AB97*I97 -> 0 | AD97: =Y97*I97 -> 0 | AE97: 0
A98: SR Traders, Charsadda | B98: =IFERROR(VLOOKUP(A98,'Distributor List'!$A$2:$D$77,2,0),"-") -> Charsadda | C98: =IFERROR(VLOOKUP(A98,'Distributor List'!$A$2:$D$77,3,0),"-") -> North-1 | D98: =IFERROR(VLOOKUP(A98,'Distributor List'!$A$2:$F$77,6,0),"-") -> Pak-2 | E98: =IFERROR(VLOOKUP(A98,'Distributor List'!$A$2:$D$77,4,0),"-") -> Distributor | F98: =IFERROR(VLOOKUP(H98,'Price List'!$A$2:$H$109,8,0),"-") -> Transformer | G98: =IFERROR(VLOOKUP(A98,'Distributor List'!$A$2:$E$77,5,0),"-") -> PSW Vacant | H98: Ectafin 2G | I98: 616.25 | J98: 0 | K98: 0 | L98: =J98*I98 -> 0 | M98: =K98*I98 -> 0 | N98: 0 | O98: =N98*I98 -> 0 | P98: =L98-O98 -> 0 | Q98: 0 | R98: =Q98*I98 -> 0 | S98: =IFERROR(L98/R98,"-") -> - | T98: 0 | U98: =J98-T98 -> 0 | V98: =T98*I98 -> 0 | W98: =L98-V98 -> 0 | X98: =IFERROR(L98/V98-1,"-") -> - | Y98: =(J98)/1*1.5 -> 0 | Z98: =IF(Y98>K98,Y98-K98,0) -> 0 | AA98: =Z98*I98 -> 0 | AB98: =IF(Y98<K98,K98-Y98,0) -> 0 | AC98: =AB98*I98 -> 0 | AD98: =Y98*I98 -> 0 | AE98: 0
A99: SR Traders, Charsadda | B99: =IFERROR(VLOOKUP(A99,'Distributor List'!$A$2:$D$77,2,0),"-") -> Charsadda | C99: =IFERROR(VLOOKUP(A99,'Distributor List'!$A$2:$D$77,3,0),"-") -> North-1 | D99: =IFERROR(VLOOKUP(A99,'Distributor List'!$A$2:$F$77,6,0),"-") -> Pak-2 | E99: =IFERROR(VLOOKUP(A99,'Distributor List'!$A$2:$D$77,4,0),"-") -> Distributor | F99: =IFERROR(VLOOKUP(H99,'Price List'!$A$2:$H$109,8,0),"-") -> Medicronis | G99: =IFERROR(VLOOKUP(A99,'Distributor List'!$A$2:$E$77,5,0),"-") -> PSW Vacant | H99: Lancix Inj. 10s | I99: 270 | J99: 0 | K99: 67 | L99: =J99*I99 -> 0 | M99: =K99*I99 -> 18090 | N99: 0 | O99: =N99*I99 -> 0 | P99: =L99-O99 -> 0 | Q99: 96 | R99: =Q99*I99 -> 25920 | S99: =IFERROR(L99/R99,"-") -> 0 | T99: 0 | U99: =J99-T99 -> 0 | V99: =T99*I99 -> 0 | W99: =L99-V99 -> 0 | X99: =IFERROR(L99/V99-1,"-") -> - | Y99: =(J99)/1*1.5 -> 0 | Z99: =IF(Y99>K99,Y99-K99,0) -> 0 | AA99: =Z99*I99 -> 0 | AB99: =IF(Y99<K99,K99-Y99,0) -> 67 | AC99: =AB99*I99 -> 18090 | AD99: =Y99*I99 -> 0 | AE99: 0
A100: SR Traders, Charsadda | B100: =IFERROR(VLOOKUP(A100,'Distributor List'!$A$2:$D$77,2,0),"-") -> Charsadda | C100: =IFERROR(VLOOKUP(A100,'Distributor List'!$A$2:$D$77,3,0),"-") -> North-1 | D100: =IFERROR(VLOOKUP(A100,'Distributor List'!$A$2:$F$77,6,0),"-") -> Pak-2 | E100: =IFERROR(VLOOKUP(A100,'Distributor List'!$A$2:$D$77,4,0),"-") -> Distributor | F100: =IFERROR(VLOOKUP(H100,'Price List'!$A$2:$H$109,8,0),"-") -> Medicronis | G100: =IFERROR(VLOOKUP(A100,'Distributor List'!$A$2:$E$77,5,0),"-") -> PSW Vacant | H100: Lancix Inj. 25s | I100: 670 | J100: 0 | K100: 21 | L100: =J100*I100 -> 0 | M100: =K100*I100 -> 14070 | N100: 0 | O100: =N100*I100 -> 0 | P100: =L100-O100 -> 0 | Q100: 48 | R100: =Q100*I100 -> 32160 | S100: =IFERROR(L100/R100,"-") -> 0 | T100: 0 | U100: =J100-T100 -> 0 | V100: =T100*I100 -> 0 | W100: =L100-V100 -> 0 | X100: =IFERROR(L100/V100-1,"-") -> - | Y100: =(J100)/1*1.5 -> 0 | Z100: =IF(Y100>K100,Y100-K100,0) -> 0 | AA100: =Z100*I100 -> 0 | AB100: =IF(Y100<K100,K100-Y100,0) -> 21 | AC100: =AB100*I100 -> 14070 | AD100: =Y100*I100 -> 0 | AE100: 0
A101: SR Traders, Charsadda | B101: =IFERROR(VLOOKUP(A101,'Distributor List'!$A$2:$D$77,2,0),"-") -> Charsadda | C101: =IFERROR(VLOOKUP(A101,'Distributor List'!$A$2:$D$77,3,0),"-") -> North-1 | D101: =IFERROR(VLOOKUP(A101,'Distributor List'!$A$2:$F$77,6,0),"-") -> Pak-2 | E101: =IFERROR(VLOOKUP(A101,'Distributor List'!$A$2:$D$77,4,0),"-") -> Distributor | F101: =IFERROR(VLOOKUP(H101,'Price List'!$A$2:$H$109,8,0),"-") -> Medicronis | G101: =IFERROR(VLOOKUP(A101,'Distributor List'!$A$2:$E$77,5,0),"-") -> PSW Vacant | H101: G.Tax 250mg | I101: 60 | J101: 0 | K101: 26 | L101: =J101*I101 -> 0 | M101: =K101*I101 -> 1560 | N101: 0 | O101: =N101*I101 -> 0 | P101: =L101-O101 -> 0 | Q101: 55.56 | R101: =Q101*I101 -> 3333.6 | S101: =IFERROR(L101/R101,"-") -> 0 | T101: 0 | U101: =J101-T101 -> 0 | V101: =T101*I101 -> 0 | W101: =L101-V101 -> 0 | X101: =IFERROR(L101/V101-1,"-") -> - | Y101: =(J101)/1*1.5 -> 0 | Z101: =IF(Y101>K101,Y101-K101,0) -> 0 | AA101: =Z101*I101 -> 0 | AB101: =IF(Y101<K101,K101-Y101,0) -> 26 | AC101: =AB101*I101 -> 1560 | AD101: =Y101*I101 -> 0 | AE101: 0
A102: SR Traders, Charsadda | B102: =IFERROR(VLOOKUP(A102,'Distributor List'!$A$2:$D$77,2,0),"-") -> Charsadda | C102: =IFERROR(VLOOKUP(A102,'Distributor List'!$A$2:$D$77,3,0),"-") -> North-1 | D102: =IFERROR(VLOOKUP(A102,'Distributor List'!$A$2:$F$77,6,0),"-") -> Pak-2 | E102: =IFERROR(VLOOKUP(A102,'Distributor List'!$A$2:$D$77,4,0),"-") -> Distributor | F102: =IFERROR(VLOOKUP(H102,'Price List'!$A$2:$H$109,8,0),"-") -> Medicronis | G102: =IFERROR(VLOOKUP(A102,'Distributor List'!$A$2:$E$77,5,0),"-") -> PSW Vacant | H102: G.Tax 500mg | I102: 56 | J102: 0 | K102: 100 | L102: =J102*I102 -> 0 | M102: =K102*I102 -> 5600 | N102: 0 | O102: =N102*I102 -> 0 | P102: =L102-O102 -> 0 | Q102: 53.58 | R102: =Q102*I102 -> 3000.48 | S102: =IFERROR(L102/R102,"-") -> 0 | T102: 0 | U102: =J102-T102 -> 0 | V102: =T102*I102 -> 0 | W102: =L102-V102 -> 0 | X102: =IFERROR(L102/V102-1,"-") -> - | Y102: =(J102)/1*1.5 -> 0 | Z102: =IF(Y102>K102,Y102-K102,0) -> 0 | AA102: =Z102*I102 -> 0 | AB102: =IF(Y102<K102,K102-Y102,0) -> 100 | AC102: =AB102*I102 -> 5600 | AD102: =Y102*I102 -> 0 | AE102: 0
... A111: SR Traders, Charsadda | B111: =IFERROR(VLOOKUP(A111,'Distributor List'!$A$2:$D$77,2,0),"-") -> Charsadda | C111: =IFERROR(VLOOKUP(A111,'Distributor List'!$A$2:$D$77,3,0),"-") -> North-1 | D111: =IFERROR(VLOOKUP(A111,'Distributor List'!$A$2:$F$77,6,0),"-") -> Pak-2 | E111: =IFERROR(VLOOKUP(A111,'Distributor List'!$A$2:$D$77,4,0),"-") -> Distributor | F111: =IFERROR(VLOOKUP(H111,'Price List'!$A$2:$H$109,8,0),"-") -> Medicronis | G111: =IFERROR(VLOOKUP(A111,'Distributor List'!$A$2:$E$77,5,0),"-") -> PSW Vacant | H111: Hostenil Syrup 120ml | I111: 90 | J111: 0 | K111: 0 | L111: =J111*I111 -> 0 | M111: =K111*I111 -> 0 | N111: 0 | O111: =N111*I111 -> 0 | P111: =L111-O111 -> 0 | Q111: 0 | R111: =Q111*I111 -> 0 | S111: =IFERROR(L111/R111,"-") -> - | T111: 0 | U111: =J111-T111 -> 0 | V111: =T111*I111 -> 0 | W111: =L111-V111 -> 0 | X111: =IFERROR(L111/V111-1,"-") -> - | Y111: =(J111)/1*1.5 -> 0 | Z111: =IF(Y111>K111,Y111-K111,0) -> 0 | AA111: =Z111*I111 -> 0 | AB111: =IF(Y111<K111,K111-Y111,0) -> 0 | AC111: =AB111*I111 -> 0 | AD111: =Y111*I111 -> 0 | AE111: 0
A112: SR Traders, Charsadda | B112: =IFERROR(VLOOKUP(A112,'Distributor List'!$A$2:$D$77,2,0),"-") -> Charsadda | C112: =IFERROR(VLOOKUP(A112,'Distributor List'!$A$2:$D$77,3,0),"-") -> North-1 | D112: =IFERROR(VLOOKUP(A112,'Distributor List'!$A$2:$F$77,6,0),"-") -> Pak-2 | E112: =IFERROR(VLOOKUP(A112,'Distributor List'!$A$2:$D$77,4,0),"-") -> Distributor | F112: =IFERROR(VLOOKUP(H112,'Price List'!$A$2:$H$109,8,0),"-") -> Medicronis | G112: =IFERROR(VLOOKUP(A112,'Distributor List'!$A$2:$E$77,5,0),"-") -> PSW Vacant | H112: kufxy Syp 120ml | I112: 99 | J112: 0 | K112: 60 | L112: =J112*I112 -> 0 | N112: 0 | O112: =N112*I112 -> 0 | P112: =L112-O112 -> 0 | Q112: 96 | R112: =Q112*I112 -> 9504 | S112: =IFERROR(L112/R112,"-") -> 0 | T112: 0 | U112: =J112-T112 -> 0 | V112: =T112*I112 -> 0 | W112: =L112-V112 -> 0 | X112: =IFERROR(L112/V112-1,"-") -> - | Y112: =(J112)/1*1.5 -> 0 | Z112: =IF(Y112>K112,Y112-K112,0) -> 0 | AA112: =Z112*I112 -> 0 | AB112: =IF(Y112<K112,K112-Y112,0) -> 60 | AC112: =AB112*I112 -> 5940 | AD112: =Y112*I112 -> 0
A113: SR Traders, Charsadda | B113: =IFERROR(VLOOKUP(A113,'Distributor List'!$A$2:$D$77,2,0),"-") -> Charsadda | C113: =IFERROR(VLOOKUP(A113,'Distributor List'!$A$2:$D$77,3,0),"-") -> North-1 | D113: =IFERROR(VLOOKUP(A113,'Distributor List'!$A$2:$F$77,6,0),"-") -> Pak-2 | E113: =IFERROR(VLOOKUP(A113,'Distributor List'!$A$2:$D$77,4,0),"-") -> Distributor | F113: =IFERROR(VLOOKUP(H113,'Price List'!$A$2:$H$109,8,0),"-") -> Medicronis | G113: =IFERROR(VLOOKUP(A113,'Distributor List'!$A$2:$E$77,5,0),"-") -> PSW Vacant | H113: Salberry Sachet 10s | I113: 105 | J113: 0 | K113: 0 | L113: =J113*I113 -> 0 | M113: =K113*I113 -> 0 | N113: 0 | O113: =N113*I113 -> 0 | P113: =L113-O113 -> 0 | Q113: 60 | R113: =Q113*I113 -> 6300 | S113: =IFERROR(L113/R113,"-") -> 0 | T113: 0 | U113: =J113-T113 -> 0 | V113: =T113*I113 -> 0 | W113: =L113-V113 -> 0 | X113: =IFERROR(L113/V113-1,"-") -> - | Y113: =(J113)/1*1.5 -> 0 | Z113: =IF(Y113>K113,Y113-K113,0) -> 0 | AA113: =Z113*I113 -> 0 | AB113: =IF(Y113<K113,K113-Y113,0) -> 0 | AC113: =AB113*I113 -> 0 | AD113: =Y113*I113 -> 0 | AE113: 0
A114: SR Traders, Charsadda | B114: =IFERROR(VLOOKUP(A114,'Distributor List'!$A$2:$D$77,2,0),"-") -> Charsadda | C114: =IFERROR(VLOOKUP(A114,'Distributor List'!$A$2:$D$77,3,0),"-") -> North-1 | D114: =IFERROR(VLOOKUP(A114,'Distributor List'!$A$2:$F$77,6,0),"-") -> Pak-2 | E114: =IFERROR(VLOOKUP(A114,'Distributor List'!$A$2:$D$77,4,0),"-") -> Distributor | F114: =IFERROR(VLOOKUP(H114,'Price List'!$A$2:$H$109,8,0),"-") -> Medicronis | G114: =IFERROR(VLOOKUP(A114,'Distributor List'!$A$2:$E$77,5,0),"-") -> PSW Vacant | H114: Berry Flow Sachet | I114: 115 | J114: 0 | K114: 61 | L114: =J114*I114 -> 0 | M114: =K114*I114 -> 7015 | N114: 0 | O114: =N114*I114 -> 0 | P114: =L114-O114 -> 0 | Q114: 60 | R114: =Q114*I114 -> 6900 | S114: =IFERROR(L114/R114,"-") -> 0 | T114: 0 | U114: =J114-T114 -> 0 | V114: =T114*I114 -> 0 | W114: =L114-V114 -> 0 | X114: =IFERROR(L114/V114-1,"-") -> - | Y114: =(J114)/1*1.5 -> 0 | Z114: =IF(Y114>K114,Y114-K114,0) -> 0 | AA114: =Z114*I114 -> 0 | AB114: =IF(Y114<K114,K114-Y114,0) -> 61 | AC114: =AB114*I114 -> 7015 | AD114: =Y114*I114 -> 0 | AE114: 0
A115: SR Traders, Charsadda | B115: =IFERROR(VLOOKUP(A115,'Distributor List'!$A$2:$D$77,2,0),"-") -> Charsadda | C115: =IFERROR(VLOOKUP(A115,'Distributor List'!$A$2:$D$77,3,0),"-") -> North-1 | D115: =IFERROR(VLOOKUP(A115,'Distributor List'!$A$2:$F$77,6,0),"-") -> Pak-2 | E115: =IFERROR(VLOOKUP(A115,'Distributor List'!$A$2:$D$77,4,0),"-") -> Distributor | F115: =IFERROR(VLOOKUP(H115,'Price List'!$A$2:$H$109,8,0),"-") -> Medicronis | G115: =IFERROR(VLOOKUP(A115,'Distributor List'!$A$2:$E$77,5,0),"-") -> PSW Vacant | H115: Cipak 200mg/100ml Inf | I115: 120 | J115: 0 | K115: 29 | L115: =J115*I115 -> 0 | M115: =K115*I115 -> 3480 | N115: 0 | O115: =N115*I115 -> 0 | P115: =L115-O115 -> 0 | Q115: 149.9175 | R115: =Q115*I115 -> 17990.1 | S115: =IFERROR(L115/R115,"-") -> 0 | T115: 0 | U115: =J115-T115 -> 0 | V115: =T115*I115 -> 0 | W115: =L115-V115 -> 0 | X115: =IFERROR(L115/V115-1,"-") -> - | Y115: =(J115)/1*1.5 -> 0 | Z115: =IF(Y115>K115,Y115-K115,0) -> 0 | AA115: =Z115*I115 -> 0 | AB115: =IF(Y115<K115,K115-Y115,0) -> 29 | AC115: =AB115*I115 -> 3480 | AD115: =Y115*I115 -> 0 | AE115: 0
A116: SR Traders, Charsadda | B116: =IFERROR(VLOOKUP(A116,'Distributor List'!$A$2:$D$77,2,0),"-") -> Charsadda | C116: =IFERROR(VLOOKUP(A116,'Distributor List'!$A$2:$D$77,3,0),"-") -> North-1 | D116: =IFERROR(VLOOKUP(A116,'Distributor List'!$A$2:$F$77,6,0),"-") -> Pak-2 | E116: =IFERROR(VLOOKUP(A116,'Distributor List'!$A$2:$D$77,4,0),"-") -> Distributor | F116: =IFERROR(VLOOKUP(H116,'Price List'!$A$2:$H$109,8,0),"-") -> Transformer | G116: =IFERROR(VLOOKUP(A116,'Distributor List'!$A$2:$E$77,5,0),"-") -> PSW Vacant | H116: Maxy 400mg/250ml Inf | I116: 299 | J116: 0 | K116: 0 | L116: =J116*I116 -> 0 | M116: =K116*I116 -> 0 | N116: 0 | O116: =N116*I116 -> 0 | P116: =L116-O116 -> 0 | Q116: 0 | R116: =Q116*I116 -> 0 | S116: =IFERROR(L116/R116,"-") -> - | T116: 0 | U116: =J116-T116 -> 0 | V116: =T116*I116 -> 0 | W116: =L116-V116 -> 0 | X116: =IFERROR(L116/V116-1,"-") -> - | Y116: =(J116)/1*1.5 -> 0 | Z116: =IF(Y116>K116,Y116-K116,0) -> 0 | AA116: =Z116*I116 -> 0 | AB116: =IF(Y116<K116,K116-Y116,0) -> 0 | AC116: =AB116*I116 -> 0 | AD116: =Y116*I116 -> 0 | AE116: 0
A117: SR Traders, Charsadda | B117: =IFERROR(VLOOKUP(A117,'Distributor List'!$A$2:$D$77,2,0),"-") -> Charsadda | C117: =IFERROR(VLOOKUP(A117,'Distributor List'!$A$2:$D$77,3,0),"-") -> North-1 | D117: =IFERROR(VLOOKUP(A117,'Distributor List'!$A$2:$F$77,6,0),"-") -> Pak-2 | E117: =IFERROR(VLOOKUP(A117,'Distributor List'!$A$2:$D$77,4,0),"-") -> Distributor | F117: =IFERROR(VLOOKUP(H117,'Price List'!$A$2:$H$109,8,0),"-") -> Transformer | G117: =IFERROR(VLOOKUP(A117,'Distributor List'!$A$2:$E$77,5,0),"-") -> PSW Vacant | H117: Evox 500mg/100ml Inf | I117: 403.75 | J117: 0 | K117: 0 | L117: =J117*I117 -> 0 | M117: =K117*I117 -> 0 | N117: 0 | O117: =N117*I117 -> 0 | P117: =L117-O117 -> 0 | Q117: 0 | R117: =Q117*I117 -> 0 | S117: =IFERROR(L117/R117,"-") -> - | T117: 0 | U117: =J117-T117 -> 0 | V117: =T117*I117 -> 0 | W117: =L117-V117 -> 0 | X117: =IFERROR(L117/V117-1,"-") -> - | Y117: =(J117)/1*1.5 -> 0 | Z117: =IF(Y117>K117,Y117-K117,0) -> 0 | AA117: =Z117*I117 -> 0 | AB117: =IF(Y117<K117,K117-Y117,0) -> 0 | AC117: =AB117*I117 -> 0 | AD117: =Y117*I117 -> 0 | AE117: 0
A118: SR Traders, Charsadda | B118: =IFERROR(VLOOKUP(A118,'Distributor List'!$A$2:$D$77,2,0),"-") -> Charsadda | C118: =IFERROR(VLOOKUP(A118,'Distributor List'!$A$2:$D$77,3,0),"-") -> North-1 | D118: =IFERROR(VLOOKUP(A118,'Distributor List'!$A$2:$F$77,6,0),"-") -> Pak-2 | E118: =IFERROR(VLOOKUP(A118,'Distributor List'!$A$2:$D$77,4,0),"-") -> Distributor | F118: =IFERROR(VLOOKUP(H118,'Price List'!$A$2:$H$109,8,0),"-") -> Medicronis | G118: =IFERROR(VLOOKUP(A118,'Distributor List'!$A$2:$E$77,5,0),"-") -> PSW Vacant | H118: Nida 200mg/100ml Inf | I118: 105 | J118: 0 | K118: 46 | L118: =J118*I118 -> 0 | M118: =K118*I118 -> 4830 | N118: 0 | O118: =N118*I118 -> 0 | P118: =L118-O118 -> 0 | Q118: 370.63125 | R118: =Q118*I118 -> 38916.281 | S118: =IFERROR(L118/R118,"-") -> 0 | T118: 0 | U118: =J118-T118 -> 0 | V118: =T118*I118 -> 0 | W118: =L118-V118 -> 0 | X118: =IFERROR(L118/V118-1,"-") -> - | Y118: =(J118)/1*1.5 -> 0 | Z118: =IF(Y118>K118,Y118-K118,0) -> 0 | AA118: =Z118*I118 -> 0 | AB118: =IF(Y118<K118,K118-Y118,0) -> 46 | AC118: =AB118*I118 -> 4830 | AD118: =Y118*I118 -> 0 | AE118: 0
A119: SR Traders, Charsadda | B119: =IFERROR(VLOOKUP(A119,'Distributor List'!$A$2:$D$77,2,0),"-") -> Charsadda | C119: =IFERROR(VLOOKUP(A119,'Distributor List'!$A$2:$D$77,3,0),"-") -> North-1 | D119: =IFERROR(VLOOKUP(A119,'Distributor List'!$A$2:$F$77,6,0),"-") -> Pak-2 | E119: =IFERROR(VLOOKUP(A119,'Distributor List'!$A$2:$D$77,4,0),"-") -> Distributor | F119: =IFERROR(VLOOKUP(H119,'Price List'!$A$2:$H$109,8,0),"-") -> Medicronis | G119: =IFERROR(VLOOKUP(A119,'Distributor List'!$A$2:$E$77,5,0),"-") -> PSW Vacant | H119: CefPak 250mg Iv Inj | I119: 53 | J119: 0 | K119: 0 | L119: =J119*I119 -> 0 | M119: =K119*I119 -> 0 | N119: 0 | O119: =N119*I119 -> 0 | P119: =L119-O119 -> 0 | Q119: 0 | R119: =Q119*I119 -> 0 | S119: =IFERROR(L119/R119,"-") -> - | T119: 0 | U119: =J119-T119 -> 0 | V119: =T119*I119 -> 0 | W119: =L119-V119 -> 0 | X119: =IFERROR(L119/V119-1,"-") -> - | Y119: =(J119)/1*1.5 -> 0 | Z119: =IF(Y119>K119,Y119-K119,0) -> 0 | AA119: =Z119*I119 -> 0 | AB119: =IF(Y119<K119,K119-Y119,0) -> 0 | AC119: =AB119*I119 -> 0 | AD119: =Y119*I119 -> 0 | AE119: 0
A120: SR Traders, Charsadda | B120: =IFERROR(VLOOKUP(A120,'Distributor List'!$A$2:$D$77,2,0),"-") -> Charsadda | C120: =IFERROR(VLOOKUP(A120,'Distributor List'!$A$2:$D$77,3,0),"-") -> North-1 | D120: =IFERROR(VLOOKUP(A120,'Distributor List'!$A$2:$F$77,6,0),"-") -> Pak-2 | E120: =IFERROR(VLOOKUP(A120,'Distributor List'!$A$2:$D$77,4,0),"-") -> Distributor | F120: =IFERROR(VLOOKUP(H120,'Price List'!$A$2:$H$109,8,0),"-") -> Medicronis | G120: =IFERROR(VLOOKUP(A120,'Distributor List'!$A$2:$E$77,5,0),"-") -> PSW Vacant | H120: CefPak 500mg Iv Inj | I120: 69 | J120: 0 | K120: 0 | L120: =J120*I120 -> 0 | M120: =K120*I120 -> 0 | N120: 0 | O120: =N120*I120 -> 0 | P120: =L120-O120 -> 0 | Q120: 0 | R120: =Q120*I120 -> 0 | S120: =IFERROR(L120/R120,"-") -> - | T120: 0 | U120: =J120-T120 -> 0 | V120: =T120*I120 -> 0 | W120: =L120-V120 -> 0 | X120: =IFERROR(L120/V120-1,"-") -> - | Y120: =(J120)/1*1.5 -> 0 | Z120: =IF(Y120>K120,Y120-K120,0) -> 0 | AA120: =Z120*I120 -> 0 | AB120: =IF(Y120<K120,K120-Y120,0) -> 0 | AC120: =AB120*I120 -> 0 | AD120: =Y120*I120 -> 0 | AE120: 0
A121: SR Traders, Charsadda | B121: =IFERROR(VLOOKUP(A121,'Distributor List'!$A$2:$D$77,2,0),"-") -> Charsadda | C121: =IFERROR(VLOOKUP(A121,'Distributor List'!$A$2:$D$77,3,0),"-") -> North-1 | D121: =IFERROR(VLOOKUP(A121,'Distributor List'!$A$2:$F$77,6,0),"-") -> Pak-2 | E121: =IFERROR(VLOOKUP(A121,'Distributor List'!$A$2:$D$77,4,0),"-") -> Distributor | F121: =IFERROR(VLOOKUP(H121,'Price List'!$A$2:$H$109,8,0),"-") -> Medicronis | G121: =IFERROR(VLOOKUP(A121,'Distributor List'!$A$2:$E$77,5,0),"-") -> PSW Vacant | H121: CefPak 1G Iv Inj | I121: 90 | J121: 0 | K121: 0 | L121: =J121*I121 -> 0 | M121: =K121*I121 -> 0 | N121: 0 | O121: =N121*I121 -> 0 | P121: =L121-O121 -> 0 | Q121: 0 | R121: =Q121*I121 -> 0 | S121: =IFERROR(L121/R121,"-") -> - | T121: 0 | U121: =J121-T121 -> 0 | V121: =T121*I121 -> 0 | W121: =L121-V121 -> 0 | X121: =IFERROR(L121/V121-1,"-") -> - | Y121: =(J121)/1*1.5 -> 0 | Z121: =IF(Y121>K121,Y121-K121,0) -> 0 | AA121: =Z121*I121 -> 0 | AB121: =IF(Y121<K121,K121-Y121,0) -> 0 | AC121: =AB121*I121 -> 0 | AD121: =Y121*I121 -> 0 | AE121: 0
A122: SR Traders, Charsadda | B122: =IFERROR(VLOOKUP(A122,'Distributor List'!$A$2:$D$77,2,0),"-") -> Charsadda | C122: =IFERROR(VLOOKUP(A122,'Distributor List'!$A$2:$D$77,3,0),"-") -> North-1 | D122: =IFERROR(VLOOKUP(A122,'Distributor List'!$A$2:$F$77,6,0),"-") -> Pak-2 | E122: =IFERROR(VLOOKUP(A122,'Distributor List'!$A$2:$D$77,4,0),"-") -> Distributor | F122: =IFERROR(VLOOKUP(H122,'Price List'!$A$2:$H$109,8,0),"-") -> Medicronis | G122: =IFERROR(VLOOKUP(A122,'Distributor List'!$A$2:$E$77,5,0),"-") -> PSW Vacant | H122: PeerGo Gel 30g | I122: 120 | J122: 0 | K122: 87 | L122: =J122*I122 -> 0 | M122: =K122*I122 -> 10440 | N122: 0 | O122: =N122*I122 -> 0 | P122: =L122-O122 -> 0 | Q122: 36 | R122: =Q122*I122 -> 4320 | S122: =IFERROR(L122/R122,"-") -> 0 | T122: 0 | U122: =J122-T122 -> 0 | V122: =T122*I122 -> 0 | W122: =L122-V122 -> 0 | X122: =IFERROR(L122/V122-1,"-") -> - | Y122: =(J122)/1*1.5 -> 0 | Z122: =IF(Y122>K122,Y122-K122,0) -> 0 | AA122: =Z122*I122 -> 0 | AB122: =IF(Y122<K122,K122-Y122,0) -> 87 | AC122: =AB122*I122 -> 10440 | AD122: =Y122*I122 -> 0 | AE122: 0
A123: SR Traders, Charsadda | B123: =IFERROR(VLOOKUP(A123,'Distributor List'!$A$2:$D$77,2,0),"-") -> Charsadda | C123: =IFERROR(VLOOKUP(A123,'Distributor List'!$A$2:$D$77,3,0),"-") -> North-1 | D123: =IFERROR(VLOOKUP(A123,'Distributor List'!$A$2:$F$77,6,0),"-") -> Pak-2 | E123: =IFERROR(VLOOKUP(A123,'Distributor List'!$A$2:$D$77,4,0),"-") -> Distributor | F123: =IFERROR(VLOOKUP(H123,'Price List'!$A$2:$H$109,8,0),"-") -> Medicronis | G123: =IFERROR(VLOOKUP(A123,'Distributor List'!$A$2:$E$77,5,0),"-") -> PSW Vacant | H123: Mediscon Syp 120ml | I123: 110 | J123: 0 | K123: 11 | L123: =J123*I123 -> 0 | M123: =K123*I123 -> 1210 | N123: 0 | O123: =N123*I123 -> 0 | P123: =L123-O123 -> 0 | Q123: 324 | R123: =Q123*I123 -> 35640 | S123: =IFERROR(L123/R123,"-") -> 0 | T123: 0 | U123: =J123-T123 -> 0 | V123: =T123*I123 -> 0 | W123: =L123-V123 -> 0 | X123: =IFERROR(L123/V123-1,"-") -> - | Y123: =(J123)/1*1.5 -> 0 | Z123: =IF(Y123>K123,Y123-K123,0) -> 0 | AA123: =Z123*I123 -> 0 | AB123: =IF(Y123<K123,K123-Y123,0) -> 11 | AC123: =AB123*I123 -> 1210 | AD123: =Y123*I123 -> 0 | AE123: 0
A124: SR Traders, Charsadda | B124: =IFERROR(VLOOKUP(A124,'Distributor List'!$A$2:$D$77,2,0),"-") -> Charsadda | C124: =IFERROR(VLOOKUP(A124,'Distributor List'!$A$2:$D$77,3,0),"-") -> North-1 | D124: =IFERROR(VLOOKUP(A124,'Distributor List'!$A$2:$F$77,6,0),"-") -> Pak-2 | E124: =IFERROR(VLOOKUP(A124,'Distributor List'!$A$2:$D$77,4,0),"-") -> Distributor | F124: =IFERROR(VLOOKUP(H124,'Price List'!$A$2:$H$109,8,0),"-") -> Medicronis | G124: =IFERROR(VLOOKUP(A124,'Distributor List'!$A$2:$E$77,5,0),"-") -> PSW Vacant | H124: KhaajGo Soap Bar | I124: 120 | J124: 0 | K124: 0 | L124: =J124*I124 -> 0 | M124: =K124*I124 -> 0 | N124: 0 | O124: =N124*I124 -> 0 | P124: =L124-O124 -> 0 | Q124: 36 | R124: =Q124*I124 -> 4320 | S124: =IFERROR(L124/R124,"-") -> 0 | T124: 0 | U124: =J124-T124 -> 0 | V124: =T124*I124 -> 0 | W124: =L124-V124 -> 0 | X124: =IFERROR(L124/V124-1,"-") -> - | Y124: =(J124)/1*1.5 -> 0 | Z124: =IF(Y124>K124,Y124-K124,0) -> 0 | AA124: =Z124*I124 -> 0 | AB124: =IF(Y124<K124,K124-Y124,0) -> 0 | AC124: =AB124*I124 -> 0 | AD124: =Y124*I124 -> 0 | AE124: 0
... A132: SR Traders, Charsadda | B132: =IFERROR(VLOOKUP(A132,'Distributor List'!$A$2:$D$77,2,0),"-") -> Charsadda | C132: =IFERROR(VLOOKUP(A132,'Distributor List'!$A$2:$D$77,3,0),"-") -> North-1 | D132: =IFERROR(VLOOKUP(A132,'Distributor List'!$A$2:$F$77,6,0),"-") -> Pak-2 | E132: =IFERROR(VLOOKUP(A132,'Distributor List'!$A$2:$D$77,4,0),"-") -> Distributor | F132: =IFERROR(VLOOKUP(H132,'Price List'!$A$2:$H$109,8,0),"-") -> Medicronis | G132: =IFERROR(VLOOKUP(A132,'Distributor List'!$A$2:$E$77,5,0),"-") -> PSW Vacant | H132: Medelac Syp 120ml | I132: 105 | J132: 0 | K132: -6 | L132: =J132*I132 -> 0 | M132: =K132*I132 -> -630 | N132: 0 | O132: =N132*I132 -> 0 | P132: =L132-O132 -> 0 | Q132: 144 | R132: =Q132*I132 -> 15120 | S132: =IFERROR(L132/R132,"-") -> 0 | T132: 0 | U132: =J132-T132 -> 0 | V132: =T132*I132 -> 0 | W132: =L132-V132 -> 0 | X132: =IFERROR(L132/V132-1,"-") -> - | Y132: =(J132)/1*1.5 -> 0 | Z132: =IF(Y132>K132,Y132-K132,0) -> 6 | AA132: =Z132*I132 -> 630 | AB132: =IF(Y132<K132,K132-Y132,0) -> 0 | AC132: =AB132*I132 -> 0 | AD132: =Y132*I132 -> 0 | AE132: 0
A133: SR Traders, Charsadda | B133: =IFERROR(VLOOKUP(A133,'Distributor List'!$A$2:$D$77,2,0),"-") -> Charsadda | C133: =IFERROR(VLOOKUP(A133,'Distributor List'!$A$2:$D$77,3,0),"-") -> North-1 | D133: =IFERROR(VLOOKUP(A133,'Distributor List'!$A$2:$F$77,6,0),"-") -> Pak-2 | E133: =IFERROR(VLOOKUP(A133,'Distributor List'!$A$2:$D$77,4,0),"-") -> Distributor | F133: =IFERROR(VLOOKUP(H133,'Price List'!$A$2:$H$109,8,0),"-") -> Medicronis | G133: =IFERROR(VLOOKUP(A133,'Distributor List'!$A$2:$E$77,5,0),"-") -> PSW Vacant | H133: Medizek 20mg | I133: 90 | J133: 0 | K133: 0 | L133: =J133*I133 -> 0 | M133: =K133*I133 -> 0 | N133: 0 | O133: =N133*I133 -> 0 | P133: =L133-O133 -> 0 | Q133: 0 | R133: 0 | S133: =IFERROR(L133/R133,"-") -> - | T133: 0 | U133: 0 | V133: =T133*I133 -> 0 | W133: =L133-V133 -> 0 | X133: =IFERROR(L133/V133-1,"-") -> - | Y133: =(J133)/1*1.5 -> 0 | Z133: =IF(Y133>K133,Y133-K133,0) -> 0 | AA133: =Z133*I133 -> 0 | AB133: =IF(Y133<K133,K133-Y133,0) -> 0 | AC133: =AB133*I133 -> 0 | AD133: =Y133*I133 -> 0 | AE133: 0
A134: SR Traders, Charsadda | B134: =IFERROR(VLOOKUP(A134,'Distributor List'!$A$2:$D$77,2,0),"-") -> Charsadda | C134: =IFERROR(VLOOKUP(A134,'Distributor List'!$A$2:$D$77,3,0),"-") -> North-1 | D134: =IFERROR(VLOOKUP(A134,'Distributor List'!$A$2:$F$77,6,0),"-") -> Pak-2 | E134: =IFERROR(VLOOKUP(A134,'Distributor List'!$A$2:$D$77,4,0),"-") -> Distributor | F134: =IFERROR(VLOOKUP(H134,'Price List'!$A$2:$H$109,8,0),"-") -> Medicronis | G134: =IFERROR(VLOOKUP(A134,'Distributor List'!$A$2:$E$77,5,0),"-") -> PSW Vacant | H134: Medizek 40mg | I134: 105 | J134: 0 | K134: 0 | L134: =J134*I134 -> 0 | M134: =K134*I134 -> 0 | N134: 0 | O134: =N134*I134 -> 0 | P134: =L134-O134 -> 0 | Q134: 0 | R134: 0 | S134: =IFERROR(L134/R134,"-") -> - | T134: 0 | U134: 0 | V134: =T134*I134 -> 0 | W134: =L134-V134 -> 0 | X134: =IFERROR(L134/V134-1,"-") -> - | Y134: =(J134)/1*1.5 -> 0 | Z134: =IF(Y134>K134,Y134-K134,0) -> 0 | AA134: =Z134*I134 -> 0 | AB134: =IF(Y134<K134,K134-Y134,0) -> 0 | AC134: =AB134*I134 -> 0 | AD134: =Y134*I134 -> 0 | AE134: 0
A135: SR Traders, Charsadda | B135: =IFERROR(VLOOKUP(A135,'Distributor List'!$A$2:$D$77,2,0),"-") -> Charsadda | C135: =IFERROR(VLOOKUP(A135,'Distributor List'!$A$2:$D$77,3,0),"-") -> North-1 | D135: =IFERROR(VLOOKUP(A135,'Distributor List'!$A$2:$F$77,6,0),"-") -> Pak-2 | E135: =IFERROR(VLOOKUP(A135,'Distributor List'!$A$2:$D$77,4,0),"-") -> Distributor | F135: =IFERROR(VLOOKUP(H135,'Price List'!$A$2:$H$109,8,0),"-") -> Medicronis | G135: =IFERROR(VLOOKUP(A135,'Distributor List'!$A$2:$E$77,5,0),"-") -> PSW Vacant | H135: Medizek INJ | I135: 120 | J135: 0 | K135: 0 | L135: =J135*I135 -> 0 | M135: =K135*I135 -> 0 | N135: 0 | O135: =N135*I135 -> 0 | P135: =L135-O135 -> 0 | Q135: 0 | R135: 0 | S135: =IFERROR(L135/R135,"-") -> - | T135: 0 | U135: 0 | V135: =T135*I135 -> 0 | W135: =L135-V135 -> 0 | X135: =IFERROR(L135/V135-1,"-") -> - | Y135: =(J135)/1*1.5 -> 0 | Z135: =IF(Y135>K135,Y135-K135,0) -> 0 | AA135: =Z135*I135 -> 0 | AB135: =IF(Y135<K135,K135-Y135,0) -> 0 | AC135: =AB135*I135 -> 0 | AD135: =Y135*I135 -> 0 | AE135: 0
A136: SR Traders, Charsadda | B136: =IFERROR(VLOOKUP(A136,'Distributor List'!$A$2:$D$77,2,0),"-") -> Charsadda | C136: =IFERROR(VLOOKUP(A136,'Distributor List'!$A$2:$D$77,3,0),"-") -> North-1 | D136: =IFERROR(VLOOKUP(A136,'Distributor List'!$A$2:$F$77,6,0),"-") -> Pak-2 | E136: =IFERROR(VLOOKUP(A136,'Distributor List'!$A$2:$D$77,4,0),"-") -> Distributor | F136: =IFERROR(VLOOKUP(H136,'Price List'!$A$2:$H$109,8,0),"-") -> Medicronis | G136: =IFERROR(VLOOKUP(A136,'Distributor List'!$A$2:$E$77,5,0),"-") -> PSW Vacant | H136: Medelac Syp 120ml | I136: 105 | J136: 0 | K136: 80 | L136: =J136*I136 -> 0 | M136: =K136*I136 -> 8400 | N136: 0 | O136: =N136*I136 -> 0 | P136: =L136-O136 -> 0 | Q136: 50 | R136: =Q136*I136 -> 5250 | S136: =IFERROR(L136/R136,"-") -> 0 | T136: 0 | U136: =J136-T136 -> 0 | V136: =T136*I136 -> 0 | W136: =L136-V136 -> 0 | X136: =IFERROR(L136/V136-1,"-") -> - | Y136: =(J136)/1*1.5 -> 0 | Z136: =IF(Y136>K136,Y136-K136,0) -> 0 | AA136: =Z136*I136 -> 0 | AB136: =IF(Y136<K136,K136-Y136,0) -> 80 | AC136: =AB136*I136 -> 8400 | AD136: =Y136*I136 -> 0 | AE136: 0
A137: SR Traders, Charsadda | B137: =IFERROR(VLOOKUP(A137,'Distributor List'!$A$2:$D$77,2,0),"-") -> Charsadda | C137: =IFERROR(VLOOKUP(A137,'Distributor List'!$A$2:$D$77,3,0),"-") -> North-1 | D137: =IFERROR(VLOOKUP(A137,'Distributor List'!$A$2:$F$77,6,0),"-") -> Pak-2 | E137: =IFERROR(VLOOKUP(A137,'Distributor List'!$A$2:$D$77,4,0),"-") -> Distributor | F137: =IFERROR(VLOOKUP(H137,'Price List'!$A$2:$H$109,8,0),"-") -> Medicronis | G137: =IFERROR(VLOOKUP(A137,'Distributor List'!$A$2:$E$77,5,0),"-") -> PSW Vacant | H137: Paxcal Tab 20's | I137: 170 | J137: 0 | K137: 70 | L137: =J137*I137 -> 0 | M137: =K137*I137 -> 11900 | N137: 0 | O137: =N137*I137 -> 0 | P137: =L137-O137 -> 0 | Q137: 50 | R137: =Q137*I137 -> 8500 | S137: =IFERROR(L137/R137,"-") -> 0 | T137: 0 | U137: =J137-T137 -> 0 | V137: =T137*I137 -> 0 | W137: =L137-V137 -> 0 | X137: =IFERROR(L137/V137-1,"-") -> - | Y137: =(J137)/1*1.5 -> 0 | Z137: =IF(Y137>K137,Y137-K137,0) -> 0 | AA137: =Z137*I137 -> 0 | AB137: =IF(Y137<K137,K137-Y137,0) -> 70 | AC137: =AB137*I137 -> 11900 | AD137: =Y137*I137 -> 0 | AE137: 0
A138: SR Traders, Charsadda | B138: =IFERROR(VLOOKUP(A138,'Distributor List'!$A$2:$D$77,2,0),"-") -> Charsadda | C138: =IFERROR(VLOOKUP(A138,'Distributor List'!$A$2:$D$77,3,0),"-") -> North-1 | D138: =IFERROR(VLOOKUP(A138,'Distributor List'!$A$2:$F$77,6,0),"-") -> Pak-2 | E138: =IFERROR(VLOOKUP(A138,'Distributor List'!$A$2:$D$77,4,0),"-") -> Distributor | F138: =IFERROR(VLOOKUP(H138,'Price List'!$A$2:$H$109,8,0),"-") -> Medicronis | G138: =IFERROR(VLOOKUP(A138,'Distributor List'!$A$2:$E$77,5,0),"-") -> PSW Vacant | H138: V-Fol 400mcg | I138: 120 | J138: 0 | K138: 5 | L138: =J138*I138 -> 0 | M138: =K138*I138 -> 600 | N138: 0 | O138: =N138*I138 -> 0 | P138: =L138-O138 -> 0 | Q138: 54 | R138: =Q138*I138 -> 6480 | S138: =IFERROR(L138/R138,"-") -> 0 | T138: 0 | U138: =J138-T138 -> 0 | V138: =T138*I138 -> 0 | W138: =L138-V138 -> 0 | X138: =IFERROR(L138/V138-1,"-") -> - | Y138: =(J138)/1*1.5 -> 0 | Z138: =IF(Y138>K138,Y138-K138,0) -> 0 | AA138: =Z138*I138 -> 0 | AB138: =IF(Y138<K138,K138-Y138,0) -> 5 | AC138: =AB138*I138 -> 600 | AD138: =Y138*I138 -> 0 | AE138: 0
A139: Noor Khan Corporation, Mingora | B139: =IFERROR(VLOOKUP(A139,'Distributor List'!$A$2:$D$77,2,0),"-") -> Mingora | C139: =IFERROR(VLOOKUP(A139,'Distributor List'!$A$2:$D$77,3,0),"-") -> North-2 | D139: =IFERROR(VLOOKUP(A139,'Distributor List'!$A$2:$F$77,6,0),"-") -> Pak-2 | E139: =IFERROR(VLOOKUP(A139,'Distributor List'!$A$2:$D$77,4,0),"-") -> Distributor | F139: =IFERROR(VLOOKUP(H139,'Price List'!$A$2:$H$109,8,0),"-") -> Medicronis | G139: =IFERROR(VLOOKUP(A139,'Distributor List'!$A$2:$E$77,5,0),"-") -> Rooh Ul Ameen | H139: Novagen 250mg | I139: 60 | J139: 30 | K139: 438 | L139: =J139*I139 -> 1800 | M139: =K139*I139 -> 26280 | N139: 30 | O139: =N139*I139 -> 1800 | P139: =L139-O139 -> 0 | Q139: 181.6 | R139: =Q139*I139 -> 10896 | S139: =IFERROR(L139/R139,"-") -> 0.16519824 | T139: 40 | U139: =J139-T139 -> -10 | V139: =T139*I139 -> 2400 | W139: =L139-V139 -> -600 | X139: =IFERROR(L139/V139-1,"-") -> -0.25 | Y139: =(J139)/1*1.5 -> 45 | Z139: =IF(Y139>K139,Y139-K139,0) -> 0 | AA139: =Z139*I139 -> 0 | AB139: =IF(Y139<K139,K139-Y139,0) -> 393 | AC139: =AB139*I139 -> 23580 | AD139: =Y139*I139 -> 2700 | AE139: 13
A140: Noor Khan Corporation, Mingora | B140: =IFERROR(VLOOKUP(A140,'Distributor List'!$A$2:$D$77,2,0),"-") -> Mingora | C140: =IFERROR(VLOOKUP(A140,'Distributor List'!$A$2:$D$77,3,0),"-") -> North-2 | D140: =IFERROR(VLOOKUP(A140,'Distributor List'!$A$2:$F$77,6,0),"-") -> Pak-2 | E140: =IFERROR(VLOOKUP(A140,'Distributor List'!$A$2:$D$77,4,0),"-") -> Distributor | F140: =IFERROR(VLOOKUP(H140,'Price List'!$A$2:$H$109,8,0),"-") -> Medicronis | G140: =IFERROR(VLOOKUP(A140,'Distributor List'!$A$2:$E$77,5,0),"-") -> Rooh Ul Ameen | H140: Novagen 500mg | I140: 80 | J140: 50 | K140: 418 | L140: =J140*I140 -> 4000 | M140: =K140*I140 -> 33440 | N140: 50 | O140: =N140*I140 -> 4000 | P140: =L140-O140 -> 0 | Q140: 825.12 | R140: =Q140*I140 -> 66009.6 | S140: =IFERROR(L140/R140,"-") -> 0.060597246 | T140: 55 | U140: =J140-T140 -> -5 | V140: =T140*I140 -> 4400 | W140: =L140-V140 -> -400 | X140: =IFERROR(L140/V140-1,"-") -> -0.090909091 | Y140: =(J140)/1*1.5 -> 75 | Z140: =IF(Y140>K140,Y140-K140,0) -> 0 | AA140: =Z140*I140 -> 0 | AB140: =IF(Y140<K140,K140-Y140,0) -> 343 | AC140: =AB140*I140 -> 27440 | AD140: =Y140*I140 -> 6000 | AE140: 14
A141: Noor Khan Corporation, Mingora | B141: =IFERROR(VLOOKUP(A141,'Distributor List'!$A$2:$D$77,2,0),"-") -> Mingora | C141: =IFERROR(VLOOKUP(A141,'Distributor List'!$A$2:$D$77,3,0),"-") -> North-2 | D141: =IFERROR(VLOOKUP(A141,'Distributor List'!$A$2:$F$77,6,0),"-") -> Pak-2 | E141: =IFERROR(VLOOKUP(A141,'Distributor List'!$A$2:$D$77,4,0),"-") -> Distributor | F141: =IFERROR(VLOOKUP(H141,'Price List'!$A$2:$H$109,8,0),"-") -> Medicronis | G141: =IFERROR(VLOOKUP(A141,'Distributor List'!$A$2:$E$77,5,0),"-") -> Rooh Ul Ameen | H141: Novagen 1g | I141: 105 | J141: 485 | K141: 347 | L141: =J141*I141 -> 50925 | M141: =K141*I141 -> 36435 | N141: 485 | O141: =N141*I141 -> 50925 | P141: =L141-O141 -> 0 | Q141: 1235.43 | R141: =Q141*I141 -> 129720.15 | S141: =IFERROR(L141/R141,"-") -> 0.39257586 | T141: 385 | U141: =J141-T141 -> 100 | V141: =T141*I141 -> 40425 | W141: =L141-V141 -> 10500 | X141: =IFERROR(L141/V141-1,"-") -> 0.25974026 | Y141: =(J141)/1*1.5 -> 727.5 | Z141: =IF(Y141>K141,Y141-K141,0) -> 380.5 | AA141: =Z141*I141 -> 39952.5 | AB141: =IF(Y141<K141,K141-Y141,0) -> 0 | AC141: =AB141*I141 -> 0 | AD141: =Y141*I141 -> 76387.5 | AE141: 15
A142: Noor Khan Corporation, Mingora | B142: =IFERROR(VLOOKUP(A142,'Distributor List'!$A$2:$D$77,2,0),"-") -> Mingora | C142: =IFERROR(VLOOKUP(A142,'Distributor List'!$A$2:$D$77,3,0),"-") -> North-2 | D142: =IFERROR(VLOOKUP(A142,'Distributor List'!$A$2:$F$77,6,0),"-") -> Pak-2 | E142: =IFERROR(VLOOKUP(A142,'Distributor List'!$A$2:$D$77,4,0),"-") -> Distributor | F142: =IFERROR(VLOOKUP(H142,'Price List'!$A$2:$H$109,8,0),"-") -> Transformer | G142: =IFERROR(VLOOKUP(A142,'Distributor List'!$A$2:$E$77,5,0),"-") -> Rooh Ul Ameen | H142: Ectafin 1G | I142: 297.5 | J142: 20 | K142: 116 | L142: =J142*I142 -> 5950 | M142: =K142*I142 -> 34510 | N142: 0 | O142: =N142*I142 -> 0 | P142: =L142-O142 -> 5950 | Q142: 125 | R142: =Q142*I142 -> 37187.5 | S142: =IFERROR(L142/R142,"-") -> 0.16 | T142: 0 | U142: =J142-T142 -> 20 | V142: =T142*I142 -> 0 | W142: =L142-V142 -> 5950 | X142: =IFERROR(L142/V142-1,"-") -> - | Y142: =(J142)/1*1.5 -> 30 | Z142: =IF(Y142>K142,Y142-K142,0) -> 0 | AA142: =Z142*I142 -> 0 | AB142: =IF(Y142<K142,K142-Y142,0) -> 86 | AC142: =AB142*I142 -> 25585 | AD142: =Y142*I142 -> 8925 | AE142: 16
A143: Noor Khan Corporation, Mingora | B143: =IFERROR(VLOOKUP(A143,'Distributor List'!$A$2:$D$77,2,0),"-") -> Mingora | C143: =IFERROR(VLOOKUP(A143,'Distributor List'!$A$2:$D$77,3,0),"-") -> North-2 | D143: =IFERROR(VLOOKUP(A143,'Distributor List'!$A$2:$F$77,6,0),"-") -> Pak-2 | E143: =IFERROR(VLOOKUP(A143,'Distributor List'!$A$2:$D$77,4,0),"-") -> Distributor | F143: =IFERROR(VLOOKUP(H143,'Price List'!$A$2:$H$109,8,0),"-") -> Transformer | G143: =IFERROR(VLOOKUP(A143,'Distributor List'!$A$2:$E$77,5,0),"-") -> Rooh Ul Ameen | H143: Ectafin 2G | I143: 429.25 | J143: 20 | K143: 127 | L143: =J143*I143 -> 8585 | M143: =K143*I143 -> 54514.75 | N143: 0 | O143: =N143*I143 -> 0 | P143: =L143-O143 -> 8585 | Q143: 150 | R143: =Q143*I143 -> 64387.5 | S143: =IFERROR(L143/R143,"-") -> 0.13333333 | T143: -10 | U143: =J143-T143 -> 30 | V143: =T143*I143 -> -4292.5 | W143: =L143-V143 -> 12877.5 | X143: =IFERROR(L143/V143-1,"-") -> -3 | Y143: =(J143)/1*1.5 -> 30 | Z143: =IF(Y143>K143,Y143-K143,0) -> 0 | AA143: =Z143*I143 -> 0 | AB143: =IF(Y143<K143,K143-Y143,0) -> 97 | AC143: =AB143*I143 -> 41637.25 | AD143: =Y143*I143 -> 12877.5 | AE143: 17
A144: Noor Khan Corporation, Mingora | B144: =IFERROR(VLOOKUP(A144,'Distributor List'!$A$2:$D$77,2,0),"-") -> Mingora | C144: =IFERROR(VLOOKUP(A144,'Distributor List'!$A$2:$D$77,3,0),"-") -> North-2 | D144: =IFERROR(VLOOKUP(A144,'Distributor List'!$A$2:$F$77,6,0),"-") -> Pak-2 | E144: =IFERROR(VLOOKUP(A144,'Distributor List'!$A$2:$D$77,4,0),"-") -> Distributor | F144: =IFERROR(VLOOKUP(H144,'Price List'!$A$2:$H$109,8,0),"-") -> Medicronis | G144: =IFERROR(VLOOKUP(A144,'Distributor List'!$A$2:$E$77,5,0),"-") -> Rooh Ul Ameen | H144: Lancix Inj. 10s | I144: 270 | J144: 230 | K144: 220 | L144: =J144*I144 -> 62100 | M144: =K144*I144 -> 59400 | N144: 230 | O144: =N144*I144 -> 62100 | P144: =L144-O144 -> 0 | Q144: 425.425 | R144: =Q144*I144 -> 114864.75 | S144: =IFERROR(L144/R144,"-") -> 0.54063583 | T144: 437 | U144: =J144-T144 -> -207 | V144: =T144*I144 -> 117990 | W144: =L144-V144 -> -55890 | X144: =IFERROR(L144/V144-1,"-") -> -0.47368421 | Y144: =(J144)/1*1.5 -> 345 | Z144: =IF(Y144>K144,Y144-K144,0) -> 125 | AA144: =Z144*I144 -> 33750 | AB144: =IF(Y144<K144,K144-Y144,0) -> 0 | AC144: =AB144*I144 -> 0 | AD144: =Y144*I144 -> 93150 | AE144: 18
A145: Noor Khan Corporation, Mingora | B145: =IFERROR(VLOOKUP(A145,'Distributor List'!$A$2:$D$77,2,0),"-") -> Mingora | C145: =IFERROR(VLOOKUP(A145,'Distributor List'!$A$2:$D$77,3,0),"-") -> North-2 | D145: =IFERROR(VLOOKUP(A145,'Distributor List'!$A$2:$F$77,6,0),"-") -> Pak-2 | E145: =IFERROR(VLOOKUP(A145,'Distributor List'!$A$2:$D$77,4,0),"-") -> Distributor | F145: =IFERROR(VLOOKUP(H145,'Price List'!$A$2:$H$109,8,0),"-") -> Medicronis | G145: =IFERROR(VLOOKUP(A145,'Distributor List'!$A$2:$E$77,5,0),"-") -> Rooh Ul Ameen | H145: Lancix Inj. 25s | I145: 670 | J145: 18 | K145: 244 | L145: =J145*I145 -> 12060 | M145: =K145*I145 -> 163480 | N145: 18 | O145: =N145*I145 -> 12060 | P145: =L145-O145 -> 0 | Q145: 167.7375 | R145: =Q145*I145 -> 112384.13 | S145: =IFERROR(L145/R145,"-") -> 0.10731053 | T145: 201 | U145: =J145-T145 -> -183 | V145: =T145*I145 -> 134670 | W145: =L145-V145 -> -122610 | X145: =IFERROR(L145/V145-1,"-") -> -0.91044776 | Y145: =(J145)/1*1.5 -> 27 | Z145: =IF(Y145>K145,Y145-K145,0) -> 0 | AA145: =Z145*I145 -> 0 | AB145: =IF(Y145<K145,K145-Y145,0) -> 217 | AC145: =AB145*I145 -> 145390 | AD145: =Y145*I145 -> 18090 | AE145: 19
A146: Noor Khan Corporation, Mingora | B146: =IFERROR(VLOOKUP(A146,'Distributor List'!$A$2:$D$77,2,0),"-") -> Mingora | C146: =IFERROR(VLOOKUP(A146,'Distributor List'!$A$2:$D$77,3,0),"-") -> North-2 | D146: =IFERROR(VLOOKUP(A146,'Distributor List'!$A$2:$F$77,6,0),"-") -> Pak-2 | E146: =IFERROR(VLOOKUP(A146,'Distributor List'!$A$2:$D$77,4,0),"-") -> Distributor | F146: =IFERROR(VLOOKUP(H146,'Price List'!$A$2:$H$109,8,0),"-") -> Medicronis | G146: =IFERROR(VLOOKUP(A146,'Distributor List'!$A$2:$E$77,5,0),"-") -> Rooh Ul Ameen | H146: G.Tax 250mg | I146: 60 | J146: 20 | K146: 334 | L146: =J146*I146 -> 1200 | M146: =K146*I146 -> 20040 | N146: 20 | O146: =N146*I146 -> 1200 | P146: =L146-O146 -> 0 | Q146: 113.1 | R146: =Q146*I146 -> 6786 | S146: =IFERROR(L146/R146,"-") -> 0.17683466 | T146: 30 | U146: =J146-T146 -> -10 | V146: =T146*I146 -> 1800 | W146: =L146-V146 -> -600 | X146: =IFERROR(L146/V146-1,"-") -> -0.33333333 | Y146: =(J146)/1*1.5 -> 30 | Z146: =IF(Y146>K146,Y146-K146,0) -> 0 | AA146: =Z146*I146 -> 0 | AB146: =IF(Y146<K146,K146-Y146,0) -> 304 | AC146: =AB146*I146 -> 18240 | AD146: =Y146*I146 -> 1800 | AE146: 20
A147: Noor Khan Corporation, Mingora | B147: =IFERROR(VLOOKUP(A147,'Distributor List'!$A$2:$D$77,2,0),"-") -> Mingora | C147: =IFERROR(VLOOKUP(A147,'Distributor List'!$A$2:$D$77,3,0),"-") -> North-2 | D147: =IFERROR(VLOOKUP(A147,'Distributor List'!$A$2:$F$77,6,0),"-") -> Pak-2 | E147: =IFERROR(VLOOKUP(A147,'Distributor List'!$A$2:$D$77,4,0),"-") -> Distributor | F147: =IFERROR(VLOOKUP(H147,'Price List'!$A$2:$H$109,8,0),"-") -> Medicronis | G147: =IFERROR(VLOOKUP(A147,'Distributor List'!$A$2:$E$77,5,0),"-") -> Rooh Ul Ameen | H147: G.Tax 500mg | I147: 76 | J147: 31 | K147: 298 | L147: =J147*I147 -> 2356 | M147: =K147*I147 -> 22648 | N147: 31 | O147: =N147*I147 -> 2356 | P147: =L147-O147 -> 0 | Q147: 114.426 | R147: =Q147*I147 -> 8696.376 | S147: =IFERROR(L147/R147,"-") -> 0.27091745 | T147: 30 | U147: =J147-T147 -> 1 | V147: =T147*I147 -> 2280 | W147: =L147-V147 -> 76 | X147: =IFERROR(L147/V147-1,"-") -> 0.033333333 | Y147: =(J147)/1*1.5 -> 46.5 | Z147: =IF(Y147>K147,Y147-K147,0) -> 0 | AA147: =Z147*I147 -> 0 | AB147: =IF(Y147<K147,K147-Y147,0) -> 251.5 | AC147: =AB147*I147 -> 19114 | AD147: =Y147*I147 -> 3534 | AE147: 21
... A177: Noor Khan Corporation, Mingora | B177: =IFERROR(VLOOKUP(A177,'Distributor List'!$A$2:$D$77,2,0),"-") -> Mingora | C177: =IFERROR(VLOOKUP(A177,'Distributor List'!$A$2:$D$77,3,0),"-") -> North-2 | D177: =IFERROR(VLOOKUP(A177,'Distributor List'!$A$2:$F$77,6,0),"-") -> Pak-2 | E177: =IFERROR(VLOOKUP(A177,'Distributor List'!$A$2:$D$77,4,0),"-") -> Distributor | F177: =IFERROR(VLOOKUP(H177,'Price List'!$A$2:$H$109,8,0),"-") -> Medicronis | G177: =IFERROR(VLOOKUP(A177,'Distributor List'!$A$2:$E$77,5,0),"-") -> Rooh Ul Ameen | H177: Medelac Syp 120ml | I177: 105 | J177: 43 | K177: 89 | L177: =J177*I177 -> 4515 | M177: =K177*I177 -> 9345 | N177: 43 | O177: =N177*I177 -> 4515 | P177: =L177-O177 -> 0 | Q177: 144 | R177: =Q177*I177 -> 15120 | S177: =IFERROR(L177/R177,"-") -> 0.29861111 | T177: 61 | U177: =J177-T177 -> -18 | V177: =T177*I177 -> 6405 | W177: =L177-V177 -> -1890 | X177: =IFERROR(L177/V177-1,"-") -> -0.29508197 | Y177: =(J177)/1*1.5 -> 64.5 | Z177: =IF(Y177>K177,Y177-K177,0) -> 0 | AA177: =Z177*I177 -> 0 | AB177: =IF(Y177<K177,K177-Y177,0) -> 24.5 | AC177: =AB177*I177 -> 2572.5 | AD177: =Y177*I177 -> 6772.5 | AE177: 0
A178: Noor Khan Corporation, Mingora | B178: =IFERROR(VLOOKUP(A178,'Distributor List'!$A$2:$D$77,2,0),"-") -> Mingora | C178: =IFERROR(VLOOKUP(A178,'Distributor List'!$A$2:$D$77,3,0),"-") -> North-2 | D178: =IFERROR(VLOOKUP(A178,'Distributor List'!$A$2:$F$77,6,0),"-") -> Pak-2 | E178: =IFERROR(VLOOKUP(A178,'Distributor List'!$A$2:$D$77,4,0),"-") -> Distributor | F178: =IFERROR(VLOOKUP(H178,'Price List'!$A$2:$H$109,8,0),"-") -> Medicronis | G178: =IFERROR(VLOOKUP(A178,'Distributor List'!$A$2:$E$77,5,0),"-") -> Rooh Ul Ameen | H178: Medizek 20mg | I178: 90 | J178: 40 | K178: 150 | L178: =J178*I178 -> 3600 | M178: =K178*I178 -> 13500 | N178: 40 | O178: =N178*I178 -> 3600 | P178: =L178-O178 -> 0 | Q178: 0 | R178: 0 | S178: =IFERROR(L178/R178,"-") -> - | T178: 0 | U178: 0 | V178: =T178*I178 -> 0 | W178: =L178-V178 -> 3600 | X178: =IFERROR(L178/V178-1,"-") -> - | Y178: =(J178)/1*1.5 -> 60 | Z178: =IF(Y178>K178,Y178-K178,0) -> 0 | AA178: =Z178*I178 -> 0 | AB178: =IF(Y178<K178,K178-Y178,0) -> 90 | AC178: =AB178*I178 -> 8100 | AD178: =Y178*I178 -> 5400 | AE178: 0
A179: Noor Khan Corporation, Mingora | B179: =IFERROR(VLOOKUP(A179,'Distributor List'!$A$2:$D$77,2,0),"-") -> Mingora | C179: =IFERROR(VLOOKUP(A179,'Distributor List'!$A$2:$D$77,3,0),"-") -> North-2 | D179: =IFERROR(VLOOKUP(A179,'Distributor List'!$A$2:$F$77,6,0),"-") -> Pak-2 | E179: =IFERROR(VLOOKUP(A179,'Distributor List'!$A$2:$D$77,4,0),"-") -> Distributor | F179: =IFERROR(VLOOKUP(H179,'Price List'!$A$2:$H$109,8,0),"-") -> Medicronis | G179: =IFERROR(VLOOKUP(A179,'Distributor List'!$A$2:$E$77,5,0),"-") -> Rooh Ul Ameen | H179: Medizek 40mg | I179: 105 | J179: 45 | K179: 145 | L179: =J179*I179 -> 4725 | M179: =K179*I179 -> 15225 | N179: 45 | O179: =N179*I179 -> 4725 | P179: =L179-O179 -> 0 | Q179: 0 | R179: 0 | S179: =IFERROR(L179/R179,"-") -> - | T179: 0 | U179: 0 | V179: =T179*I179 -> 0 | W179: =L179-V179 -> 4725 | X179: =IFERROR(L179/V179-1,"-") -> - | Y179: =(J179)/1*1.5 -> 67.5 | Z179: =IF(Y179>K179,Y179-K179,0) -> 0 | AA179: =Z179*I179 -> 0 | AB179: =IF(Y179<K179,K179-Y179,0) -> 77.5 | AC179: =AB179*I179 -> 8137.5 | AD179: =Y179*I179 -> 7087.5 | AE179: 0
A180: Noor Khan Corporation, Mingora | B180: =IFERROR(VLOOKUP(A180,'Distributor List'!$A$2:$D$77,2,0),"-") -> Mingora | C180: =IFERROR(VLOOKUP(A180,'Distributor List'!$A$2:$D$77,3,0),"-") -> North-2 | D180: =IFERROR(VLOOKUP(A180,'Distributor List'!$A$2:$F$77,6,0),"-") -> Pak-2 | E180: =IFERROR(VLOOKUP(A180,'Distributor List'!$A$2:$D$77,4,0),"-") -> Distributor | F180: =IFERROR(VLOOKUP(H180,'Price List'!$A$2:$H$109,8,0),"-") -> Medicronis | G180: =IFERROR(VLOOKUP(A180,'Distributor List'!$A$2:$E$77,5,0),"-") -> Rooh Ul Ameen | H180: Medizek INJ | I180: 120 | J180: 30 | K180: 50 | L180: =J180*I180 -> 3600 | M180: =K180*I180 -> 6000 | N180: 30 | O180: =N180*I180 -> 3600 | P180: =L180-O180 -> 0 | Q180: 0 | R180: 0 | S180: =IFERROR(L180/R180,"-") -> - | T180: 0 | U180: 0 | V180: =T180*I180 -> 0 | W180: =L180-V180 -> 3600 | X180: =IFERROR(L180/V180-1,"-") -> - | Y180: =(J180)/1*1.5 -> 45 | Z180: =IF(Y180>K180,Y180-K180,0) -> 0 | AA180: =Z180*I180 -> 0 | AB180: =IF(Y180<K180,K180-Y180,0) -> 5 | AC180: =AB180*I180 -> 600 | AD180: =Y180*I180 -> 5400 | AE180: 0
A181: Noor Khan Corporation, Mingora | B181: =IFERROR(VLOOKUP(A181,'Distributor List'!$A$2:$D$77,2,0),"-") -> Mingora | C181: =IFERROR(VLOOKUP(A181,'Distributor List'!$A$2:$D$77,3,0),"-") -> North-2 | D181: =IFERROR(VLOOKUP(A181,'Distributor List'!$A$2:$F$77,6,0),"-") -> Pak-2 | E181: =IFERROR(VLOOKUP(A181,'Distributor List'!$A$2:$D$77,4,0),"-") -> Distributor | F181: =IFERROR(VLOOKUP(H181,'Price List'!$A$2:$H$109,8,0),"-") -> Medicronis | G181: =IFERROR(VLOOKUP(A181,'Distributor List'!$A$2:$E$77,5,0),"-") -> Rooh Ul Ameen | H181: Paxcal Syrup 120ml | I181: 105 | J181: 60 | K181: 45 | L181: =J181*I181 -> 6300 | M181: =K181*I181 -> 4725 | N181: 60 | O181: =N181*I181 -> 6300 | P181: =L181-O181 -> 0 | Q181: 75 | R181: =Q181*I181 -> 7875 | S181: =IFERROR(L181/R181,"-") -> 0.8 | T181: 39 | U181: =J181-T181 -> 21 | V181: =T181*I181 -> 4095 | W181: =L181-V181 -> 2205 | X181: =IFERROR(L181/V181-1,"-") -> 0.53846154 | Y181: =(J181)/1*1.5 -> 90 | Z181: =IF(Y181>K181,Y181-K181,0) -> 45 | AA181: =Z181*I181 -> 4725 | AB181: =IF(Y181<K181,K181-Y181,0) -> 0 | AC181: =AB181*I181 -> 0 | AD181: =Y181*I181 -> 9450 | AE181: 0
A182: Noor Khan Corporation, Mingora | B182: =IFERROR(VLOOKUP(A182,'Distributor List'!$A$2:$D$77,2,0),"-") -> Mingora | C182: =IFERROR(VLOOKUP(A182,'Distributor List'!$A$2:$D$77,3,0),"-") -> North-2 | D182: =IFERROR(VLOOKUP(A182,'Distributor List'!$A$2:$F$77,6,0),"-") -> Pak-2 | E182: =IFERROR(VLOOKUP(A182,'Distributor List'!$A$2:$D$77,4,0),"-") -> Distributor | F182: =IFERROR(VLOOKUP(H182,'Price List'!$A$2:$H$109,8,0),"-") -> Medicronis | G182: =IFERROR(VLOOKUP(A182,'Distributor List'!$A$2:$E$77,5,0),"-") -> Rooh Ul Ameen | H182: Paxcal Tab 20's | I182: 170 | J182: 35 | K182: 91 | L182: =J182*I182 -> 5950 | M182: =K182*I182 -> 15470 | N182: 35 | O182: =N182*I182 -> 5950 | P182: =L182-O182 -> 0 | Q182: 75 | R182: =Q182*I182 -> 12750 | S182: =IFERROR(L182/R182,"-") -> 0.46666667 | T182: 55 | U182: =J182-T182 -> -20 | V182: =T182*I182 -> 9350 | W182: =L182-V182 -> -3400 | X182: =IFERROR(L182/V182-1,"-") -> -0.36363636 | Y182: =(J182)/1*1.5 -> 52.5 | Z182: =IF(Y182>K182,Y182-K182,0) -> 0 | AA182: =Z182*I182 -> 0 | AB182: =IF(Y182<K182,K182-Y182,0) -> 38.5 | AC182: =AB182*I182 -> 6545 | AD182: =Y182*I182 -> 8925 | AE182: 0
A183: Noor Khan Corporation, Mingora | B183: =IFERROR(VLOOKUP(A183,'Distributor List'!$A$2:$D$77,2,0),"-") -> Mingora | C183: =IFERROR(VLOOKUP(A183,'Distributor List'!$A$2:$D$77,3,0),"-") -> North-2 | D183: =IFERROR(VLOOKUP(A183,'Distributor List'!$A$2:$F$77,6,0),"-") -> Pak-2 | E183: =IFERROR(VLOOKUP(A183,'Distributor List'!$A$2:$D$77,4,0),"-") -> Distributor | F183: =IFERROR(VLOOKUP(H183,'Price List'!$A$2:$H$109,8,0),"-") -> Medicronis | G183: =IFERROR(VLOOKUP(A183,'Distributor List'!$A$2:$E$77,5,0),"-") -> Rooh Ul Ameen | H183: V-Fol 400mcg | I183: 120 | J183: 59 | K183: 25 | L183: =J183*I183 -> 7080 | M183: =K183*I183 -> 3000 | N183: 59 | O183: =N183*I183 -> 7080 | P183: =L183-O183 -> 0 | Q183: 129.6 | R183: =Q183*I183 -> 15552 | S183: =IFERROR(L183/R183,"-") -> 0.45524691 | T183: 63 | U183: =J183-T183 -> -4 | V183: =T183*I183 -> 7560 | W183: =L183-V183 -> -480 | X183: =IFERROR(L183/V183-1,"-") -> -0.063492063 | Y183: =(J183)/1*1.5 -> 88.5 | Z183: =IF(Y183>K183,Y183-K183,0) -> 63.5 | AA183: =Z183*I183 -> 7620 | AB183: =IF(Y183<K183,K183-Y183,0) -> 0 | AC183: =AB183*I183 -> 0 | AD183: =Y183*I183 -> 10620 | AE183: 49
A184: Umar Medicine Distribution, Swabi | B184: =IFERROR(VLOOKUP(A184,'Distributor List'!$A$2:$D$77,2,0),"-") -> Swabi | C184: =IFERROR(VLOOKUP(A184,'Distributor List'!$A$2:$D$77,3,0),"-") -> North-1 | D184: =IFERROR(VLOOKUP(A184,'Distributor List'!$A$2:$F$77,6,0),"-") -> Pak-2 | E184: =IFERROR(VLOOKUP(A184,'Distributor List'!$A$2:$D$77,4,0),"-") -> Distributor | F184: =IFERROR(VLOOKUP(H184,'Price List'!$A$2:$H$109,8,0),"-") -> Medicronis | G184: =IFERROR(VLOOKUP(A184,'Distributor List'!$A$2:$E$77,5,0),"-") -> PSW Vacant | H184: Novagen 250mg | I184: 60 | J184: 0 | K184: 159 | L184: =J184*I184 -> 0 | M184: =K184*I184 -> 9540 | N184: 0 | O184: =N184*I184 -> 0 | P184: =L184-O184 -> 0 | Q184: 172.8 | R184: =Q184*I184 -> 10368 | S184: =IFERROR(L184/R184,"-") -> 0 | T184: 0 | U184: =J184-T184 -> 0 | V184: =T184*I184 -> 0 | W184: =L184-V184 -> 0 | X184: =IFERROR(L184/V184-1,"-") -> - | Y184: =(J184)/1*1.5 -> 0 | Z184: =IF(Y184>K184,Y184-K184,0) -> 0 | AA184: =Z184*I184 -> 0 | AB184: =IF(Y184<K184,K184-Y184,0) -> 159 | AC184: =AB184*I184 -> 9540 | AD184: =Y184*I184 -> 0 | AE184: 0
A185: Umar Medicine Distribution, Swabi | B185: =IFERROR(VLOOKUP(A185,'Distributor List'!$A$2:$D$77,2,0),"-") -> Swabi | C185: =IFERROR(VLOOKUP(A185,'Distributor List'!$A$2:$D$77,3,0),"-") -> North-1 | D185: =IFERROR(VLOOKUP(A185,'Distributor List'!$A$2:$F$77,6,0),"-") -> Pak-2 | E185: =IFERROR(VLOOKUP(A185,'Distributor List'!$A$2:$D$77,4,0),"-") -> Distributor | F185: =IFERROR(VLOOKUP(H185,'Price List'!$A$2:$H$109,8,0),"-") -> Medicronis | G185: =IFERROR(VLOOKUP(A185,'Distributor List'!$A$2:$E$77,5,0),"-") -> PSW Vacant | H185: Novagen 500mg | I185: 78 | J185: 0 | K185: 170 | L185: =J185*I185 -> 0 | M185: =K185*I185 -> 13260 | N185: 0 | O185: =N185*I185 -> 0 | P185: =L185-O185 -> 0 | Q185: 414.72 | R185: =Q185*I185 -> 32348.16 | S185: =IFERROR(L185/R185,"-") -> 0 | T185: 0 | U185: =J185-T185 -> 0 | V185: =T185*I185 -> 0 | W185: =L185-V185 -> 0 | X185: =IFERROR(L185/V185-1,"-") -> - | Y185: =(J185)/1*1.5 -> 0 | Z185: =IF(Y185>K185,Y185-K185,0) -> 0 | AA185: =Z185*I185 -> 0 | AB185: =IF(Y185<K185,K185-Y185,0) -> 170 | AC185: =AB185*I185 -> 13260 | AD185: =Y185*I185 -> 0 | AE185: 0
A186: Umar Medicine Distribution, Swabi | B186: =IFERROR(VLOOKUP(A186,'Distributor List'!$A$2:$D$77,2,0),"-") -> Swabi | C186: =IFERROR(VLOOKUP(A186,'Distributor List'!$A$2:$D$77,3,0),"-") -> North-1 | D186: =IFERROR(VLOOKUP(A186,'Distributor List'!$A$2:$F$77,6,0),"-") -> Pak-2 | E186: =IFERROR(VLOOKUP(A186,'Distributor List'!$A$2:$D$77,4,0),"-") -> Distributor | F186: =IFERROR(VLOOKUP(H186,'Price List'!$A$2:$H$109,8,0),"-") -> Medicronis | G186: =IFERROR(VLOOKUP(A186,'Distributor List'!$A$2:$E$77,5,0),"-") -> PSW Vacant | H186: Novagen 1g | I186: 105 | J186: 30 | K186: 230 | L186: =J186*I186 -> 3150 | M186: =K186*I186 -> 24150 | N186: 30 | O186: =N186*I186 -> 3150 | P186: =L186-O186 -> 0 | Q186: 622.08 | R186: =Q186*I186 -> 65318.4 | S186: =IFERROR(L186/R186,"-") -> 0.048225309 | T186: 50 | U186: =J186-T186 -> -20 | V186: =T186*I186 -> 5250 | W186: =L186-V186 -> -2100 | X186: =IFERROR(L186/V186-1,"-") -> -0.4 | Y186: =(J186)/1*1.5 -> 45 | Z186: =IF(Y186>K186,Y186-K186,0) -> 0 | AA186: =Z186*I186 -> 0 | AB186: =IF(Y186<K186,K186-Y186,0) -> 185 | AC186: =AB186*I186 -> 19425 | AD186: =Y186*I186 -> 4725 | AE186: 0
A187: Umar Medicine Distribution, Swabi | B187: =IFERROR(VLOOKUP(A187,'Distributor List'!$A$2:$D$77,2,0),"-") -> Swabi | C187: =IFERROR(VLOOKUP(A187,'Distributor List'!$A$2:$D$77,3,0),"-") -> North-1 | D187: =IFERROR(VLOOKUP(A187,'Distributor List'!$A$2:$F$77,6,0),"-") -> Pak-2 | E187: =IFERROR(VLOOKUP(A187,'Distributor List'!$A$2:$D$77,4,0),"-") -> Distributor | F187: =IFERROR(VLOOKUP(H187,'Price List'!$A$2:$H$109,8,0),"-") -> Transformer | G187: =IFERROR(VLOOKUP(A187,'Distributor List'!$A$2:$E$77,5,0),"-") -> PSW Vacant | H187: Ectafin 1G | I187: 140 | J187: 0 | K187: 51 | L187: =J187*I187 -> 0 | M187: =K187*I187 -> 7140 | N187: 0 | O187: =N187*I187 -> 0 | P187: =L187-O187 -> 0 | Q187: 0 | R187: =Q187*I187 -> 0 | S187: =IFERROR(L187/R187,"-") -> - | T187: 0 | U187: =J187-T187 -> 0 | V187: =T187*I187 -> 0 | W187: =L187-V187 -> 0 | X187: =IFERROR(L187/V187-1,"-") -> - | Y187: =(J187)/1*1.5 -> 0 | Z187: =IF(Y187>K187,Y187-K187,0) -> 0 | AA187: =Z187*I187 -> 0 | AB187: =IF(Y187<K187,K187-Y187,0) -> 51 | AC187: =AB187*I187 -> 7140 | AD187: =Y187*I187 -> 0 | AE187: 0
...

Sheet Price List
A1: Price List
A3: Product Name | B3: Selling Price | C3: Composition | D3: Shipper Size | E3: 10% Dist. Disc. | F3: Net Price | G3: Net With 1% Sales Tax | H3: Group
A4: Pd-Con 150mg | B4: 35 | C4: Fluconazole | D4: 350 | E4: =B4*0.1 -> 3.5 | F4: =B4*90% -> 31.5 | G4: =F4*1%+F4 -> 31.815 | H4: General
A5: Oxaliv 250mg. Tablet | B5: 85 | C5: Levofloxacin | D5: 400 | E5: =B5*0.1 -> 8.5 | F5: =B5*90% -> 76.5 | G5: =F5*1%+F5 -> 77.265 | H5: General
A6: Oxaliv 500mg. Tablet | B6: 130 | C6: Levofloxacin | D6: 400 | E6: =B6*0.1 -> 13 | F6: =B6*90% -> 117 | G6: =F6*1%+F6 -> 118.17 | H6: General
A7: Zamclo 50mg | B7: 45 | C7: Diclofenac Sodium | D7: 400 | E7: =B7*0.1 -> 4.5 | F7: =B7*90% -> 40.5 | G7: =F7*1%+F7 -> 40.905 | H7: General
A8: Mecozam | B8: 180 | C8: Mecobalamin | D8: 216 | E8: =B8*0.1 -> 18 | F8: =B8*90% -> 162 | G8: =F8*1%+F8 -> 163.62 | H8: General
A9: Pd-Kast 10mg Tablet | B9: 70 | C9: Montelukast Sodium | D9: 200 | E9: =B9*0.1 -> 7 | F9: =B9*90% -> 63 | G9: =F9*1%+F9 -> 63.63 | H9: General
A10: Pd-Kast 5mg Tablet | B10: 58 | C10: Montelukast Sodium | D10: 200 | E10: =B10*0.1 -> 5.8 | F10: =B10*90% -> 52.2 | G10: =F10*1%+F10 -> 52.722 | H10: General
A11: Kozivin 250mg Cap 10's | B11: 230 | C11: Azithromycin | D11: 250 | E11: =B11*0.1 -> 23 | F11: =B11*90% -> 207 | G11: =F11*1%+F11 -> 209.07 | H11: General
A12: Kozivin 500mg Tab 6's | B12: 250 | C12: Azithromycin | D12: 250 | E12: =B12*0.1 -> 25 | F12: =B12*90% -> 225 | G12: =F12*1%+F12 -> 227.25 | H12: General
A13: Zamlide 600mg Tab | B13: 400 | C13: Linezolid | D13: 100 | E13: =B13*0.1 -> 40 | F13: =B13*90% -> 360 | G13: =F13*1%+F13 -> 363.6 | H13: General
A14: Zamblin 100mg. Cap | B14: 95 | C14: Pregabalin | D14: 200 | E14: =B14*0.1 -> 9.5 | F14: =B14*90% -> 85.5 | G14: =F14*1%+F14 -> 86.355 | H14: General
A15: Zamblin 50mg. Cap | B15: 72 | C15: Pregabalin | D15: 200 | E15: =B15*0.1 -> 7.2 | F15: =B15*90% -> 64.8 | G15: =F15*1%+F15 -> 65.448 | H15: General
... A33: Appilib Syp 120ml | B33: 80 | C33: Appetizer | D33: 110 | E33: =B33*0.1 -> 8 | F33: =B33*90% -> 72 | G33: =F33*1%+F33 -> 72.72 | H33: General
A34: Gee T.N Ointment | B34: 170 | D34: 200 | E34: =B34*0.1 -> 17 | F34: =B34*90% -> 153 | G34: =F34*1%+F34 -> 154.53 | H34: Medicronis
A35: Gencoff Syp 120ml | B35: 90 | C35: Cough Syp | D35: 110 | E35: =B35*0.1 -> 9 | F35: =B35*90% -> 81 | G35: =F35*1%+F35 -> 81.81 | H35: General
A36: Cranifer Sachet | B36: 99 | C36: Cranberry Sachet | D36: 110 | E36: =B36*0.1 -> 9.9 | F36: =B36*90% -> 89.1 | G36: =F36*1%+F36 -> 89.991 | H36: General
A37: Colimax Drops | B37: 170 | C37: Colic Drops | D37: 180 | E37: =B37*0.1 -> 17 | F37: =B37*90% -> 153 | G37: =F37*1%+F37 -> 154.53 | H37: Transformer
A38: KhaajGo Lotion | B38: 99 | C38: Anti Scabies | D38: 100 | E38: =B38*0.1 -> 9.9 | F38: =B38*90% -> 89.1 | G38: =F38*1%+F38 -> 89.991 | H38: Medicronis
A39: KhaajGo Soap Bar | B39: 120 | C39: Anti Scabies | D39: 100 | E39: =B39*0.1 -> 12 | F39: =B39*90% -> 108 | G39: =F39*1%+F39 -> 109.08 | H39: Medicronis
A40: PeerGo Gel 30g | B40: 110 | C40: Pain Killer Gel | D40: 100 | E40: =B40*0.1 -> 11 | F40: =B40*90% -> 99 | G40: =F40*1%+F40 -> 99.99 | H40: Medicronis
A41: Step In Cream 30g | B41: 140 | C41: Crack Heeling Cream | D41: 100 | E41: =B41*0.1 -> 14 | F41: =B41*90% -> 126 | G41: =F41*1%+F41 -> 127.26 | H41: Medicronis
A42: Nos On Balm 20g | B42: 99 | C42: Balm | D42: 120 | E42: =B42*0.1 -> 9.9 | F42: =B42*90% -> 89.1 | G42: =F42*1%+F42 -> 89.991 | H42: Medicronis
A43: Apivo Syrup 120ml | B43: 80 | C43: Appetizer | D43: 99 | E43: =B43*0.1 -> 8 | F43: =B43*90% -> 72 | G43: =F43*1%+F43 -> 72.72 | H43: Medicronis
A44: Hostenil Syrup 120ml | B44: 90 | C44: Cough Syp | D44: 99 | E44: =B44*0.1 -> 9 | F44: =B44*90% -> 81 | G44: =F44*1%+F44 -> 81.81 | H44: Medicronis
A45: kufxy Syp 120ml | B45: 99 | C45: Cough Syp | D45: 120 | E45: =B45*0.1 -> 9.9 | F45: =B45*90% -> 89.1 | G45: =F45*1%+F45 -> 89.991 | H45: Medicronis
A46: Salberry Sachet 10s | B46: 105 | C46: Cranberry + Vitamin-C | D46: 100 | E46: =B46*0.1 -> 10.5 | F46: =B46*90% -> 94.5 | G46: =F46*1%+F46 -> 95.445 | H46: Medicronis
A47: Berry Flow Sachet | B47: 115 | C47: Cranberry + Vitamin-C | D47: 100 | E47: =B47*0.1 -> 11.5 | F47: =B47*90% -> 103.5 | G47: =F47*1%+F47 -> 104.535 | H47: Medicronis
A48: Clan Plus Syp | B48: 255 | D48: 110 | E48: =B48*0.1 -> 25.5 | F48: =B48*90% -> 229.5 | G48: =F48*1%+F48 -> 231.795 | H48: Transformer
A49: Cipak 200mg/100ml Inf | B49: 99 | C49: Ciprofloxacin | D49: 50 | E49: =B49*0.1 -> 9.9 | F49: =B49*90% -> 89.1 | G49: =F49*1%+F49 -> 89.991 | H49: Medicronis
A50: Medegar Syrup 120ml | B50: 85 | C50: Appetizer | D50: 110 | E50: =B50*0.1 -> 8.5 | F50: =B50*90% -> 76.5 | G50: =F50*1%+F50 -> 77.265 | H50: Medicronis
A51: Maxy 400mg/250ml Inf | B51: 299 | C51: Moxifloxacin | D51: 25 | E51: =B51*0.1 -> 29.9 | F51: =B51*90% -> 269.1 | G51: =F51*1%+F51 -> 271.791 | H51: Transformer
A52: Evox 500mg/100ml Inf | B52: 125 | C52: Levofloxacin | D52: 50 | E52: =B52*0.1 -> 12.5 | F52: =B52*90% -> 112.5 | G52: =F52*1%+F52 -> 113.625 | H52: Transformer
A53: Nida 200mg/100ml Inf | B53: 99 | C53: Metronidazole | D53: 70 | E53: =B53*0.1 -> 9.9 | F53: =B53*90% -> 89.1 | G53: =F53*1%+F53 -> 89.991 | H53: Medicronis
A54: CefPak 250mg Iv Inj | B54: 53 | C54: Ceftriaxone | D54: 192 | E54: =B54*0.1 -> 5.3 | F54: =B54*90% -> 47.7 | G54: =F54*1%+F54 -> 48.177 | H54: Medicronis
A55: CefPak 500mg Iv Inj | B55: 69 | C55: Ceftriaxone | D55: 192 | E55: =B55*0.1 -> 6.9 | F55: =B55*90% -> 62.1 | G55: =F55*1%+F55 -> 62.721 | H55: Medicronis
A56: CefPak 1G Iv Inj | B56: 90 | C56: Ceftriaxone | D56: 192 | E56: =B56*0.1 -> 9 | F56: =B56*90% -> 81 | G56: =F56*1%+F56 -> 81.81 | H56: Medicronis
A57: Paxcal Syrup 120ml | B57: 105 | D57: 110 | E57: =B57*0.1 -> 10.5 | F57: =B57*90% -> 94.5 | G57: =F57*1%+F57 -> 95.445 | H57: Medicronis
A58: Paxcal Tab 20's | B58: 170 | D58: 100 | E58: =B58*0.1 -> 17 | F58: =B58*90% -> 153 | G58: =F58*1%+F58 -> 154.53 | H58: Medicronis
A59: Aminal Plus Syp 120ml | B59: 90 | D59: 110 | E59: =B59*0.1 -> 9 | F59: =B59*90% -> 81 | G59: =F59*1%+F59 -> 81.81 | H59: Medicronis
A60: Mexiron Syp 120ml | B60: 105 | D60: 110 | E60: =B60*0.1 -> 10.5 | F60: =B60*90% -> 94.5 | G60: =F60*1%+F60 -> 95.445 | H60: Medicronis
A61: Medvit Syp 120ml | B61: 105 | D61: 110 | E61: =B61*0.1 -> 10.5 | F61: =B61*90% -> 94.5 | G61: =F61*1%+F61 -> 95.445 | H61: Medicronis
A62: Medelac Syp 120ml | B62: 105 | D62: 110 | E62: =B62*0.1 -> 10.5 | F62: =B62*90% -> 94.5 | G62: =F62*1%+F62 -> 95.445 | H62: Medicronis
A63: Medizek 20mg | B63: 90 | D63: 300 | E63: =B63*0.1 -> 9 | F63: =B63*90% -> 81 | G63: =F63*1%+F63 -> 81.81 | H63: Medicronis
A64: Medizek 40mg | B64: 105 | D64: 300 | E64: =B64*0.1 -> 10.5 | F64: =B64*90% -> 94.5 | G64: =F64*1%+F64 -> 95.445 | H64: Medicronis
A65: Medizek INJ | B65: 120 | D65: 354 | E65: =B65*0.1 -> 12 | F65: =B65*90% -> 108 | G65: =F65*1%+F65 -> 109.08 | H65: Medicronis
A66: Trenmed Tab | B66: 680 | D66: 100 | E66: =B66*0.1 -> 68 | F66: =B66*90% -> 612 | G66: =F66*1%+F66 -> 618.12 | H66: Transformer
A67: Mediscon Syp 120ml | B67: 99 | D67: 50 | E67: 8 | F67: 90 | G67: =F67*1%+F67 -> 90.9 | H67: Medicronis
A68: V-Fol 400mcg | B68: 99 | C68: L-Methylfolate 400mcg | D68: 200 | E68: =B68*0.1 -> 9.9 | F68: =B68*90% -> 89.1 | G68: =F68*1%+F68 -> 89.991 | H68: Medicronis

Sheet Orders
A1: Distributor Name | B1: AIM Pharma, HYD
E2: Medicronis Pharmaceutical (Pvt.) Ltd.
E3: INVENTORY ORDER
E4: =B1 -> AIM Pharma, HYD | L4: 2nd Order Apr-25 | N4: 45771
E5: PRODUCTS | F5: CARTN | G5: NET | H5: Sales | I5: Stock | J5: INVENTORY | K5: STOCK | L5: DEMAND | M5: CARTON | N5: INPUT | O5: FINAL
E6: ALL | F6: ROUND | G6: RATE | H6: 45771 | I6: 45771 | J6: 45 DAYS | K6: TRANSIT | L6: ORDER | M6: SIZE | N6: RTM/FTM | O6: ORDER
E7: Novagen 250mg | F7: 208 | G7: 54.6 | H7: =SUMIFS(DATA!$J$4:$J$5288,DATA!$H$4:$H$5288,$E7,DATA!$A$4:$A$5288,$E$4) -> 0 | I7: =SUMIFS(DATA!$K$4:$K$5288,DATA!$H$4:$H$5288,$E7,DATA!$A$4:$A$5288,$E$4) -> 472 | J7: =(H7)/1*1.5 -> 0 | K7: 0 | L7: =IF(J7>I7+K7,J7-I7-K7,0) -> 0 | M7: =MROUND(L7,F7) -> 0 | N7: 0 | O7: =IF(M7+N7>0,M7+N7,0) -> 0
E8: Novagen 500mg | F8: 208 | G8: 72.8 | H8: =SUMIFS(DATA!$J$4:$J$5288,DATA!$H$4:$H$5288,$E8,DATA!$A$4:$A$5288,$E$4) -> 23 | I8: =SUMIFS(DATA!$K$4:$K$5288,DATA!$H$4:$H$5288,$E8,DATA!$A$4:$A$5288,$E$4) -> 311 | J8: =(H8)/1*1.5 -> 34.5 | K8: 0 | L8: =IF(J8>I8+K8,J8-I8-K8,0) -> 0 | M8: =MROUND(L8,F8) -> 0 | N8: 0 | O8: =IF(M8+N8>0,M8+N8,0) -> 0
E9: Novagen 1g | F9: 208 | G9: 95.55 | H9: =SUMIFS(DATA!$J$4:$J$5288,DATA!$H$4:$H$5288,$E9,DATA!$A$4:$A$5288,$E$4) -> 152 | I9: =SUMIFS(DATA!$K$4:$K$5288,DATA!$H$4:$H$5288,$E9,DATA!$A$4:$A$5288,$E$4) -> 312 | J9: =(H9)/1*1.5 -> 228 | K9: 0 | L9: =IF(J9>I9+K9,J9-I9-K9,0) -> 0 | M9: =MROUND(L9,F9) -> 0 | N9: 0 | O9: =IF(M9+N9>0,M9+N9,0) -> 0
E10: Ectafin 1G | F10: 192 | G10: 355.81 | H10: =SUMIFS(DATA!$J$4:$J$5288,DATA!$H$4:$H$5288,$E10,DATA!$A$4:$A$5288,$E$4) -> 20 | I10: =SUMIFS(DATA!$K$4:$K$5288,DATA!$H$4:$H$5288,$E10,DATA!$A$4:$A$5288,$E$4) -> 53 | J10: =(H10)/1*1.5 -> 30 | K10: 0 | L10: =IF(J10>I10+K10,J10-I10-K10,0) -> 0 | M10: =MROUND(L10,F10) -> 0 | N10: 0 | O10: =IF(M10+N10>0,M10+N10,0) -> 0
E11: Ectafin 2G | F11: 192 | G11: 560.7875 | H11: =SUMIFS(DATA!$J$4:$J$5288,DATA!$H$4:$H$5288,$E11,DATA!$A$4:$A$5288,$E$4) -> 0 | I11: =SUMIFS(DATA!$K$4:$K$5288,DATA!$H$4:$H$5288,$E11,DATA!$A$4:$A$5288,$E$4) -> 47 | J11: =(H11)/1*1.5 -> 0 | K11: 0 | L11: =IF(J11>I11+K11,J11-I11-K11,0) -> 0 | M11: =MROUND(L11,F11) -> 0 | N11: 0 | O11: =IF(M11+N11>0,M11+N11,0) -> 0
E12: Lancix Inj. 10s | F12: 200 | G12: 245.7 | H12: =SUMIFS(DATA!$J$4:$J$5288,DATA!$H$4:$H$5288,$E12,DATA!$A$4:$A$5288,$E$4) -> 13 | I12: =SUMIFS(DATA!$K$4:$K$5288,DATA!$H$4:$H$5288,$E12,DATA!$A$4:$A$5288,$E$4) -> 178 | J12: =(H12)/1*1.5 -> 19.5 | K12: 0 | L12: =IF(J12>I12+K12,J12-I12-K12,0) -> 0 | M12: =MROUND(L12,F12) -> 0 | N12: 0 | O12: =IF(M12+N12>0,M12+N12,0) -> 0
E13: Lancix Inj. 25s | F13: 100 | G13: 609.7 | H13: =SUMIFS(DATA!$J$4:$J$5288,DATA!$H$4:$H$5288,$E13,DATA!$A$4:$A$5288,$E$4) -> 27 | I13: =SUMIFS(DATA!$K$4:$K$5288,DATA!$H$4:$H$5288,$E13,DATA!$A$4:$A$5288,$E$4) -> 13 | J13: =(H13)/1*1.5 -> 40.5 | K13: 0 | L13: =IF(J13>I13+K13,J13-I13-K13,0) -> 27.5 | M13: =MROUND(L13,F13) -> 0 | N13: 0 | O13: =IF(M13+N13>0,M13+N13,0) -> 0
E14: Maxy 400mg/250ml Inf | F14: 25 | G14: 502.775 | H14: =SUMIFS(DATA!$J$4:$J$5288,DATA!$H$4:$H$5288,$E14,DATA!$A$4:$A$5288,$E$4) -> -3 | I14: =SUMIFS(DATA!$K$4:$K$5288,DATA!$H$4:$H$5288,$E14,DATA!$A$4:$A$5288,$E$4) -> 127 | J14: =(H14)/1*1.5 -> -4.5 | K14: 0 | L14: =IF(J14>I14+K14,J14-I14-K14,0) -> 0 | M14: =MROUND(L14,F14) -> 0 | N14: 0 | O14: =IF(M14+N14>0,M14+N14,0) -> 0
E15: Nida 200mg/100ml Inf | F15: 70 | G15: 95.55 | H15: =SUMIFS(DATA!$J$4:$J$5288,DATA!$H$4:$H$5288,$E15,DATA!$A$4:$A$5288,$E$4) -> 448 | I15: =SUMIFS(DATA!$K$4:$K$5288,DATA!$H$4:$H$5288,$E15,DATA!$A$4:$A$5288,$E$4) -> 103 | J15: =(H15)/1*1.5 -> 672 | K15: 0 | L15: =IF(J15>I15+K15,J15-I15-K15,0) -> 569 | M15: =MROUND(L15,F15) -> 560 | N15: 0 | O15: =IF(M15+N15>0,M15+N15,0) -> 560
E16: Cipak 200mg/100ml Inf | F16: 50 | G16: 109.2 | H16: =SUMIFS(DATA!$J$4:$J$5288,DATA!$H$4:$H$5288,$E16,DATA!$A$4:$A$5288,$E$4) -> 13 | I16: =SUMIFS(DATA!$K$4:$K$5288,DATA!$H$4:$H$5288,$E16,DATA!$A$4:$A$5288,$E$4) -> 30 | J16: =(H16)/1*1.5 -> 19.5 | K16: 0 | L16: =IF(J16>I16+K16,J16-I16-K16,0) -> 0 | M16: =MROUND(L16,F16) -> 0 | N16: 0 | O16: =IF(M16+N16>0,M16+N16,0) -> 0
E17: Evox 500mg/100ml Inf | F17: 40 | G17: 367.4125 | H17: =SUMIFS(DATA!$J$4:$J$5288,DATA!$H$4:$H$5288,$E17,DATA!$A$4:$A$5288,$E$4) -> 0 | I17: =SUMIFS(DATA!$K$4:$K$5288,DATA!$H$4:$H$5288,$E17,DATA!$A$4:$A$5288,$E$4) -> 90 | J17: =(H17)/1*1.5 -> 0 | K17: 0 | L17: =IF(J17>I17+K17,J17-I17-K17,0) -> 0 | M17: =MROUND(L17,F17) -> 0 | N17: 0 | O17: =IF(M17+N17>0,M17+N17,0) -> 0
E18: CefPak 250mg iv Inj | F18: 192 | G18: 48.23 | H18: =SUMIFS(DATA!$J$4:$J$5288,DATA!$H$4:$H$5288,$E18,DATA!$A$4:$A$5288,$E$4) -> 0 | I18: =SUMIFS(DATA!$K$4:$K$5288,DATA!$H$4:$H$5288,$E18,DATA!$A$4:$A$5288,$E$4) -> 0 | J18: =(H18)/1*1.5 -> 0 | K18: 0 | L18: =IF(J18>I18+K18,J18-I18-K18,0) -> 0 | M18: =MROUND(L18,F18) -> 0 | N18: 0 | O18: =IF(M18+N18>0,M18+N18,0) -> 0
... E21: Apivo Syrup 120ml | F21: 99 | G21: 77.35 | H21: =SUMIFS(DATA!$J$4:$J$5288,DATA!$H$4:$H$5288,$E21,DATA!$A$4:$A$5288,$E$4) -> 0 | I21: =SUMIFS(DATA!$K$4:$K$5288,DATA!$H$4:$H$5288,$E21,DATA!$A$4:$A$5288,$E$4) -> 3 | J21: =(H21)/1*1.5 -> 0 | K21: 0 | L21: =IF(J21>I21+K21,J21-I21-K21,0) -> 0 | M21: =MROUND(L21,F21) -> 0 | N21: 0 | O21: =IF(M21+N21>0,M21+N21,0) -> 0
E22: Apivo Syrup 120ml | F22: 99 | G22: 0 | H22: 0 | I22: 0 | J22: 0 | K22: 0 | L22: 0 | M22: 0 | N22: 0 | O22: 0
E23: Medegar Syrup 120ml | F23: 110 | G23: 86.45 | H23: =SUMIFS(DATA!$J$4:$J$5288,DATA!$H$4:$H$5288,$E23,DATA!$A$4:$A$5288,$E$4) -> 26 | I23: =SUMIFS(DATA!$K$4:$K$5288,DATA!$H$4:$H$5288,$E23,DATA!$A$4:$A$5288,$E$4) -> 42 | J23: =(H23)/1*1.5 -> 39 | K23: 0 | L23: =IF(J23>I23+K23,J23-I23-K23,0) -> 0 | M23: =MROUND(L23,F23) -> 0 | N23: 0 | O23: =IF(M23+N23>0,M23+N23,0) -> 0
E24: Medegar Syrup 120ml | F24: 110 | G24: 0 | H24: 0 | I24: 0 | J24: 0 | K24: 0 | L24: 0 | M24: 0 | N24: 0 | O24: 0
E25: Hostenil Syrup 120ml | F25: 99 | G25: 81.9 | H25: =SUMIFS(DATA!$J$4:$J$5288,DATA!$H$4:$H$5288,$E25,DATA!$A$4:$A$5288,$E$4) -> 0 | I25: =SUMIFS(DATA!$K$4:$K$5288,DATA!$H$4:$H$5288,$E25,DATA!$A$4:$A$5288,$E$4) -> 1 | J25: =(H25)/1*1.5 -> 0 | K25: 0 | L25: =IF(J25>I25+K25,J25-I25-K25,0) -> 0 | M25: =MROUND(L25,F25) -> 0 | N25: 0 | O25: =IF(M25+N25>0,M25+N25,0) -> 0
E26: Hostenil Syrup 120ml | F26: 99 | G26: 0 | H26: 0 | I26: 0 | J26: 0 | K26: 0 | L26: 0 | M26: 0 | N26: 0 | O26: 0
E27: kufxy Syp 120ml | F27: 100 | G27: 90.09 | H27: =SUMIFS(DATA!$J$4:$J$5288,DATA!$H$4:$H$5288,$E27,DATA!$A$4:$A$5288,$E$4) -> 29 | I27: =SUMIFS(DATA!$K$4:$K$5288,DATA!$H$4:$H$5288,$E27,DATA!$A$4:$A$5288,$E$4) -> 82 | J27: =(H27)/1*1.5 -> 43.5 | K27: 0 | L27: =IF(J27>I27+K27,J27-I27-K27,0) -> 0 | M27: =MROUND(L27,F27) -> 0 | N27: 0 | O27: =IF(M27+N27>0,M27+N27,0) -> 0
E28: kufxy Syp 120ml | F28: 20 | G28: 0 | H28: 0 | I28: 0 | J28: 0 | K28: 0 | L28: 0 | M28: 0 | N28: 0 | O28: 0
E29: Salberry Sachet 10s | F29: 100 | G29: 95.55 | H29: =SUMIFS(DATA!$J$4:$J$5288,DATA!$H$4:$H$5288,$E29,DATA!$A$4:$A$5288,$E$4) -> 0 | I29: =SUMIFS(DATA!$K$4:$K$5288,DATA!$H$4:$H$5288,$E29,DATA!$A$4:$A$5288,$E$4) -> 0 | J29: =(H29)/1*1.5 -> 0 | K29: 0 | L29: =IF(J29>I29+K29,J29-I29-K29,0) -> 0 | M29: =MROUND(L29,F29) -> 0 | N29: 0 | O29: =IF(M29+N29>0,M29+N29,0) -> 0
E30: Berry Flow Sachet | F30: 100 | G30: 104.65 | H30: =SUMIFS(DATA!$J$4:$J$5288,DATA!$H$4:$H$5288,$E30,DATA!$A$4:$A$5288,$E$4) -> 65 | I30: =SUMIFS(DATA!$K$4:$K$5288,DATA!$H$4:$H$5288,$E30,DATA!$A$4:$A$5288,$E$4) -> 8 | J30: =(H30)/1*1.5 -> 97.5 | K30: 0 | L30: =IF(J30>I30+K30,J30-I30-K30,0) -> 89.5 | M30: =MROUND(L30,F30) -> 100 | N30: 0 | O30: =IF(M30+N30>0,M30+N30,0) -> 100
E31: Colimax Drops | F31: 180 | G31: 170.17 | H31: =SUMIFS(DATA!$J$4:$J$5288,DATA!$H$4:$H$5288,$E31,DATA!$A$4:$A$5288,$E$4) -> 20 | I31: =SUMIFS(DATA!$K$4:$K$5288,DATA!$H$4:$H$5288,$E31,DATA!$A$4:$A$5288,$E$4) -> 68 | J31: =(H31)/1*1.5 -> 30 | K31: 0 | L31: =IF(J31>I31+K31,J31-I31-K31,0) -> 0 | M31: =MROUND(L31,F31) -> 0 | N31: 0 | O31: =IF(M31+N31>0,M31+N31,0) -> 0
E32: Colimax Drops | F32: 180 | G32: 0 | H32: 0 | I32: 0 | J32: 0 | K32: 0 | L32: 0 | M32: 0 | N32: 0 | O32: 0
E33: KhaajGo Lotion | F33: 100 | G33: 100.1 | H33: =SUMIFS(DATA!$J$4:$J$5288,DATA!$H$4:$H$5288,$E33,DATA!$A$4:$A$5288,$E$4) -> 30 | I33: =SUMIFS(DATA!$K$4:$K$5288,DATA!$H$4:$H$5288,$E33,DATA!$A$4:$A$5288,$E$4) -> 0 | J33: =(H33)/1*1.5 -> 45 | K33: 0 | L33: =IF(J33>I33+K33,J33-I33-K33,0) -> 45 | M33: =MROUND(L33,F33) -> 0 | N33: 0 | O33: =IF(M33+N33>0,M33+N33,0) -> 0
E34: KhaajGo Soap Bar | F34: 100 | G34: 118.3 | H34: =SUMIFS(DATA!$J$4:$J$5288,DATA!$H$4:$H$5288,$E34,DATA!$A$4:$A$5288,$E$4) -> 31 | I34: =SUMIFS(DATA!$K$4:$K$5288,DATA!$H$4:$H$5288,$E34,DATA!$A$4:$A$5288,$E$4) -> 148 | J34: =(H34)/1*1.5 -> 46.5 | K34: 0 | L34: =IF(J34>I34+K34,J34-I34-K34,0) -> 0 | M34: =MROUND(L34,F34) -> 0 | N34: 0 | O34: =IF(M34+N34>0,M34+N34,0) -> 0
E35: PeerGo Gel 30g | F35: 100 | G35: 109.2 | H35: =SUMIFS(DATA!$J$4:$J$5288,DATA!$H$4:$H$5288,$E35,DATA!$A$4:$A$5288,$E$4) -> 2 | I35: =SUMIFS(DATA!$K$4:$K$5288,DATA!$H$4:$H$5288,$E35,DATA!$A$4:$A$5288,$E$4) -> 0 | J35: =(H35)/1*1.5 -> 3 | K35: 0 | L35: =IF(J35>I35+K35,J35-I35-K35,0) -> 3 | M35: =MROUND(L35,F35) -> 0 | N35: 0 | O35: =IF(M35+N35>0,M35+N35,0) -> 0
E36: Step In Cream 30g | F36: 100 | G36: 136.5 | H36: =SUMIFS(DATA!$J$4:$J$5288,DATA!$H$4:$H$5288,$E36,DATA!$A$4:$A$5288,$E$4) -> 2 | I36: =SUMIFS(DATA!$K$4:$K$5288,DATA!$H$4:$H$5288,$E36,DATA!$A$4:$A$5288,$E$4) -> 82 | J36: =(H36)/1*1.5 -> 3 | K36: 0 | L36: =IF(J36>I36+K36,J36-I36-K36,0) -> 0 | M36: =MROUND(L36,F36) -> 0 | N36: 0 | O36: =IF(M36+N36>0,M36+N36,0) -> 0
E37: Step In Cream 30g | F37: 100 | G37: 0 | H37: 0 | I37: 0 | J37: 0 | K37: 0 | L37: 0 | M37: 0 | N37: 0 | O37: 0
E38: Trenmed Tab | F38: 100 | G38: 618.8 | H38: =SUMIFS(DATA!$J$4:$J$5288,DATA!$H$4:$H$5288,$E38,DATA!$A$4:$A$5288,$E$4) -> 17 | I38: =SUMIFS(DATA!$K$4:$K$5288,DATA!$H$4:$H$5288,$E38,DATA!$A$4:$A$5288,$E$4) -> 13 | J38: =(H38)/1*1.5 -> 25.5 | K38: 0 | L38: =IF(J38>I38+K38,J38-I38-K38,0) -> 12.5 | M38: =MROUND(L38,F38) -> 0 | N38: 0 | O38: =IF(M38+N38>0,M38+N38,0) -> 0
E39: Clan Plus Syp | F39: 110 | G39: 232.05 | H39: =SUMIFS(DATA!$J$4:$J$5288,DATA!$H$4:$H$5288,$E39,DATA!$A$4:$A$5288,$E$4) -> 2 | I39: =SUMIFS(DATA!$K$4:$K$5288,DATA!$H$4:$H$5288,$E39,DATA!$A$4:$A$5288,$E$4) -> 51 | J39: =(H39)/1*1.5 -> 3 | K39: 0 | L39: =IF(J39>I39+K39,J39-I39-K39,0) -> 0 | M39: =MROUND(L39,F39) -> 0 | N39: 0 | O39: =IF(M39+N39>0,M39+N39,0) -> 0
E40: Clan Plus Syp | F40: 110 | G40: 0 | H40: 0 | I40: 0 | J40: 0 | K40: 0 | L40: 0 | M40: 0 | N40: 0 | O40: 0
E41: Gee T.N Ointment | F41: 200 | G41: 163.8 | H41: =SUMIFS(DATA!$J$4:$J$5288,DATA!$H$4:$H$5288,$E41,DATA!$A$4:$A$5288,$E$4) -> 150 | I41: =SUMIFS(DATA!$K$4:$K$5288,DATA!$H$4:$H$5288,$E41,DATA!$A$4:$A$5288,$E$4) -> 0 | J41: =(H41)/1*1.5 -> 225 | K41: 0 | L41: =IF(J41>I41+K41,J41-I41-K41,0) -> 225 | M41: =MROUND(L41,F41) -> 200 | N41: 0 | O41: =IF(M41+N41>0,M41+N41,0) -> 200
E42: Nos On Balm 20g | F42: 200 | G42: 90.09 | H42: =SUMIFS(DATA!$J$4:$J$5288,DATA!$H$4:$H$5288,$E42,DATA!$A$4:$A$5288,$E$4) -> 30 | I42: =SUMIFS(DATA!$K$4:$K$5288,DATA!$H$4:$H$5288,$E42,DATA!$A$4:$A$5288,$E$4) -> 103 | J42: =(H42)/1*1.5 -> 45 | K42: 0 | L42: =IF(J42>I42+K42,J42-I42-K42,0) -> 0 | M42: =MROUND(L42,F42) -> 0 | N42: 0 | O42: =IF(M42+N42>0,M42+N42,0) -> 0
E43: Nos On Balm 20g | F43: 40 | G43: 0 | H43: 0 | I43: 0 | J43: 0 | K43: 0 | L43: 0 | M43: 0 | N43: 0 | O43: =IF(M43+N43>0,M43+N43,0) -> 0
E44: Medvit Syp 120ml | F44: 100 | G44: 100.1 | H44: =SUMIFS(DATA!$J$4:$J$5288,DATA!$H$4:$H$5288,$E44,DATA!$A$4:$A$5288,$E$4) -> 65 | I44: =SUMIFS(DATA!$K$4:$K$5288,DATA!$H$4:$H$5288,$E44,DATA!$A$4:$A$5288,$E$4) -> 16 | J44: =(H44)/1*1.5 -> 97.5 | K44: 0 | L44: =IF(J44>I44+K44,J44-I44-K44,0) -> 81.5 | M44: =MROUND(L44,F44) -> 100 | N44: 0 | O44: =IF(M44+N44>0,M44+N44,0) -> 100
E45: Medvit Syp 120ml | F45: 10 | G45: 0 | H45: 0 | I45: 0 | J45: =(H45)/1*1.5 -> 0 | K45: 0 | L45: =IF(J45>I45+K45,J45-I45-K45,0) -> 0 | M45: =MROUND(L45,F45) -> 0 | N45: 0 | O45: =IF(M45+N45>0,M45+N45,0) -> 0
E46: Mexiron Syp 120ml | F46: 100 | G46: 100.1 | H46: =SUMIFS(DATA!$J$4:$J$5288,DATA!$H$4:$H$5288,$E46,DATA!$A$4:$A$5288,$E$4) -> 85 | I46: =SUMIFS(DATA!$K$4:$K$5288,DATA!$H$4:$H$5288,$E46,DATA!$A$4:$A$5288,$E$4) -> 11 | J46: =(H46)/1*1.5 -> 127.5 | K46: 0 | L46: =IF(J46>I46+K46,J46-I46-K46,0) -> 116.5 | M46: =MROUND(L46,F46) -> 100 | N46: 0 | O46: =IF(M46+N46>0,M46+N46,0) -> 100
E47: Mexiron Syp 120ml | F47: 10 | G47: 0 | H47: 0 | I47: 0 | J47: =(H47)/1*1.5 -> 0 | K47: 0 | L47: =IF(J47>I47+K47,J47-I47-K47,0) -> 0 | M47: =MROUND(L47,F47) -> 0 | N47: 0 | O47: =IF(M47+N47>0,M47+N47,0) -> 0
E48: Medelac Syp 120ml | F48: 100 | G48: 95.55 | H48: =SUMIFS(DATA!$J$4:$J$5288,DATA!$H$4:$H$5288,$E48,DATA!$A$4:$A$5288,$E$4) -> 162 | I48: =SUMIFS(DATA!$K$4:$K$5288,DATA!$H$4:$H$5288,$E48,DATA!$A$4:$A$5288,$E$4) -> 42 | J48: =(H48)/1*1.5 -> 243 | K48: 0 | L48: =IF(J48>I48+K48,J48-I48-K48,0) -> 201 | M48: =MROUND(L48,F48) -> 200 | N48: 0 | O48: =IF(M48+N48>0,M48+N48,0) -> 200
E49: Medelac Syp 120ml | F49: 10 | G49: 0 | H49: 0 | I49: 0 | J49: =(H49)/1*1.5 -> 0 | K49: 0 | L49: =IF(J49>I49+K49,J49-I49-K49,0) -> 0 | M49: =MROUND(L49,F49) -> 0 | N49: 0 | O49: =IF(M49+N49>0,M49+N49,0) -> 0
E50: Aminal Plus Syp 120ml | F50: 100 | G50: 81.9 | H50: =SUMIFS(DATA!$J$4:$J$5288,DATA!$H$4:$H$5288,$E50,DATA!$A$4:$A$5288,$E$4) -> 3 | I50: =SUMIFS(DATA!$K$4:$K$5288,DATA!$H$4:$H$5288,$E50,DATA!$A$4:$A$5288,$E$4) -> 220 | J50: =(H50)/1*1.5 -> 4.5 | K50: 0 | L50: =IF(J50>I50+K50,J50-I50-K50,0) -> 0 | M50: =MROUND(L50,F50) -> 0 | N50: 0 | O50: =IF(M50+N50>0,M50+N50,0) -> 0
E51: Aminal Plus Syp 120ml | F51: 10 | G51: 0 | H51: 0 | I51: 0 | J51: =(H51)/1*1.5 -> 0 | K51: 0 | L51: =IF(J51>I51+K51,J51-I51-K51,0) -> 0 | M51: =MROUND(L51,F51) -> 0 | N51: 0 | O51: =IF(M51+N51>0,M51+N51,0) -> 0
E52: Mediscon Syp 120ml | F52: 50 | G52: 100.1 | H52: =SUMIFS(DATA!$J$4:$J$5288,DATA!$H$4:$H$5288,$E52,DATA!$A$4:$A$5288,$E$4) -> 357 | I52: =SUMIFS(DATA!$K$4:$K$5288,DATA!$H$4:$H$5288,$E52,DATA!$A$4:$A$5288,$E$4) -> 168 | J52: =(H52)/1*1.5 -> 535.5 | K52: 0 | L52: =IF(J52>I52+K52,J52-I52-K52,0) -> 367.5 | M52: =MROUND(L52,F52) -> 350 | N52: 0 | O52: =IF(M52+N52>0,M52+N52,0) -> 350
E53: Mediscon Syp 120ml | F53: 50 | G53: 0 | H53: 0 | I53: 0 | J53: =(H53)/1*1.5 -> 0 | K53: 0 | L53: =IF(J53>I53+K53,J53-I53-K53,0) -> 0 | M53: =MROUND(L53,F53) -> 0 | N53: 0 | O53: =IF(M53+N53>0,M53+N53,0) -> 0
E54: Paxcal Syrup 120ml | F54: 100 | G54: 95.55 | H54: =SUMIFS(DATA!$J$4:$J$5288,DATA!$H$4:$H$5288,$E54,DATA!$A$4:$A$5288,$E$4) -> 8 | I54: =SUMIFS(DATA!$K$4:$K$5288,DATA!$H$4:$H$5288,$E54,DATA!$A$4:$A$5288,$E$4) -> 18 | J54: =(H54)/1*1.5 -> 12 | K54: 0 | L54: =IF(J54>I54+K54,J54-I54-K54,0) -> 0 | M54: =MROUND(L54,F54) -> 0 | N54: 0 | O54: =IF(M54+N54>0,M54+N54,0) -> 0
E55: Paxcal Syrup 120ml | F55: 10 | G55: 0 | H55: 0 | I55: 0 | J55: =(H55)/1*1.5 -> 0 | K55: 0 | L55: =IF(J55>I55+K55,J55-I55-K55,0) -> 0 | M55: =MROUND(L55,F55) -> 0 | N55: 0 | O55: =IF(M55+N55>0,M55+N55,0) -> 0
E56: Paxcal Tab 20's | F56: 100 | G56: 154.7 | H56: =SUMIFS(DATA!$J$4:$J$5288,DATA!$H$4:$H$5288,$E56,DATA!$A$4:$A$5288,$E$4) -> 3 | I56: =SUMIFS(DATA!$K$4:$K$5288,DATA!$H$4:$H$5288,$E56,DATA!$A$4:$A$5288,$E$4) -> 41 | J56: =(H56)/1*1.5 -> 4.5 | K56: 0 | L56: =IF(J56>I56+K56,J56-I56-K56,0) -> 0 | M56: =MROUND(L56,F56) -> 0 | N56: 0 | O56: =IF(M56+N56>0,M56+N56,0) -> 0
E57: V-Fol 400mcg | F57: 200 | G57: 109.2 | H57: =SUMIFS(DATA!$J$4:$J$5288,DATA!$H$4:$H$5288,$E57,DATA!$A$4:$A$5288,$E$4) -> 185 | I57: =SUMIFS(DATA!$K$4:$K$5288,DATA!$H$4:$H$5288,$E57,DATA!$A$4:$A$5288,$E$4) -> 15 | J57: =(H57)/1*1.5 -> 277.5 | K57: 0 | L57: =IF(J57>I57+K57,J57-I57-K57,0) -> 262.5 | M57: =MROUND(L57,F57) -> 200 | N57: 0 | O57: =IF(M57+N57>0,M57+N57,0) -> 200
E58: G.Tax 250mg | F58: 208 | G58: 54.6 | H58: =SUMIFS(DATA!$J$4:$J$5288,DATA!$H$4:$H$5288,$E58,DATA!$A$4:$A$5288,$E$4) -> 0 | I58: =SUMIFS(DATA!$K$4:$K$5288,DATA!$H$4:$H$5288,$E58,DATA!$A$4:$A$5288,$E$4) -> 0 | J58: =(H58)/1*1.5 -> 0 | K58: 0 | L58: =IF(J58>I58+K58,J58-I58-K58,0) -> 0 | M58: =MROUND(L58,F58) -> 0 | N58: 0 | O58: =IF(M58+N58>0,M58+N58,0) -> 0
E59: G.Tax 500mg | F59: 208 | G59: 70.98 | H59: =SUMIFS(DATA!$J$4:$J$5288,DATA!$H$4:$H$5288,$E59,DATA!$A$4:$A$5288,$E$4) -> 0 | I59: =SUMIFS(DATA!$K$4:$K$5288,DATA!$H$4:$H$5288,$E59,DATA!$A$4:$A$5288,$E$4) -> 63 | J59: =(H59)/1*1.5 -> 0 | K59: 0 | L59: =IF(J59>I59+K59,J59-I59-K59,0) -> 0 | M59: =MROUND(L59,F59) -> 0 | N59: 0 | O59: =IF(M59+N59>0,M59+N59,0) -> 0
E60: G.Tax 1G | F60: 208 | G60: 101.92 | H60: =SUMIFS(DATA!$J$4:$J$5288,DATA!$H$4:$H$5288,$E60,DATA!$A$4:$A$5288,$E$4) -> 0 | I60: =SUMIFS(DATA!$K$4:$K$5288,DATA!$H$4:$H$5288,$E60,DATA!$A$4:$A$5288,$E$4) -> 262 | J60: =(H60)/1*1.5 -> 0 | K60: 0 | L60: =IF(J60>I60+K60,J60-I60-K60,0) -> 0 | M60: =MROUND(L60,F60) -> 0 | N60: 0 | O60: =IF(M60+N60>0,M60+N60,0) -> 0
E61: Medizek 20mg | F61: 300 | G61: 81 | H61: =SUMIFS(DATA!$J$4:$J$5288,DATA!$H$4:$H$5288,$E61,DATA!$A$4:$A$5288,$E$4) -> 77 | I61: =SUMIFS(DATA!$K$4:$K$5288,DATA!$H$4:$H$5288,$E61,DATA!$A$4:$A$5288,$E$4) -> 19 | J61: =(H61)/1*1.5 -> 115.5 | K61: 0 | L61: =IF(J61>I61+K61,J61-I61-K61,0) -> 96.5 | M61: =MROUND(L61,F61) -> 0 | N61: 0 | O61: =IF(M61+N61>0,M61+N61,0) -> 0
E62: Medizek 40mg | F62: 300 | G62: 94.5 | H62: =SUMIFS(DATA!$J$4:$J$5288,DATA!$H$4:$H$5288,$E62,DATA!$A$4:$A$5288,$E$4) -> 0 | I62: =SUMIFS(DATA!$K$4:$K$5288,DATA!$H$4:$H$5288,$E62,DATA!$A$4:$A$5288,$E$4) -> 0 | J62: =(H62)/1*1.5 -> 0 | K62: 0 | L62: =IF(J62>I62+K62,J62-I62-K62,0) -> 0 | M62: =MROUND(L62,F62) -> 0 | N62: 0 | O62: =IF(M62+N62>0,M62+N62,0) -> 0
E63: Medizek INJ | F63: 354 | G63: 108 | H63: =SUMIFS(DATA!$J$4:$J$5288,DATA!$H$4:$H$5288,$E63,DATA!$A$4:$A$5288,$E$4) -> 20 | I63: =SUMIFS(DATA!$K$4:$K$5288,DATA!$H$4:$H$5288,$E63,DATA!$A$4:$A$5288,$E$4) -> 22 | J63: =(H63)/1*1.5 -> 30 | K63: 0 | L63: =IF(J63>I63+K63,J63-I63-K63,0) -> 8 | M63: =MROUND(L63,F63) -> 0 | N63: 0 | O63: =IF(M63+N63>0,M63+N63,0) -> 0
E64: G-Sef 125mg Susp 60ml | F64: 100 | G64: 136.5 | H64: =SUMIFS(DATA!$J$4:$J$5288,DATA!$H$4:$H$5288,$E64,DATA!$A$4:$A$5288,$E$4) -> 0 | I64: =SUMIFS(DATA!$K$4:$K$5288,DATA!$H$4:$H$5288,$E64,DATA!$A$4:$A$5288,$E$4) -> 0 | J64: =(H64)/1*1.5 -> 0 | K64: 0 | L64: =IF(J64>I64+K64,J64-I64-K64,0) -> 0 | M64: =MROUND(L64,F64) -> 0 | N64: 0 | O64: =IF(M64+N64>0,M64+N64,0) -> 0
E65: G-Sef 250mg Susp 60ml | F65: 100 | G65: 195.65 | H65: =SUMIFS(DATA!$J$4:$J$5288,DATA!$H$4:$H$5288,$E65,DATA!$A$4:$A$5288,$E$4) -> -10 | I65: =SUMIFS(DATA!$K$4:$K$5288,DATA!$H$4:$H$5288,$E65,DATA!$A$4:$A$5288,$E$4) -> 31 | J65: =(H65)/1*1.5 -> -15 | K65: 0 | L65: =IF(J65>I65+K65,J65-I65-K65,0) -> 0 | M65: =MROUND(L65,F65) -> 0 | N65: 0 | O65: =IF(M65+N65>0,M65+N65,0) -> 0
E66: TOTAL ORDER | H66: =SUMPRODUCT($G$7:$G$65*H7:H65) -> 240518.43 | I66: =SUMPRODUCT($G$7:$G$65*I7:I65) -> 459143.18 | J66: =SUMPRODUCT($G$7:$G$65*J7:J65) -> 360777.65 | K66: =SUMPRODUCT($G$7:$G$65*K7:K65) -> 0 | L66: =SUMPRODUCT($G$7:$G$65*L7:L65) -> 243080.57 | M66: =SUMPRODUCT($G$7:$G$65*M7:M65) -> 192738 | N66: =SUMPRODUCT($G$7:$G$65*N7:N65) -> 0 | O66: =SUMPRODUCT($G$7:$G$65*O7:O65) -> 192738
M67: 9% DISCOUNT | O67: =O66*0.91 -> 175391.58
M68: 1% SALES TAX | O68: =O67*1.01 -> 177145.5
M69: LEDGER BALANCE | O69: 0
M70: NET ORDER VALUE | O70: =O68+O69 -> 177145.5

Sheet Distributor List
A1: Customer | B1: Area | C1: Region | D1: Category | E1: RSM | F1: Country | H1: BUM
A2: AYAN PHARMA, Taunsa | B2: Taunsa | C2: Center-2 | D2: Distributor | E2: DG Khan Vacant | F2: Pak-1 | H2: M Mudassar
A3: AIM Pharma, HYD | B3: Hyderabad | C3: South | D3: Distributor | E3: Farhan Sheikh | F3: Pak-2
A4: AMT International, FSD | B4: Faisalabad | C4: Center-1 | D4: Distributor | E4: FSD Vacant | F4: Pak-1 | H4: Asghar
A5: Ali Pharma, Vehari | B5: Vehari | C5: Center-2 | D5: Distributor | E5: Rehan Hussain | F5: Pak-1 | H5: M Mudassar
A6: AHMAD TRADER, FSD | B6: Faisalabad | C6: Center-1 | D6: Distributor | E6: FSD Vacant | F6: Pak-1 | H6: Asghar
A7: Asim Traders, Loralai | B7: Loralai | C7: South | D7: Distributor | E7: Nasir Pervaiz | F7: Pak-2 | H7: Shahzad Ahmed
A8: Ayyan Medicine Company, SKP | B8: SKP | C8: Center-1 | D8: Distributor | E8: Usama Ashfaq | F8: Pak-1 | H8: Asghar
A9: AL SHIFA DISTRIBUTOR, Jampur | B9: Jampur | C9: Center-2 | D9: Distributor | E9: DG Khan Vacant | F9: Pak-1 | H9: M Mudassar
A10: Al Rehman Medical Sources, Lahore | B10: Lahore | C10: Center-1 | D10: Distributor | E10: Usama Ashfaq | F10: Pak-1 | H10: Asghar
A11: AL-HARAM ENTERPRISES, Kohat | B11: Kohat | C11: North-1 | D11: Distributor | E11: Bannu Vacant | F11: Pak-2 | H11: Mehtab Ali Shah | Q11: 20
A12: ALI DISTRIBUTOR, RYK | B12: R.Y.Khan | C12: Center-2 | D12: Distributor | E12: Rehan Hussain | F12: Pak-1 | H12: M Mudassar
A13: AL Harmain Distribution, D.G Khan | B13: D.G.Khan | C13: Center-2 | D13: Distributor | E13: DG Khan Vacant | F13: Pak-1 | H13: M Mudassar
A14: All Pakistan | B14: National | C14: National | D14: National | E14: National | H14: Sheraz Pervaiz | Q14: -240
A15: AQ DISTRIBUTOR,Sargodha | B15: Sargodha | C15: Center-1 | D15: Distributor | E15: FSD Vacant | F15: Pak-1 | H15: Asghar | Q15: 10
A16: Ayyan Pharma, Rajan Pur | B16: Rajan pur | C16: Center-2 | D16: Distributor | E16: DG Khan Vacant | F16: Pak-1 | H16: M Mudassar
A17: Basher Pharma, Gujranwala | B17: Gujranwala | C17: center-1 | D17: Distributor | E17: Gujranwala Vacant | F17: Pak-1 | H17: Asghar
A18: BINSINA DISTRIBUTOR, BRW | B18: Burewala | C18: Center-2 | D18: Distributor | E18: Rehan Hussain | F18: Pak-1 | H18: M Mudassar
A19: Chishti Pharma, Multan | B19: Multan | C19: Center-2 | D19: Distributor | E19: Rehan Hussain | F19: Pak-1 | H19: M Mudassar
A20: CHAUDHARY MEDICINE COMPANY, MWL | B20: Mianwali | C20: North-1 | D20: Distributor | E20: Bannu Vacant | F20: Pak-2 | H20: Mehtab Ali Shah
A21: Drug Core Distributor, Bannu | B21: Bannu | C21: North-1 | D21: Distributor | E21: Bannu Vacant | F21: Pak-2 | H21: Mehtab Ali Shah
A22: Evergreen Enterprises, D.I.Khan | B22: D.I.Khan | C22: North-1 | D22: Distributor | E22: Bannu Vacant | F22: Pak-2 | H22: Mehtab Ali Shah
A23: Global Pharma, SKP | B23: SKP | C23: Center-1 | D23: Distributor | E23: Usama Ashfaq | F23: Pak-1 | H23: Asghar
A24: Hameed & Sons Medicine, D.I.Khan | B24: D.I.Khan | C24: North-1 | D24: Distributor | E24: Bannu Vacant | F24: Pak-2 | H24: Mehtab Ali Shah
A25: Hashmani Health Care | B25: Karachi | C25: South | D25: Distributor | E25: Farhan Sheikh | F25: Pak-2 | H25: Shahzad Ahmed
A26: HAJI NIZAM UD DIN & SONS, Quetta | B26: Quetta | C26: South | D26: Distributor | E26: Nasir Pervaiz | F26: Pak-2 | H26: Shahzad Ahmed
A27: Hamza Medicine Company, TTS | B27: TTS | C27: Center-1 | D27: Distributor | E27: FSD Vacant | F27: Pak-1 | H27: Asghar
... A39: Noor Khan Corporation, Mingora | B39: Mingora | C39: North-2 | D39: Distributor | E39: Rooh Ul Ameen | F39: Pak-2 | H39: Mehtab Ali Shah
A40: N&G Enterprises, SWL | B40: SWL | C40: Center-1 | D40: Distributor | E40: FSD Vacant | F40: Pak-1 | H40: Asghar | Q40: 20
A41: NEW SHAHZAIB PHARMACY, Okara | B41: Okara | C41: Center-1 | D41: Distributor | E41: FSD Vacant | F41: Pak-1 | H41: Asghar | Q41: 10
A42: Naveed Pharma, Haripur | B42: Haripur | C42: North-2 | D42: Distributor | E42: RWP Vacant | F42: Pak-2 | H42: Mehtab Ali Shah
A43: NEW TAWAKAL ENTERPRISES, ABBT | B43: Abbottabad | C43: North-2 | D43: Distributor | E43: RWP Vacant | F43: Pak-2 | H43: Mehtab Ali Shah | Q43: 9
A44: Al Makkah Trading Co, Buner | B44: Buner | C44: North-2 | D44: Distributor | E44: Rooh Ul Ameen | F44: Pak-2 | H44: Mehtab Ali Shah
A45: Pharmarite Distributor, Jehlum | B45: Jhelum | C45: Center-1 | D45: Distributor | E45: Gujranwala Vacant | F45: Pak-1 | H45: Asghar
A46: Bukhari Medicine Company, MBD | B46: MBD | C46: Center-1 | D46: Distributor | E46: Gujranwala Vacant | F46: Pak-1 | H46: Asghar
A47: PUNJAB MEDICINE COMPANY, Layyah | B47: Layyah | C47: Center-2 | D47: Distributor | E47: DG Khan Vacant | F47: Pak-1 | H47: M Mudassar | Q47: 55
A48: Dost Enterprises, PSW | B48: Peshawar | C48: North-1 | D48: Distributor | E48: PSW Vacant | F48: Pak-2 | H48: Mehtab Ali Shah
A49: Royal Medicine Company, Sadiqabad | B49: Sadiq Abad | C49: Center-2 | D49: Distributor | E49: Rehan Hussain | F49: Pak-1 | H49: M Mudassar
A50: Ruman Medicine, RYK | B50: R.Y.Khan | C50: Center-2 | D50: Distributor | E50: Rehan Hussain | F50: Pak-1 | H50: M Mudassar
A51: REHMAN DRUG AGENCY, SKT | B51: Sialkot | C51: Center-1 | D51: Distributor | E51: Usama Ashfaq | F51: Pak-1 | H51: Asghar
A52: REHMAT PHARMA, Rajanpur | B52: Rajan pur | C52: Center-2 | D52: Whole Saler | E52: DG Khan Vacant | F52: Pak-1 | H52: M Mudassar | Q52: 10
A53: Faiz Enterprises, Rajanpur | B53: Rajan pur | C53: Center-2 | D53: Whole Saler | E53: DG Khan Vacant | F53: Pak-1 | H53: M Mudassar
A54: RELIABLE MEDICOS MIRPURKHAS, MPK | B54: Mirpur Khas | C54: South | D54: Distributor | E54: Farhan Sheikh | F54: Pak-2 | H54: Shahzad Ahmed | Q54: 6
A55: RJ Traders, Badin | B55: Badin | C55: South | D55: Distributor | E55: Farhan Sheikh | F55: Pak-2 | H55: Shahzad Ahmed
A56: Tawakal Enterprises Channel 2, HYD | B56: Hyderabad | C56: South | D56: Distributor | E56: Farhan Sheikh | F56: Pak-2 | H56: Shahzad Ahmed
A57: Hamed Pharma, Bannu | B57: Bannu | C57: North-1 | D57: Distributor | E57: Bannu Vacant | F57: Pak-2 | H57: Mehtab Ali Shah
A58: Hussain Medicose, Shahdadpur | B58: Shahdadpur | C58: South | D58: Distributor | E58: Farhan Sheikh | F58: Pak-2 | H58: Shahzad Ahmed
A59: Umar Medicine Distribution, Swabi | B59: Swabi | C59: North-1 | D59: Distributor | E59: PSW Vacant | F59: Pak-2 | H59: Mehtab Ali Shah
A60: SR Traders, Charsadda | B60: Charsadda | C60: North-1 | D60: Distributor | E60: PSW Vacant | F60: Pak-2 | H60: Mehtab Ali Shah
A61: Steris Pharma, D.I Khan | B61: D.I.Khan | C61: North-1 | D61: Distributor | E61: Bannu Vacant | F61: Pak-2 | H61: Mehtab Ali Shah
A62: SHAFIQ ENTERPRISES, Khanpur | B62: Khanpur | C62: Center-2 | D62: Distributor | E62: Rehan Hussain | F62: Pak-1 | H62: M Mudassar | Q62: 10
A63: THE HAMZA TRADERS, Kasur | B63: Kasur | C63: Center-1 | D63: Distributor | E63: Usama Ashfaq | F63: Pak-1 | H63: Asghar | Q63: -5
A64: Umer Traders, Bannu | B64: Bannu | C64: North-1 | D64: Distributor | E64: Bannu Vacant | F64: Pak-2 | H64: Mehtab Ali Shah
